Workbook
Name Canby_Molalla_Dustin: MGR!$A$212:$O$224
Name Div_2_Wireless: MGR!$A$4:$O$37
Name Stayton_Peoples_Dennis: MGR!#REF!

Sheet MGR
A1: North Sky Manager Review - P&L by Project - June FY27 through Week 2.
A2: Contract Name | B2: Contract # | C2: Former # | D2: Direct Labor Hours | E2: PTD Revenue | F2: PTD Adj Revenue | G2: PTD Costs | H2: PTD Adj Costs | I2: PTD Margin | J2: PTD % | K2: Unbilled (WIP) | L2: Accrued Revenue |$4000+| | M2: Accrued Costs |$4000+| | N2: Profit Center Management Comments | O2: Ross' Comments | P2: JTD Revenue | Q2: JTD Adj Revenue | R2: JTD Costs | S2: JTD Adj Costs | T2: JTD Margin | U2: JTD Margin %
A3: Division 2 - Wireless & Installation
A4: Div 2 - Wireless - Nate
A5: =VLOOKUP(B5,'SAP Contracts'!A:J,10,FALSE) -> American Tower Corporation-WA | B5: =VLOOKUP(C5,'Active North Sky Projects'!C:D,2,FALSE) -> 21171 | C5: 2484115 | D5: =IFERROR(VLOOKUP(B5,'MTD Hours Paste Data'!A:C,3,FALSE),"") -> 55.36 | E5: =IFERROR(VLOOKUP(B5,'ACDOCA - Paste Data'!B:G,6,FALSE),0) -> 10001 | F5: =E5 +L5 -> 10001 | G5: =IFERROR(VLOOKUP(B5,'ACDOCA - Paste Data'!B:H,7,FALSE),0) -> 9014.15 | H5: =G5+M5 -> 9014.15 | I5: =F5-H5 -> 986.85 | J5: =IFERROR(I5/F5,0) -> 0.098675132 | K5: =IFERROR(VLOOKUP(B5,'WIP - Paste Data'!B:E,4,FALSE),"") -> 10001 | P5: =IFERROR(VLOOKUP(B5,'JTD Paste Data'!A:B,2,FALSE),"0") -> 37883.74 | Q5: =SUM(P5+L5) -> 37883.74 | R5: =IFERROR(VLOOKUP(B5,'JTD Paste Data'!A:C,3,FALSE),"0") -> 33776.75 | S5: =SUM(R5+M5) -> 33776.75 | T5: =SUM(Q5-S5) -> 4106.99 | U5: =IFERROR(T5/Q5,0) -> 0.10841036
A6: =VLOOKUP(B6,'SAP Contracts'!A:J,10,FALSE) -> Astound - WA - Drone Work | B6: =VLOOKUP(C6,'Active North Sky Projects'!C:D,2,FALSE) -> 21053 | C6: 2486024 | D6: =IFERROR(VLOOKUP(B6,'MTD Hours Paste Data'!A:C,3,FALSE),"") | E6: =IFERROR(VLOOKUP(B6,'ACDOCA - Paste Data'!B:G,6,FALSE),0) -> 0 | F6: =E6 +L6 -> 0 | G6: =IFERROR(VLOOKUP(B6,'ACDOCA - Paste Data'!B:H,7,FALSE),0) -> 0 | H6: =G6+M6 -> 0 | I6: =F6-H6 -> 0 | J6: =IFERROR(I6/F6,0) -> 0 | K6: =IFERROR(VLOOKUP(B6,'WIP - Paste Data'!B:E,4,FALSE),"") | P6: =IFERROR(VLOOKUP(B6,'JTD Paste Data'!A:B,2,FALSE),"0") -> 6500 | Q6: =SUM(P6+L6) -> 6500 | R6: =IFERROR(VLOOKUP(B6,'JTD Paste Data'!A:C,3,FALSE),"0") -> 4309.11 | S6: =SUM(R6+M6) -> 4309.11 | T6: =SUM(Q6-S6) -> 2190.89 | U6: =IFERROR(T6/Q6,0) -> 0.33706
A7: =VLOOKUP(B7,'SAP Contracts'!A:J,10,FALSE) -> Astound - WA - Lewis River | B7: =VLOOKUP(C7,'Active North Sky Projects'!C:D,2,FALSE) -> 21395 | C7: 2486022 | D7: =IFERROR(VLOOKUP(B7,'MTD Hours Paste Data'!A:C,3,FALSE),"") | E7: =IFERROR(VLOOKUP(B7,'ACDOCA - Paste Data'!B:G,6,FALSE),0) -> 0 | F7: =E7 +L7 -> 0 | G7: =IFERROR(VLOOKUP(B7,'ACDOCA - Paste Data'!B:H,7,FALSE),0) -> 0 | H7: =G7+M7 -> 0 | I7: =F7-H7 -> 0 | J7: =IFERROR(I7/F7,0) -> 0 | K7: =IFERROR(VLOOKUP(B7,'WIP - Paste Data'!B:E,4,FALSE),"") | P7: =IFERROR(VLOOKUP(B7,'JTD Paste Data'!A:B,2,FALSE),"0") -> 121030 | Q7: =SUM(P7+L7) -> 121030 | R7: =IFERROR(VLOOKUP(B7,'JTD Paste Data'!A:C,3,FALSE),"0") -> 94039.27 | S7: =SUM(R7+M7) -> 94039.27 | T7: =SUM(Q7-S7) -> 26990.73 | U7: =IFERROR(T7/Q7,0) -> 0.22300859
A8: =VLOOKUP(B8,'SAP Contracts'!A:J,10,FALSE) -> Astound - WA- Oak Harbor | B8: =VLOOKUP(C8,'Active North Sky Projects'!C:D,2,FALSE) -> 21387 | C8: 2486021 | D8: =IFERROR(VLOOKUP(B8,'MTD Hours Paste Data'!A:C,3,FALSE),"") | E8: =IFERROR(VLOOKUP(B8,'ACDOCA - Paste Data'!B:G,6,FALSE),0) -> 0 | F8: =E8 +L8 -> 0 | G8: =IFERROR(VLOOKUP(B8,'ACDOCA - Paste Data'!B:H,7,FALSE),0) -> 0 | H8: =G8+M8 -> 0 | I8: =F8-H8 -> 0 | J8: =IFERROR(I8/F8,0) -> 0 | K8: =IFERROR(VLOOKUP(B8,'WIP - Paste Data'!B:E,4,FALSE),"") -> 8400 | P8: =IFERROR(VLOOKUP(B8,'JTD Paste Data'!A:B,2,FALSE),"0") -> 8400 | Q8: =SUM(P8+L8) -> 8400 | R8: =IFERROR(VLOOKUP(B8,'JTD Paste Data'!A:C,3,FALSE),"0") -> 6564.52 | S8: =SUM(R8+M8) -> 6564.52 | T8: =SUM(Q8-S8) -> 1835.48 | U8: =IFERROR(T8/Q8,0) -> 0.21850952
A9: =VLOOKUP(B9,'SAP Contracts'!A:J,10,FALSE) -> Colville Tribes - MAT Solar | B9: =VLOOKUP(C9,'Active North Sky Projects'!C:D,2,FALSE) -> 21415 | C9: 2486026 | D9: =IFERROR(VLOOKUP(B9,'MTD Hours Paste Data'!A:C,3,FALSE),"") -> 0 | E9: =IFERROR(VLOOKUP(B9,'ACDOCA - Paste Data'!B:G,6,FALSE),0) -> 307 | F9: =E9 +L9 -> 307 | G9: =IFERROR(VLOOKUP(B9,'ACDOCA - Paste Data'!B:H,7,FALSE),0) -> 402.9 | H9: =G9+M9 -> 402.9 | I9: =F9-H9 -> -95.9 | J9: =IFERROR(I9/F9,0) -> -0.31237785 | K9: =IFERROR(VLOOKUP(B9,'WIP - Paste Data'!B:E,4,FALSE),"") -> 308463 | P9: =IFERROR(VLOOKUP(B9,'JTD Paste Data'!A:B,2,FALSE),"0") -> 308463 | Q9: =SUM(P9+L9) -> 308463 | R9: =IFERROR(VLOOKUP(B9,'JTD Paste Data'!A:C,3,FALSE),"0") -> 318316.45 | S9: =SUM(R9+M9) -> 318316.45 | T9: =SUM(Q9-S9) -> -9853.45 | U9: =IFERROR(T9/Q9,0) -> -0.031943702
A10: =VLOOKUP(B10,'SAP Contracts'!A:J,10,FALSE) -> Colville Tribes - Wireless Maintenance | B10: =VLOOKUP(C10,'Active North Sky Projects'!C:D,2,FALSE) -> 21412 | C10: 2484120 | D10: =IFERROR(VLOOKUP(B10,'MTD Hours Paste Data'!A:C,3,FALSE),"") -> 0 | E10: =IFERROR(VLOOKUP(B10,'ACDOCA - Paste Data'!B:G,6,FALSE),0) -> 0 | F10: =E10 +L10 -> 0 | G10: =IFERROR(VLOOKUP(B10,'ACDOCA - Paste Data'!B:H,7,FALSE),0) -> 0 | H10: =G10+M10 -> 0 | I10: =F10-H10 -> 0 | J10: =IFERROR(I10/F10,0) -> 0 | K10: =IFERROR(VLOOKUP(B10,'WIP - Paste Data'!B:E,4,FALSE),"") -> 1200 | P10: =IFERROR(VLOOKUP(B10,'JTD Paste Data'!A:B,2,FALSE),"0") -> 28840.56 | Q10: =SUM(P10+L10) -> 28840.56 | R10: =IFERROR(VLOOKUP(B10,'JTD Paste Data'!A:C,3,FALSE),"0") -> 23560.93 | S10: =SUM(R10+M10) -> 23560.93 | T10: =SUM(Q10-S10) -> 5279.63 | U10: =IFERROR(T10/Q10,0) -> 0.18306267
A11: =VLOOKUP(B11,'SAP Contracts'!A:J,10,FALSE) -> Colville Tribes - Wireless Sites | B11: =VLOOKUP(C11,'Active North Sky Projects'!C:D,2,FALSE) -> 21407 | C11: 2486025 | D11: =IFERROR(VLOOKUP(B11,'MTD Hours Paste Data'!A:C,3,FALSE),"") -> 338.1 | E11: =IFERROR(VLOOKUP(B11,'ACDOCA - Paste Data'!B:G,6,FALSE),0) -> 115227 | F11: =E11 +L11 -> 115227 | G11: =IFERROR(VLOOKUP(B11,'ACDOCA - Paste Data'!B:H,7,FALSE),0) -> 134086.4 | H11: =G11+M11 -> 134086.4 | I11: =F11-H11 -> -18859.4 | J11: =IFERROR(I11/F11,0) -> -0.16367171 | K11: =IFERROR(VLOOKUP(B11,'WIP - Paste Data'!B:E,4,FALSE),"") -> 524157.86 | P11: =IFERROR(VLOOKUP(B11,'JTD Paste Data'!A:B,2,FALSE),"0") -> 1524157.9 | Q11: =SUM(P11+L11) -> 1524157.9 | R11: =IFERROR(VLOOKUP(B11,'JTD Paste Data'!A:C,3,FALSE),"0") -> 1498782.8 | S11: =SUM(R11+M11) -> 1498782.8 | T11: =SUM(Q11-S11) -> 25375.05 | U11: =IFERROR(T11/Q11,0) -> 0.016648571
A12: =VLOOKUP(B12,'SAP Contracts'!A:J,10,FALSE) -> Crown Castle - ID | B12: =VLOOKUP(C12,'Active North Sky Projects'!C:D,2,FALSE) -> 21191 | C12: 2136014 | D12: =IFERROR(VLOOKUP(B12,'MTD Hours Paste Data'!A:C,3,FALSE),"") -> 0 | E12: =IFERROR(VLOOKUP(B12,'ACDOCA - Paste Data'!B:G,6,FALSE),0) -> 0 | F12: =E12 +L12 -> 0 | G12: =IFERROR(VLOOKUP(B12,'ACDOCA - Paste Data'!B:H,7,FALSE),0) -> 0 | H12: =G12+M12 -> 0 | I12: =F12-H12 -> 0 | J12: =IFERROR(I12/F12,0) -> 0 | K12: =IFERROR(VLOOKUP(B12,'WIP - Paste Data'!B:E,4,FALSE),"") | P12: =IFERROR(VLOOKUP(B12,'JTD Paste Data'!A:B,2,FALSE),"0") -> 14864.2 | Q12: =SUM(P12+L12) -> 14864.2 | R12: =IFERROR(VLOOKUP(B12,'JTD Paste Data'!A:C,3,FALSE),"0") -> 14299.7 | S12: =SUM(R12+M12) -> 14299.7 | T12: =SUM(Q12-S12) -> 564.5 | U12: =IFERROR(T12/Q12,0) -> 0.037977153
A13: =VLOOKUP(B13,'SAP Contracts'!A:J,10,FALSE) -> Spokane Tribe - WA | B13: =VLOOKUP(C13,'Active North Sky Projects'!C:D,2,FALSE) -> 21057 | C13: 2486030 | D13: =IFERROR(VLOOKUP(B13,'MTD Hours Paste Data'!A:C,3,FALSE),"") -> 0 | E13: =IFERROR(VLOOKUP(B13,'ACDOCA - Paste Data'!B:G,6,FALSE),0) -> 0 | F13: =E13 +L13 -> 0 | G13: =IFERROR(VLOOKUP(B13,'ACDOCA - Paste Data'!B:H,7,FALSE),0) -> 0 | H13: =G13+M13 -> 0 | I13: =F13-H13 -> 0 | J13: =IFERROR(I13/F13,0) -> 0 | K13: =IFERROR(VLOOKUP(B13,'WIP - Paste Data'!B:E,4,FALSE),"") -> 24462.22 | P13: =IFERROR(VLOOKUP(B13,'JTD Paste Data'!A:B,2,FALSE),"0") -> 48099.55 | Q13: =SUM(P13+L13) -> 48099.55 | R13: =IFERROR(VLOOKUP(B13,'JTD Paste Data'!A:C,3,FALSE),"0") -> 44805.26 | S13: =SUM(R13+M13) -> 44805.26 | T13: =SUM(Q13-S13) -> 3294.29 | U13: =IFERROR(T13/Q13,0) -> 0.068488998
A14: =VLOOKUP(B14,'SAP Contracts'!A:J,10,FALSE) -> T-Mobile- Eastern OR Market 2025-2026 | B14: =VLOOKUP(C14,'Active North Sky Projects'!C:D,2,FALSE) -> 21288 | C14: 2386051 | D14: =IFERROR(VLOOKUP(B14,'MTD Hours Paste Data'!A:C,3,FALSE),"") -> 0 | E14: =IFERROR(VLOOKUP(B14,'ACDOCA - Paste Data'!B:G,6,FALSE),0) -> 0 | F14: =E14 +L14 -> 0 | G14: =IFERROR(VLOOKUP(B14,'ACDOCA - Paste Data'!B:H,7,FALSE),0) -> 0 | H14: =G14+M14 -> 0 | I14: =F14-H14 -> 0 | J14: =IFERROR(I14/F14,0) -> 0 | K14: =IFERROR(VLOOKUP(B14,'WIP - Paste Data'!B:E,4,FALSE),"") | P14: =IFERROR(VLOOKUP(B14,'JTD Paste Data'!A:B,2,FALSE),"0") -> 77676.8 | Q14: =SUM(P14+L14) -> 77676.8 | R14: =IFERROR(VLOOKUP(B14,'JTD Paste Data'!A:C,3,FALSE),"0") -> 79399.49 | S14: =SUM(R14+M14) -> 79399.49 | T14: =SUM(Q14-S14) -> -1722.69 | U14: =IFERROR(T14/Q14,0) -> -0.022177664
A15: T-Mobile-Eastern OR Market 2026 | B15: 21922 | C15: 2386061 | D15: =IFERROR(VLOOKUP(B15,'MTD Hours Paste Data'!A:C,3,FALSE),"") | E15: =IFERROR(VLOOKUP(B15,'ACDOCA - Paste Data'!B:G,6,FALSE),0) -> 44607.78 | F15: =E15 +L15 -> 44607.78 | G15: =IFERROR(VLOOKUP(B15,'ACDOCA - Paste Data'!B:H,7,FALSE),0) -> 29107.6 | H15: =G15+M15 -> 29107.6 | I15: =F15-H15 -> 15500.18 | J15: =IFERROR(I15/F15,0) -> 0.34747705 | K15: =IFERROR(VLOOKUP(B15,'WIP - Paste Data'!B:E,4,FALSE),"") -> 86609.59 | P15: =IFERROR(VLOOKUP(B15,'JTD Paste Data'!A:B,2,FALSE),"0") -> 144125.82 | Q15: =SUM(P15+L15) -> 144125.82 | R15: =IFERROR(VLOOKUP(B15,'JTD Paste Data'!A:C,3,FALSE),"0") -> 86076.79 | S15: =SUM(R15+M15) -> 86076.79 | T15: =SUM(Q15-S15) -> 58049.03 | U15: =IFERROR(T15/Q15,0) -> 0.40276635
A16: T-Mobile-Idaho Market 2026 | B16: =VLOOKUP(C16,'Active North Sky Projects'!C:D,2,FALSE) -> 21250 | C16: 2136060 | D16: =IFERROR(VLOOKUP(B16,'MTD Hours Paste Data'!A:C,3,FALSE),"") -> 18.01 | E16: =IFERROR(VLOOKUP(B16,'ACDOCA - Paste Data'!B:G,6,FALSE),0) -> 3336 | F16: =E16 +L16 -> 3336 | G16: =IFERROR(VLOOKUP(B16,'ACDOCA - Paste Data'!B:H,7,FALSE),0) -> 2974.03 | H16: =G16+M16 -> 2974.03 | I16: =F16-H16 -> 361.97 | J16: =IFERROR(I16/F16,0) -> 0.1085042 | K16: =IFERROR(VLOOKUP(B16,'WIP - Paste Data'!B:E,4,FALSE),"") -> 3336 | P16: =IFERROR(VLOOKUP(B16,'JTD Paste Data'!A:B,2,FALSE),"0") -> 175988 | Q16: =SUM(P16+L16) -> 175988 | R16: =IFERROR(VLOOKUP(B16,'JTD Paste Data'!A:C,3,FALSE),"0") -> 151343.1 | S16: =SUM(R16+M16) -> 151343.1 | T16: =SUM(Q16-S16) -> 24644.9 | U16: =IFERROR(T16/Q16,0) -> 0.14003739
A17: =VLOOKUP(B17,'SAP Contracts'!A:J,10,FALSE) -> T-Mobile-Idaho Market 2025-2026 | B17: =VLOOKUP(C17,'Active North Sky Projects'!C:D,2,FALSE) -> 21513 | C17: 2136050 | D17: =IFERROR(VLOOKUP(B17,'MTD Hours Paste Data'!A:C,3,FALSE),"") -> 0 | E17: =IFERROR(VLOOKUP(B17,'ACDOCA - Paste Data'!B:G,6,FALSE),0) -> 0 | F17: =E17 +L17 -> 0 | G17: =IFERROR(VLOOKUP(B17,'ACDOCA - Paste Data'!B:H,7,FALSE),0) -> 0 | H17: =G17+M17 -> 0 | I17: =F17-H17 -> 0 | J17: =IFERROR(I17/F17,0) -> 0 | K17: =IFERROR(VLOOKUP(B17,'WIP - Paste Data'!B:E,4,FALSE),"") | P17: =IFERROR(VLOOKUP(B17,'JTD Paste Data'!A:B,2,FALSE),"0") -> 615365.66 | Q17: =SUM(P17+L17) -> 615365.66 | R17: =IFERROR(VLOOKUP(B17,'JTD Paste Data'!A:C,3,FALSE),"0") -> 595218.44 | S17: =SUM(R17+M17) -> 595218.44 | T17: =SUM(Q17-S17) -> 20147.22 | U17: =IFERROR(T17/Q17,0) -> 0.032740241
A18: =VLOOKUP(B18,'SAP Contracts'!A:J,10,FALSE) -> T-Mobile-Portland Market 2024-2025 | B18: =VLOOKUP(C18,'Active North Sky Projects'!C:D,2,FALSE) -> 21223 | C18: 2385009 | D18: =IFERROR(VLOOKUP(B18,'MTD Hours Paste Data'!A:C,3,FALSE),"") | E18: =IFERROR(VLOOKUP(B18,'ACDOCA - Paste Data'!B:G,6,FALSE),0) -> 0 | F18: =E18 +L18 -> 0 | G18: =IFERROR(VLOOKUP(B18,'ACDOCA - Paste Data'!B:H,7,FALSE),0) -> 0 | H18: =G18+M18 -> 0 | I18: =F18-H18 -> 0 | J18: =IFERROR(I18/F18,0) -> 0 | K18: =IFERROR(VLOOKUP(B18,'WIP - Paste Data'!B:E,4,FALSE),"") | P18: =IFERROR(VLOOKUP(B18,'JTD Paste Data'!A:B,2,FALSE),"0") -> 0 | Q18: =SUM(P18+L18) -> 0 | R18: =IFERROR(VLOOKUP(B18,'JTD Paste Data'!A:C,3,FALSE),"0") -> 0 | S18: =SUM(R18+M18) -> 0 | T18: =SUM(Q18-S18) -> 0 | U18: =IFERROR(T18/Q18,0) -> 0
A19: =VLOOKUP(B19,'SAP Contracts'!A:J,10,FALSE) -> T-Mobile-Portland Market 2025-2026 | B19: =VLOOKUP(C19,'Active North Sky Projects'!C:D,2,FALSE) -> 21277 | C19: 2386050 | D19: =IFERROR(VLOOKUP(B19,'MTD Hours Paste Data'!A:C,3,FALSE),"") -> 0 | E19: =IFERROR(VLOOKUP(B19,'ACDOCA - Paste Data'!B:G,6,FALSE),0) -> 0 | F19: =E19 +L19 -> 0 | G19: =IFERROR(VLOOKUP(B19,'ACDOCA - Paste Data'!B:H,7,FALSE),0) -> 0 | H19: =G19+M19 -> 0 | I19: =F19-H19 -> 0 | J19: =IFERROR(I19/F19,0) -> 0 | K19: =IFERROR(VLOOKUP(B19,'WIP - Paste Data'!B:E,4,FALSE),"") -> 16550.89 | P19: =IFERROR(VLOOKUP(B19,'JTD Paste Data'!A:B,2,FALSE),"0") -> 460420.05 | Q19: =SUM(P19+L19) -> 460420.05 | R19: =IFERROR(VLOOKUP(B19,'JTD Paste Data'!A:C,3,FALSE),"0") -> 414578.26 | S19: =SUM(R19+M19) -> 414578.26 | T19: =SUM(Q19-S19) -> 45841.79 | U19: =IFERROR(T19/Q19,0) -> 0.099565147
A20: T-Mobile-Portland Market 2026 | B20: =VLOOKUP(C20,'Active North Sky Projects'!C:D,2,FALSE) -> 21531 | C20: 2386060 | D20: =IFERROR(VLOOKUP(B20,'MTD Hours Paste Data'!A:C,3,FALSE),"") -> 0 | E20: =IFERROR(VLOOKUP(B20,'ACDOCA - Paste Data'!B:G,6,FALSE),0) -> 16846 | F20: =E20 +L20 -> 16846 | G20: =IFERROR(VLOOKUP(B20,'ACDOCA - Paste Data'!B:H,7,FALSE),0) -> 9474.1 | H20: =G20+M20 -> 9474.1 | I20: =F20-H20 -> 7371.9 | J20: =IFERROR(I20/F20,0) -> 0.43760537 | K20: =IFERROR(VLOOKUP(B20,'WIP - Paste Data'!B:E,4,FALSE),"") -> 153342.12 | P20: =IFERROR(VLOOKUP(B20,'JTD Paste Data'!A:B,2,FALSE),"0") -> 415381.62 | Q20: =SUM(P20+L20) -> 415381.62 | R20: =IFERROR(VLOOKUP(B20,'JTD Paste Data'!A:C,3,FALSE),"0") -> 383684.04 | S20: =SUM(R20+M20) -> 383684.04 | T20: =SUM(Q20-S20) -> 31697.58 | U20: =IFERROR(T20/Q20,0) -> 0.076309539
A21: =VLOOKUP(B21,'SAP Contracts'!A:J,10,FALSE) -> T-Mobile-Spokane Market 2025-2026 | B21: =VLOOKUP(C21,'Active North Sky Projects'!C:D,2,FALSE) -> 21159 | C21: 2486051 | D21: =IFERROR(VLOOKUP(B21,'MTD Hours Paste Data'!A:C,3,FALSE),"") -> 0 | E21: =IFERROR(VLOOKUP(B21,'ACDOCA - Paste Data'!B:G,6,FALSE),0) -> 0 | F21: =E21 +L21 -> 0 | G21: =IFERROR(VLOOKUP(B21,'ACDOCA - Paste Data'!B:H,7,FALSE),0) -> 0 | H21: =G21+M21 -> 0 | I21: =F21-H21 -> 0 | J21: =IFERROR(I21/F21,0) -> 0 | K21: =IFERROR(VLOOKUP(B21,'WIP - Paste Data'!B:E,4,FALSE),"") | P21: =IFERROR(VLOOKUP(B21,'JTD Paste Data'!A:B,2,FALSE),"0") -> 606822.98 | Q21: =SUM(P21+L21) -> 606822.98 | R21: =IFERROR(VLOOKUP(B21,'JTD Paste Data'!A:C,3,FALSE),"0") -> 584176.29 | S21: =SUM(R21+M21) -> 584176.29 | T21: =SUM(Q21-S21) -> 22646.69 | U21: =IFERROR(T21/Q21,0) -> 0.037320093
A22: T-Mobile-Spokane Market 2026 | B22: =VLOOKUP(C22,'Active North Sky Projects'!C:D,2,FALSE) -> 21529 | C22: 2486061 | D22: =IFERROR(VLOOKUP(B22,'MTD Hours Paste Data'!A:C,3,FALSE),"") -> 0 | E22: =IFERROR(VLOOKUP(B22,'ACDOCA - Paste Data'!B:G,6,FALSE),0) -> 10124.34 | F22: =E22 +L22 -> 10124.34 | G22: =IFERROR(VLOOKUP(B22,'ACDOCA - Paste Data'!B:H,7,FALSE),0) -> 10718.75 | H22: =G22+M22 -> 10718.75 | I22: =F22-H22 -> -594.41 | J22: =IFERROR(I22/F22,0) -> -0.058710988 | K22: =IFERROR(VLOOKUP(B22,'WIP - Paste Data'!B:E,4,FALSE),"") -> 9165.86 | P22: =IFERROR(VLOOKUP(B22,'JTD Paste Data'!A:B,2,FALSE),"0") -> 338552.68 | Q22: =SUM(P22+L22) -> 338552.68 | R22: =IFERROR(VLOOKUP(B22,'JTD Paste Data'!A:C,3,FALSE),"0") -> 293852.63 | S22: =SUM(R22+M22) -> 293852.63 | T22: =SUM(Q22-S22) -> 44700.05 | U22: =IFERROR(T22/Q22,0) -> 0.13203278
A23: ODOT - Adel Safety Climb | B23: 22025 | C23: N/A | D23: =IFERROR(VLOOKUP(B23,'MTD Hours Paste Data'!A:C,3,FALSE),"") | E23: =IFERROR(VLOOKUP(B23,'ACDOCA - Paste Data'!B:G,6,FALSE),0) -> 0 | F23: =E23 +L23 -> 0 | G23: =IFERROR(VLOOKUP(B23,'ACDOCA - Paste Data'!B:H,7,FALSE),0) -> 0 | H23: =G23+M23 -> 0 | I23: =F23-H23 -> 0 | J23: =IFERROR(I23/F23,0) -> 0 | K23: =IFERROR(VLOOKUP(B23,'WIP - Paste Data'!B:E,4,FALSE),"") | P23: =IFERROR(VLOOKUP(B23,'JTD Paste Data'!A:B,2,FALSE),"0") -> 0 | Q23: =SUM(P23+L23) -> 0 | R23: =IFERROR(VLOOKUP(B23,'JTD Paste Data'!A:C,3,FALSE),"0") -> 1515.55 | S23: =SUM(R23+M23) -> 1515.55 | T23: =SUM(Q23-S23) -> -1515.55 | U23: =IFERROR(T23/Q23,0) -> 0
A24: NSC--StarTouch Short | B24: 21047 | C24: N/A | D24: =IFERROR(VLOOKUP(B24,'MTD Hours Paste Data'!A:C,3,FALSE),"") -> 9.94 | E24: =IFERROR(VLOOKUP(B24,'ACDOCA - Paste Data'!B:G,6,FALSE),0) -> 2750 | F24: =E24 +L24 -> 2750 | G24: =IFERROR(VLOOKUP(B24,'ACDOCA - Paste Data'!B:H,7,FALSE),0) -> 782.42 | H24: =G24+M24 -> 782.42 | I24: =F24-H24 -> 1967.58 | J24: =IFERROR(I24/F24,0) -> 0.71548364 | K24: =IFERROR(VLOOKUP(B24,'WIP - Paste Data'!B:E,4,FALSE),"") -> 2750 | P24: =IFERROR(VLOOKUP(B24,'JTD Paste Data'!A:B,2,FALSE),"0") -> 2750 | Q24: =SUM(P24+L24) -> 2750 | R24: =IFERROR(VLOOKUP(B24,'JTD Paste Data'!A:C,3,FALSE),"0") -> 782.42 | S24: =SUM(R24+M24) -> 782.42 | T24: =SUM(Q24-S24) -> 1967.58 | U24: =IFERROR(T24/Q24,0) -> 0.71548364
A25: VZ-Verizon ID Harvard | B25: 21187 | C25: 2136011 | D25: =IFERROR(VLOOKUP(B25,'MTD Hours Paste Data'!A:C,3,FALSE),"") -> 0 | E25: =IFERROR(VLOOKUP(B25,'ACDOCA - Paste Data'!B:G,6,FALSE),0) -> 0 | F25: =E25 +L25 -> 0 | G25: =IFERROR(VLOOKUP(B25,'ACDOCA - Paste Data'!B:H,7,FALSE),0) -> 0 | H25: =G25+M25 -> 0 | I25: =F25-H25 -> 0 | J25: =IFERROR(I25/F25,0) -> 0 | K25: =IFERROR(VLOOKUP(B25,'WIP - Paste Data'!B:E,4,FALSE),"") -> 13875.74 | P25: =IFERROR(VLOOKUP(B25,'JTD Paste Data'!A:B,2,FALSE),"0") -> 269677.42 | Q25: =SUM(P25+L25) -> 269677.42 | R25: =IFERROR(VLOOKUP(B25,'JTD Paste Data'!A:C,3,FALSE),"0") -> 249220.14 | S25: =SUM(R25+M25) -> 249220.14 | T25: =SUM(Q25-S25) -> 20457.28 | U25: =IFERROR(T25/Q25,0) -> 0.075858335
A26: =VLOOKUP(B26,'SAP Contracts'!A:J,10,FALSE) -> VZ-Verizon ID Careywood | B26: =VLOOKUP(C26,'Active North Sky Projects'!C:D,2,FALSE) -> 21648 | C26: 2136012 | D26: =IFERROR(VLOOKUP(B26,'MTD Hours Paste Data'!A:C,3,FALSE),"") -> 0 | E26: =IFERROR(VLOOKUP(B26,'ACDOCA - Paste Data'!B:G,6,FALSE),0) -> 0 | F26: =E26 +L26 -> 0 | G26: =IFERROR(VLOOKUP(B26,'ACDOCA - Paste Data'!B:H,7,FALSE),0) -> 3198.39 | H26: =G26+M26 -> 3198.39 | I26: =F26-H26 -> -3198.39 | J26: =IFERROR(I26/F26,0) -> 0 | K26: =IFERROR(VLOOKUP(B26,'WIP - Paste Data'!B:E,4,FALSE),"") -> 337431.37 | P26: =IFERROR(VLOOKUP(B26,'JTD Paste Data'!A:B,2,FALSE),"0") -> 337431.37 | Q26: =SUM(P26+L26) -> 337431.37 | R26: =IFERROR(VLOOKUP(B26,'JTD Paste Data'!A:C,3,FALSE),"0") -> 340197.03 | S26: =SUM(R26+M26) -> 340197.03 | T26: =SUM(Q26-S26) -> -2765.66 | U26: =IFERROR(T26/Q26,0) -> -0.0081962148
A27: =VLOOKUP(B27,'SAP Contracts'!A:J,10,FALSE) -> VZ-Verizon Idaho Market (Msa) | B27: =VLOOKUP(C27,'Active North Sky Projects'!C:D,2,FALSE) -> 21643 | C27: 2135002 | D27: =IFERROR(VLOOKUP(B27,'MTD Hours Paste Data'!A:C,3,FALSE),"") -> 55.35 | E27: =IFERROR(VLOOKUP(B27,'ACDOCA - Paste Data'!B:G,6,FALSE),0) -> 1 | F27: =E27 +L27 -> 1 | G27: =IFERROR(VLOOKUP(B27,'ACDOCA - Paste Data'!B:H,7,FALSE),0) -> 4894.27 | H27: =G27+M27 -> 4894.27 | I27: =F27-H27 -> -4893.27 | J27: =IFERROR(I27/F27,0) -> -4893.27 | K27: =IFERROR(VLOOKUP(B27,'WIP - Paste Data'!B:E,4,FALSE),"") -> 138947.03 | P27: =IFERROR(VLOOKUP(B27,'JTD Paste Data'!A:B,2,FALSE),"0") -> 1254903.4 | Q27: =SUM(P27+L27) -> 1254903.4 | R27: =IFERROR(VLOOKUP(B27,'JTD Paste Data'!A:C,3,FALSE),"0") -> 1179314.8 | S27: =SUM(R27+M27) -> 1179314.8 | T27: =SUM(Q27-S27) -> 75588.56 | U27: =IFERROR(T27/Q27,0) -> 0.060234566
A28: =VLOOKUP(B28,'SAP Contracts'!A:J,10,FALSE) -> VZ-Verizon Or Market (MSA) | B28: =VLOOKUP(C28,'Active North Sky Projects'!C:D,2,FALSE) -> 21145 | C28: 2384111 | D28: =IFERROR(VLOOKUP(B28,'MTD Hours Paste Data'!A:C,3,FALSE),"") -> 0 | E28: =IFERROR(VLOOKUP(B28,'ACDOCA - Paste Data'!B:G,6,FALSE),0) -> 0 | F28: =E28 +L28 -> 0 | G28: =IFERROR(VLOOKUP(B28,'ACDOCA - Paste Data'!B:H,7,FALSE),0) -> 0 | H28: =G28+M28 -> 0 | I28: =F28-H28 -> 0 | J28: =IFERROR(I28/F28,0) -> 0 | K28: =IFERROR(VLOOKUP(B28,'WIP - Paste Data'!B:E,4,FALSE),"") -> 77449.54 | P28: =IFERROR(VLOOKUP(B28,'JTD Paste Data'!A:B,2,FALSE),"0") -> 3748513.8 | Q28: =SUM(P28+L28) -> 3748513.8 | R28: =IFERROR(VLOOKUP(B28,'JTD Paste Data'!A:C,3,FALSE),"0") -> 3497940 | S28: =SUM(R28+M28) -> 3497940 | T28: =SUM(Q28-S28) -> 250573.83 | U28: =IFERROR(T28/Q28,0) -> 0.06684618
A29: =VLOOKUP(B29,'SAP Contracts'!A:J,10,FALSE) -> VZ-Verizon Or Mosser | B29: =VLOOKUP(C29,'Active North Sky Projects'!C:D,2,FALSE) -> 21579 | C29: 2384101 | D29: =IFERROR(VLOOKUP(B29,'MTD Hours Paste Data'!A:C,3,FALSE),"") | E29: =IFERROR(VLOOKUP(B29,'ACDOCA - Paste Data'!B:G,6,FALSE),0) -> 0 | F29: =E29 +L29 -> 0 | G29: =IFERROR(VLOOKUP(B29,'ACDOCA - Paste Data'!B:H,7,FALSE),0) -> 0 | H29: =G29+M29 -> 0 | I29: =F29-H29 -> 0 | J29: =IFERROR(I29/F29,0) -> 0 | K29: =IFERROR(VLOOKUP(B29,'WIP - Paste Data'!B:E,4,FALSE),"") -> 6225.64 | P29: =IFERROR(VLOOKUP(B29,'JTD Paste Data'!A:B,2,FALSE),"0") -> 85176.52 | Q29: =SUM(P29+L29) -> 85176.52 | R29: =IFERROR(VLOOKUP(B29,'JTD Paste Data'!A:C,3,FALSE),"0") -> 71641.24 | S29: =SUM(R29+M29) -> 71641.24 | T29: =SUM(Q29-S29) -> 13535.28 | U29: =IFERROR(T29/Q29,0) -> 0.15890858
A30: =VLOOKUP(B30,'SAP Contracts'!A:J,10,FALSE) -> VZ-Verizon OR Ruch | B30: =VLOOKUP(C30,'Active North Sky Projects'!C:D,2,FALSE) -> 21903 | C30: 2387000 | D30: =IFERROR(VLOOKUP(B30,'MTD Hours Paste Data'!A:C,3,FALSE),"") | E30: =IFERROR(VLOOKUP(B30,'ACDOCA - Paste Data'!B:G,6,FALSE),0) -> 2120 | F30: =E30 +L30 -> 2120 | G30: =IFERROR(VLOOKUP(B30,'ACDOCA - Paste Data'!B:H,7,FALSE),0) -> 1558.65 | H30: =G30+M30 -> 1558.65 | I30: =F30-H30 -> 561.35 | J30: =IFERROR(I30/F30,0) -> 0.26478774 | K30: =IFERROR(VLOOKUP(B30,'WIP - Paste Data'!B:E,4,FALSE),"") -> 13622.54 | P30: =IFERROR(VLOOKUP(B30,'JTD Paste Data'!A:B,2,FALSE),"0") -> 51720.16 | Q30: =SUM(P30+L30) -> 51720.16 | R30: =IFERROR(VLOOKUP(B30,'JTD Paste Data'!A:C,3,FALSE),"0") -> 45205.92 | S30: =SUM(R30+M30) -> 45205.92 | T30: =SUM(Q30-S30) -> 6514.24 | U30: =IFERROR(T30/Q30,0) -> 0.12595166
A31: =VLOOKUP(B31,'SAP Contracts'!A:J,10,FALSE) -> VZ-Verizon Spokane Market (MSA) | B31: =VLOOKUP(C31,'Active North Sky Projects'!C:D,2,FALSE) -> 21135 | C31: 2484111 | D31: =IFERROR(VLOOKUP(B31,'MTD Hours Paste Data'!A:C,3,FALSE),"") -> 0 | E31: =IFERROR(VLOOKUP(B31,'ACDOCA - Paste Data'!B:G,6,FALSE),0) -> 0 | F31: =E31 +L31 -> 0 | G31: =IFERROR(VLOOKUP(B31,'ACDOCA - Paste Data'!B:H,7,FALSE),0) -> 0 | H31: =G31+M31 -> 0 | I31: =F31-H31 -> 0 | J31: =IFERROR(I31/F31,0) -> 0 | K31: =IFERROR(VLOOKUP(B31,'WIP - Paste Data'!B:E,4,FALSE),"") -> 88717.35 | P31: =IFERROR(VLOOKUP(B31,'JTD Paste Data'!A:B,2,FALSE),"0") -> 775765.17 | Q31: =SUM(P31+L31) -> 775765.17 | R31: =IFERROR(VLOOKUP(B31,'JTD Paste Data'!A:C,3,FALSE),"0") -> 756555.52 | S31: =SUM(R31+M31) -> 756555.52 | T31: =SUM(Q31-S31) -> 19209.65 | U31: =IFERROR(T31/Q31,0) -> 0.024762197
A32: =VLOOKUP(B32,'SAP Contracts'!A:J,10,FALSE) -> VZ-Verizon Sw Wa Market (MSA) | B32: =VLOOKUP(C32,'Active North Sky Projects'!C:D,2,FALSE) -> 21196 | C32: 2484116 | D32: =IFERROR(VLOOKUP(B32,'MTD Hours Paste Data'!A:C,3,FALSE),"") -> 0 | E32: =IFERROR(VLOOKUP(B32,'ACDOCA - Paste Data'!B:G,6,FALSE),0) -> 1964.41 | F32: =E32 +L32 -> 1964.41 | G32: =IFERROR(VLOOKUP(B32,'ACDOCA - Paste Data'!B:H,7,FALSE),0) -> 2778.31 | H32: =G32+M32 -> 2778.31 | I32: =F32-H32 -> -813.9 | J32: =IFERROR(I32/F32,0) -> -0.41432288 | K32: =IFERROR(VLOOKUP(B32,'WIP - Paste Data'!B:E,4,FALSE),"") -> 1964.41 | P32: =IFERROR(VLOOKUP(B32,'JTD Paste Data'!A:B,2,FALSE),"0") -> 1249465.6 | Q32: =SUM(P32+L32) -> 1249465.6 | R32: =IFERROR(VLOOKUP(B32,'JTD Paste Data'!A:C,3,FALSE),"0") -> 1176895.2 | S32: =SUM(R32+M32) -> 1176895.2 | T32: =SUM(Q32-S32) -> 72570.43 | U32: =IFERROR(T32/Q32,0) -> 0.058081173
A33: =VLOOKUP(B33,'SAP Contracts'!A:J,10,FALSE) -> VZ-Verizon Wa North Colfax | B33: =VLOOKUP(C33,'Active North Sky Projects'!C:D,2,FALSE) -> 21242 | C33: 2485013 | D33: =IFERROR(VLOOKUP(B33,'MTD Hours Paste Data'!A:C,3,FALSE),"") | E33: =IFERROR(VLOOKUP(B33,'ACDOCA - Paste Data'!B:G,6,FALSE),0) -> 0 | F33: =E33 +L33 -> 0 | G33: =IFERROR(VLOOKUP(B33,'ACDOCA - Paste Data'!B:H,7,FALSE),0) -> 0 | H33: =G33+M33 -> 0 | I33: =F33-H33 -> 0 | J33: =IFERROR(I33/F33,0) -> 0 | K33: =IFERROR(VLOOKUP(B33,'WIP - Paste Data'!B:E,4,FALSE),"") -> 6497.5 | P33: =IFERROR(VLOOKUP(B33,'JTD Paste Data'!A:B,2,FALSE),"0") -> 230835.16 | Q33: =SUM(P33+L33) -> 230835.16 | R33: =IFERROR(VLOOKUP(B33,'JTD Paste Data'!A:C,3,FALSE),"0") -> 211644.11 | S33: =SUM(R33+M33) -> 211644.11 | T33: =SUM(Q33-S33) -> 19191.05 | U33: =IFERROR(T33/Q33,0) -> 0.083137465
A34: VZ- Verizon 2026 | B34: 22008 | C34: N/A | D34: =IFERROR(VLOOKUP(B34,'MTD Hours Paste Data'!A:C,3,FALSE),"") | E34: =IFERROR(VLOOKUP(B34,'ACDOCA - Paste Data'!B:G,6,FALSE),0) -> 86853.78 | F34: =E34 +L34 -> 86853.78 | G34: =IFERROR(VLOOKUP(B34,'ACDOCA - Paste Data'!B:H,7,FALSE),0) -> 61812.59 | H34: =G34+M34 -> 61812.59 | I34: =F34-H34 -> 25041.19 | J34: =IFERROR(I34/F34,0) -> 0.28831434 | K34: =IFERROR(VLOOKUP(B34,'WIP - Paste Data'!B:E,4,FALSE),"") -> 227167.44 | P34: =IFERROR(VLOOKUP(B34,'JTD Paste Data'!A:B,2,FALSE),"0") -> 227167.44 | Q34: =SUM(P34+L34) -> 227167.44 | R34: =IFERROR(VLOOKUP(B34,'JTD Paste Data'!A:C,3,FALSE),"0") -> 177646.56 | S34: =SUM(R34+M34) -> 177646.56 | T34: =SUM(Q34-S34) -> 49520.88 | U34: =IFERROR(T34/Q34,0) -> 0.21799286
A35: VZ - Timbers | B35: 22048 | C35: N/A | D35: =IFERROR(VLOOKUP(B35,'MTD Hours Paste Data'!A:C,3,FALSE),"") | E35: =IFERROR(VLOOKUP(B35,'ACDOCA - Paste Data'!B:G,6,FALSE),0) -> 0 | F35: =E35 +L35 -> 0 | G35: =IFERROR(VLOOKUP(B35,'ACDOCA - Paste Data'!B:H,7,FALSE),0) -> 0 | H35: =G35+M35 -> 0 | I35: =F35-H35 -> 0 | J35: =IFERROR(I35/F35,0) -> 0 | K35: =IFERROR(VLOOKUP(B35,'WIP - Paste Data'!B:E,4,FALSE),"") | P35: =IFERROR(VLOOKUP(B35,'JTD Paste Data'!A:B,2,FALSE),"0") -> 8540.16 | Q35: =SUM(P35+L35) -> 8540.16 | R35: =IFERROR(VLOOKUP(B35,'JTD Paste Data'!A:C,3,FALSE),"0") -> 1117.29 | S35: =SUM(R35+M35) -> 1117.29 | T35: =SUM(Q35-S35) -> 7422.87 | U35: =IFERROR(T35/Q35,0) -> 0.86917224
A36: =VLOOKUP(B36,'SAP Contracts'!A:J,10,FALSE) -> T-Mobile-Idaho Market 2024-2025 | B36: =VLOOKUP(C36,'Active North Sky Projects'!C:D,2,FALSE) -> 21161 | C36: 2135000 | D36: =IFERROR(VLOOKUP(B36,'MTD Hours Paste Data'!A:C,3,FALSE),"") | E36: =IFERROR(VLOOKUP(B36,'ACDOCA - Paste Data'!B:G,6,FALSE),0) -> 0 | F36: =E36 +L36 -> 0 | G36: =IFERROR(VLOOKUP(B36,'ACDOCA - Paste Data'!B:H,7,FALSE),0) -> 0 | H36: =G36+M36 -> 0 | I36: =F36-H36 -> 0 | J36: =IFERROR(I36/F36,0) -> 0 | K36: =IFERROR(VLOOKUP(B36,'WIP - Paste Data'!B:E,4,FALSE),"") | P36: =IFERROR(VLOOKUP(B36,'JTD Paste Data'!A:B,2,FALSE),"0") -> 0 | Q36: =SUM(P36+L36) -> 0 | R36: =IFERROR(VLOOKUP(B36,'JTD Paste Data'!A:C,3,FALSE),"0") -> 0 | S36: =SUM(R36+M36) -> 0 | T36: =SUM(Q36-S36) -> 0 | U36: =IFERROR(T36/Q36,0) -> 0
A37: Total Wireless Projects | B37: PCA | E37: =SUM(E5:E36) -> 294138.31 | F37: =SUM(F5:F36) -> 294138.31 | G37: =SUM(G5:G36) -> 270802.56 | H37: =SUM(H5:H36) -> 270802.56 | I37: =F37-H37 -> 23335.75 | J37: =IFERROR(I37/F37,0) -> 0.079335976 | K37: =SUM(K5:K36) -> 2060337.1 | L37: =SUM(L5:L36) -> 0 | M37: =SUM(M5:M36) -> 0 | O37: =SUM(O5:O36) -> 0 | P37: =SUM(P5:P36) -> 13174519 | Q37: =SUM(Q5:Q36) -> 13174519 | R37: =SUM(R5:R36) -> 12336460 | S37: =SUM(S5:S36) -> 12336460 | T37: =SUM(T5:T36) -> 838059.12 | U37: =IFERROR(T37/Q37,0) -> 0.063612124
A38: Div 2 - Structured Wiring PNW - Jason
A39: =VLOOKUP(B39,'SAP Contracts'!A:J,10,FALSE) -> Astound - OR Wave Broadband | B39: =VLOOKUP(C39,'Active North Sky Projects'!C:D,2,FALSE) -> 21586 | C39: 2385000 | D39: =IFERROR(VLOOKUP(B39,'MTD Hours Paste Data'!A:C,3,FALSE),"") -> 0 | E39: =IFERROR(VLOOKUP(B39,'ACDOCA - Paste Data'!B:G,6,FALSE),0) -> 0 | F39: =E39 +L39 -> 0 | G39: =IFERROR(VLOOKUP(B39,'ACDOCA - Paste Data'!B:H,7,FALSE),0) -> 0 | H39: =G39+M39 -> 0 | I39: =F39-H39 -> 0 | J39: =IFERROR(I39/F39,0) -> 0 | K39: =IFERROR(VLOOKUP(B39,'WIP - Paste Data'!B:E,4,FALSE),"") -> 11862.94 | P39: =IFERROR(VLOOKUP(B39,'JTD Paste Data'!A:B,2,FALSE),"0") -> 440215.08 | Q39: =SUM(P39+L39) -> 440215.08 | R39: =IFERROR(VLOOKUP(B39,'JTD Paste Data'!A:C,3,FALSE),"0") -> 335168.35 | S39: =SUM(R39+M39) -> 335168.35 | T39: =SUM(Q39-S39) -> 105046.73 | U39: =IFERROR(T39/Q39,0) -> 0.23862592
A40: =VLOOKUP(B40,'SAP Contracts'!A:J,10,FALSE) -> Astound - WA Wave Broadband | B40: =VLOOKUP(C40,'Active North Sky Projects'!C:D,2,FALSE) -> 21398 | C40: 2484117 | D40: =IFERROR(VLOOKUP(B40,'MTD Hours Paste Data'!A:C,3,FALSE),"") -> 76.46 | E40: =IFERROR(VLOOKUP(B40,'ACDOCA - Paste Data'!B:G,6,FALSE),0) -> 12000 | F40: =E40 +L40 -> 12000 | G40: =IFERROR(VLOOKUP(B40,'ACDOCA - Paste Data'!B:H,7,FALSE),0) -> 17256.38 | H40: =G40+M40 -> 17256.38 | I40: =F40-H40 -> -5256.38 | J40: =IFERROR(I40/F40,0) -> -0.43803167 | K40: =IFERROR(VLOOKUP(B40,'WIP - Paste Data'!B:E,4,FALSE),"") -> 159215.92 | P40: =IFERROR(VLOOKUP(B40,'JTD Paste Data'!A:B,2,FALSE),"0") -> 1858637.4 | Q40: =SUM(P40+L40) -> 1858637.4 | R40: =IFERROR(VLOOKUP(B40,'JTD Paste Data'!A:C,3,FALSE),"0") -> 1520921.8 | S40: =SUM(R40+M40) -> 1520921.8 | T40: =SUM(Q40-S40) -> 337715.67 | U40: =IFERROR(T40/Q40,0) -> 0.18170067
A41: =VLOOKUP(B41,'SAP Contracts'!A:J,10,FALSE) -> Consol Bus Svs-Canby dba Directlink Resi | B41: =VLOOKUP(C41,'Active North Sky Projects'!C:D,2,FALSE) -> 21572 | C41: 2383011 | D41: =IFERROR(VLOOKUP(B41,'MTD Hours Paste Data'!A:C,3,FALSE),"") -> 173.97 | E41: =IFERROR(VLOOKUP(B41,'ACDOCA - Paste Data'!B:G,6,FALSE),0) -> 17400 | F41: =E41 +L41 -> 17400 | G41: =IFERROR(VLOOKUP(B41,'ACDOCA - Paste Data'!B:H,7,FALSE),0) -> 25559.73 | H41: =G41+M41 -> 25559.73 | I41: =F41-H41 -> -8159.73 | J41: =IFERROR(I41/F41,0) -> -0.46895 | K41: =IFERROR(VLOOKUP(B41,'WIP - Paste Data'!B:E,4,FALSE),"") -> 9625 | P41: =IFERROR(VLOOKUP(B41,'JTD Paste Data'!A:B,2,FALSE),"0") -> 944750 | Q41: =SUM(P41+L41) -> 944750 | R41: =IFERROR(VLOOKUP(B41,'JTD Paste Data'!A:C,3,FALSE),"0") -> 883231.54 | S41: =SUM(R41+M41) -> 883231.54 | T41: =SUM(Q41-S41) -> 61518.46 | U41: =IFERROR(T41/Q41,0) -> 0.065116126
A42: =VLOOKUP(B42,'SAP Contracts'!A:J,10,FALSE) -> Hunter Communications & Technologies, LL | B42: =VLOOKUP(C42,'Active North Sky Projects'!C:D,2,FALSE) -> 21406 | C42: 2386011 | D42: =IFERROR(VLOOKUP(B42,'MTD Hours Paste Data'!A:C,3,FALSE),"") | E42: =IFERROR(VLOOKUP(B42,'ACDOCA - Paste Data'!B:G,6,FALSE),0) -> 0 | F42: =E42 +L42 -> 0 | G42: =IFERROR(VLOOKUP(B42,'ACDOCA - Paste Data'!B:H,7,FALSE),0) -> 0 | H42: =G42+M42 -> 0 | I42: =F42-H42 -> 0 | J42: =IFERROR(I42/F42,0) -> 0 | K42: =IFERROR(VLOOKUP(B42,'WIP - Paste Data'!B:E,4,FALSE),"") | P42: =IFERROR(VLOOKUP(B42,'JTD Paste Data'!A:B,2,FALSE),"0") -> 0 | Q42: =SUM(P42+L42) -> 0 | R42: =IFERROR(VLOOKUP(B42,'JTD Paste Data'!A:C,3,FALSE),"0") -> 0 | S42: =SUM(R42+M42) -> 0 | T42: =SUM(Q42-S42) -> 0 | U42: =IFERROR(T42/Q42,0) -> 0
A43: =VLOOKUP(B43,'SAP Contracts'!A:J,10,FALSE) -> Ziply - OR - MDU | B43: 21258 | C43: 2386010 | D43: =IFERROR(VLOOKUP(B43,'MTD Hours Paste Data'!A:C,3,FALSE),"") -> 0 | E43: =IFERROR(VLOOKUP(B43,'ACDOCA - Paste Data'!B:G,6,FALSE),0) -> 0 | F43: =E43 +L43 -> 0 | G43: =IFERROR(VLOOKUP(B43,'ACDOCA - Paste Data'!B:H,7,FALSE),0) -> 483.33 | H43: =G43+M43 -> 483.33 | I43: =F43-H43 -> -483.33 | J43: =IFERROR(I43/F43,0) -> 0 | K43: =IFERROR(VLOOKUP(B43,'WIP - Paste Data'!B:E,4,FALSE),"") | P43: =IFERROR(VLOOKUP(B43,'JTD Paste Data'!A:B,2,FALSE),"0") -> 0 | Q43: =SUM(P43+L43) -> 0 | R43: =IFERROR(VLOOKUP(B43,'JTD Paste Data'!A:C,3,FALSE),"0") -> 2070.09 | S43: =SUM(R43+M43) -> 2070.09 | T43: =SUM(Q43-S43) -> -2070.09 | U43: =IFERROR(T43/Q43,0) -> 0
A44: =VLOOKUP(B44,'SAP Contracts'!A:J,10,FALSE) -> Mereo 89, LLC | B44: =VLOOKUP(C44,'Active North Sky Projects'!C:D,2,FALSE) -> 21424 | C44: 2486050 | D44: =IFERROR(VLOOKUP(B44,'MTD Hours Paste Data'!A:C,3,FALSE),"") -> 0 | E44: =IFERROR(VLOOKUP(B44,'ACDOCA - Paste Data'!B:G,6,FALSE),0) -> 0 | F44: =E44 +L44 -> 0 | G44: =IFERROR(VLOOKUP(B44,'ACDOCA - Paste Data'!B:H,7,FALSE),0) -> 0 | H44: =G44+M44 -> 0 | I44: =F44-H44 -> 0 | J44: =IFERROR(I44/F44,0) -> 0 | K44: =IFERROR(VLOOKUP(B44,'WIP - Paste Data'!B:E,4,FALSE),"") | P44: =IFERROR(VLOOKUP(B44,'JTD Paste Data'!A:B,2,FALSE),"0") -> 42916.03 | Q44: =SUM(P44+L44) -> 42916.03 | R44: =IFERROR(VLOOKUP(B44,'JTD Paste Data'!A:C,3,FALSE),"0") -> 40311.43 | S44: =SUM(R44+M44) -> 40311.43 | T44: =SUM(Q44-S44) -> 2604.6 | U44: =IFERROR(T44/Q44,0) -> 0.060690609
A45: Total Structured Wiring - Jason | B45: PCB | E45: =SUM(E39:E44) -> 29400 | F45: =SUM(F39:F44) -> 29400 | G45: =SUM(G39:G44) -> 43299.44 | H45: =SUM(H39:H44) -> 43299.44 | I45: =F45-H45 -> -13899.44 | J45: =IFERROR(I45/F45,0) -> -0.47277007 | K45: =SUM(K39:K44) -> 180703.86 | L45: =SUM(L39:L44) -> 0 | M45: =SUM(M39:M44) -> 0 | P45: =SUM(P39:P44) -> 3286518.5 | Q45: =SUM(Q39:Q44) -> 3286518.5 | R45: =SUM(R39:R44) -> 2781703.2 | S45: =SUM(S39:S44) -> 2781703.2 | T45: =SUM(T39:T44) -> 504815.37 | U45: =IFERROR(T45/Q45,0) -> 0.15360186
A46: Div 2 - Structured Wiring - Bryan
A47: =VLOOKUP(B47,'SAP Contracts'!A:J,10,FALSE) -> CommPro Services, LLC - AL | B47: =VLOOKUP(C47,'Active North Sky Projects'!C:D,2,FALSE) -> 21307 | C47: 2014000 | D47: =IFERROR(VLOOKUP(B47,'MTD Hours Paste Data'!A:C,3,FALSE),"") -> 0 | E47: =IFERROR(VLOOKUP(B47,'ACDOCA - Paste Data'!B:G,6,FALSE),0) -> 0 | F47: =E47 +L47 -> 0 | G47: =IFERROR(VLOOKUP(B47,'ACDOCA - Paste Data'!B:H,7,FALSE),0) -> 0 | H47: =G47+M47 -> 0 | I47: =F47-H47 -> 0 | J47: =IFERROR(I47/F47,0) -> 0 | K47: =IFERROR(VLOOKUP(B47,'WIP - Paste Data'!B:E,4,FALSE),"") | P47: =IFERROR(VLOOKUP(B47,'JTD Paste Data'!A:B,2,FALSE),"0") -> 930089.63 | Q47: =SUM(P47+L47) -> 930089.63 | R47: =IFERROR(VLOOKUP(B47,'JTD Paste Data'!A:C,3,FALSE),"0") -> 691583.58 | S47: =SUM(R47+M47) -> 691583.58 | T47: =SUM(Q47-S47) -> 238506.05 | U47: =IFERROR(T47/Q47,0) -> 0.2564334
A48: =VLOOKUP(B48,'SAP Contracts'!A:J,10,FALSE) -> CommPro Services, LLC - IN | B48: =VLOOKUP(C48,'Active North Sky Projects'!C:D,2,FALSE) -> 21554 | C48: 2156000 | D48: =IFERROR(VLOOKUP(B48,'MTD Hours Paste Data'!A:C,3,FALSE),"") -> 0 | E48: =IFERROR(VLOOKUP(B48,'ACDOCA - Paste Data'!B:G,6,FALSE),0) -> 4750 | F48: =E48 +L48 -> 4750 | G48: =IFERROR(VLOOKUP(B48,'ACDOCA - Paste Data'!B:H,7,FALSE),0) -> 708.56 | H48: =G48+M48 -> 708.56 | I48: =F48-H48 -> 4041.44 | J48: =IFERROR(I48/F48,0) -> 0.85082947 | K48: =IFERROR(VLOOKUP(B48,'WIP - Paste Data'!B:E,4,FALSE),"") -> 4750 | P48: =IFERROR(VLOOKUP(B48,'JTD Paste Data'!A:B,2,FALSE),"0") -> 288201.2 | Q48: =SUM(P48+L48) -> 288201.2 | R48: =IFERROR(VLOOKUP(B48,'JTD Paste Data'!A:C,3,FALSE),"0") -> 227325.24 | S48: =SUM(R48+M48) -> 227325.24 | T48: =SUM(Q48-S48) -> 60875.96 | U48: =IFERROR(T48/Q48,0) -> 0.2112273
A49: =VLOOKUP(B49,'SAP Contracts'!A:J,10,FALSE) -> CommPro Services, LLC - GA | B49: 21638 | C49: 2113000 | D49: =IFERROR(VLOOKUP(B49,'MTD Hours Paste Data'!A:C,3,FALSE),"") -> 0 | E49: =IFERROR(VLOOKUP(B49,'ACDOCA - Paste Data'!B:G,6,FALSE),0) -> 0 | F49: =E49 +L49 -> 0 | G49: =IFERROR(VLOOKUP(B49,'ACDOCA - Paste Data'!B:H,7,FALSE),0) -> -308.68 | H49: =G49+M49 -> -308.68 | I49: =F49-H49 -> 308.68 | J49: =IFERROR(I49/F49,0) -> 0 | K49: =IFERROR(VLOOKUP(B49,'WIP - Paste Data'!B:E,4,FALSE),"") | P49: =IFERROR(VLOOKUP(B49,'JTD Paste Data'!A:B,2,FALSE),"0") -> 689352.72 | Q49: =SUM(P49+L49) -> 689352.72 | R49: =IFERROR(VLOOKUP(B49,'JTD Paste Data'!A:C,3,FALSE),"0") -> 505598.01 | S49: =SUM(R49+M49) -> 505598.01 | T49: =SUM(Q49-S49) -> 183754.71 | U49: =IFERROR(T49/Q49,0) -> 0.26656123
A50: =VLOOKUP(B50,'SAP Contracts'!A:J,10,FALSE) -> CommPro Services, LLC - KY | B50: =VLOOKUP(C50,'Active North Sky Projects'!C:D,2,FALSE) -> 21557 | C50: 2180000 | D50: =IFERROR(VLOOKUP(B50,'MTD Hours Paste Data'!A:C,3,FALSE),"") -> 0 | E50: =IFERROR(VLOOKUP(B50,'ACDOCA - Paste Data'!B:G,6,FALSE),0) -> 0 | F50: =E50 +L50 -> 0 | G50: =IFERROR(VLOOKUP(B50,'ACDOCA - Paste Data'!B:H,7,FALSE),0) -> 114.24 | H50: =G50+M50 -> 114.24 | I50: =F50-H50 -> -114.24 | J50: =IFERROR(I50/F50,0) -> 0 | K50: =IFERROR(VLOOKUP(B50,'WIP - Paste Data'!B:E,4,FALSE),"") | P50: =IFERROR(VLOOKUP(B50,'JTD Paste Data'!A:B,2,FALSE),"0") -> 441403 | Q50: =SUM(P50+L50) -> 441403 | R50: =IFERROR(VLOOKUP(B50,'JTD Paste Data'!A:C,3,FALSE),"0") -> 385108.46 | S50: =SUM(R50+M50) -> 385108.46 | T50: =SUM(Q50-S50) -> 56294.54 | U50: =IFERROR(T50/Q50,0) -> 0.12753547
A51: =VLOOKUP(B51,'SAP Contracts'!A:J,10,FALSE) -> CommPro Services, LLC (MS) | B51: =VLOOKUP(C51,'Active North Sky Projects'!C:D,2,FALSE) -> 21273 | C51: 2254000 | D51: =IFERROR(VLOOKUP(B51,'MTD Hours Paste Data'!A:C,3,FALSE),"") -> 162.38 | E51: =IFERROR(VLOOKUP(B51,'ACDOCA - Paste Data'!B:G,6,FALSE),0) -> 117449 | F51: =E51 +L51 -> 117449 | G51: =IFERROR(VLOOKUP(B51,'ACDOCA - Paste Data'!B:H,7,FALSE),0) -> 83084.39 | H51: =G51+M51 -> 83084.39 | I51: =F51-H51 -> 34364.61 | J51: =IFERROR(I51/F51,0) -> 0.29259176 | K51: =IFERROR(VLOOKUP(B51,'WIP - Paste Data'!B:E,4,FALSE),"") -> 156899 | P51: =IFERROR(VLOOKUP(B51,'JTD Paste Data'!A:B,2,FALSE),"0") -> 254930 | Q51: =SUM(P51+L51) -> 254930 | R51: =IFERROR(VLOOKUP(B51,'JTD Paste Data'!A:C,3,FALSE),"0") -> 191143.95 | S51: =SUM(R51+M51) -> 191143.95 | T51: =SUM(Q51-S51) -> 63786.05 | U51: =IFERROR(T51/Q51,0) -> 0.25021006
A52: =VLOOKUP(B52,'SAP Contracts'!A:J,10,FALSE) -> CommPro Services, LLC - SC | B52: =VLOOKUP(C52,'Active North Sky Projects'!C:D,2,FALSE) -> 21591 | C52: 2413000 | D52: =IFERROR(VLOOKUP(B52,'MTD Hours Paste Data'!A:C,3,FALSE),"") | E52: =IFERROR(VLOOKUP(B52,'ACDOCA - Paste Data'!B:G,6,FALSE),0) -> 0 | F52: =E52 +L52 -> 0 | G52: =IFERROR(VLOOKUP(B52,'ACDOCA - Paste Data'!B:H,7,FALSE),0) -> 0 | H52: =G52+M52 -> 0 | I52: =F52-H52 -> 0 | J52: =IFERROR(I52/F52,0) -> 0 | K52: =IFERROR(VLOOKUP(B52,'WIP - Paste Data'!B:E,4,FALSE),"") | P52: =IFERROR(VLOOKUP(B52,'JTD Paste Data'!A:B,2,FALSE),"0") -> 0 | Q52: =SUM(P52+L52) -> 0 | R52: =IFERROR(VLOOKUP(B52,'JTD Paste Data'!A:C,3,FALSE),"0") -> 0 | S52: =SUM(R52+M52) -> 0 | T52: =SUM(Q52-S52) -> 0 | U52: =IFERROR(T52/Q52,0) -> 0
A53: =VLOOKUP(B53,'SAP Contracts'!A:J,10,FALSE) -> CommPro Services, LLC - TN | B53: =VLOOKUP(C53,'Active North Sky Projects'!C:D,2,FALSE) -> 21290 | C53: 2434000 | D53: =IFERROR(VLOOKUP(B53,'MTD Hours Paste Data'!A:C,3,FALSE),"") -> 0 | E53: =IFERROR(VLOOKUP(B53,'ACDOCA - Paste Data'!B:G,6,FALSE),0) -> 0 | F53: =E53 +L53 -> 0 | G53: =IFERROR(VLOOKUP(B53,'ACDOCA - Paste Data'!B:H,7,FALSE),0) -> 607.93 | H53: =G53+M53 -> 607.93 | I53: =F53-H53 -> -607.93 | J53: =IFERROR(I53/F53,0) -> 0 | K53: =IFERROR(VLOOKUP(B53,'WIP - Paste Data'!B:E,4,FALSE),"") | P53: =IFERROR(VLOOKUP(B53,'JTD Paste Data'!A:B,2,FALSE),"0") -> 700244.64 | Q53: =SUM(P53+L53) -> 700244.64 | R53: =IFERROR(VLOOKUP(B53,'JTD Paste Data'!A:C,3,FALSE),"0") -> 543089.91 | S53: =SUM(R53+M53) -> 543089.91 | T53: =SUM(Q53-S53) -> 157154.73 | U53: =IFERROR(T53/Q53,0) -> 0.22442832
A54: CommPro Services, LLC - NC | B54: 21561 | C54: N/A | D54: =IFERROR(VLOOKUP(B54,'MTD Hours Paste Data'!A:C,3,FALSE),"") | E54: =IFERROR(VLOOKUP(B54,'ACDOCA - Paste Data'!B:G,6,FALSE),0) -> 0 | F54: =E54 +L54 -> 0 | G54: =IFERROR(VLOOKUP(B54,'ACDOCA - Paste Data'!B:H,7,FALSE),0) -> 0 | H54: =G54+M54 -> 0 | I54: =F54-H54 -> 0 | J54: =IFERROR(I54/F54,0) -> 0 | K54: =IFERROR(VLOOKUP(B54,'WIP - Paste Data'!B:E,4,FALSE),"") | P54: =IFERROR(VLOOKUP(B54,'JTD Paste Data'!A:B,2,FALSE),"0") -> 409561.47 | Q54: =SUM(P54+L54) -> 409561.47 | R54: =IFERROR(VLOOKUP(B54,'JTD Paste Data'!A:C,3,FALSE),"0") -> 272674.17 | S54: =SUM(R54+M54) -> 272674.17 | T54: =SUM(Q54-S54) -> 136887.3 | U54: =IFERROR(T54/Q54,0) -> 0.33422895
A55: CommPro Services, LLC - FL | B55: 21637 | C55: N/A | D55: =IFERROR(VLOOKUP(B55,'MTD Hours Paste Data'!A:C,3,FALSE),"") | E55: =IFERROR(VLOOKUP(B55,'ACDOCA - Paste Data'!B:G,6,FALSE),0) -> 0 | F55: =E55 +L55 -> 0 | G55: =IFERROR(VLOOKUP(B55,'ACDOCA - Paste Data'!B:H,7,FALSE),0) -> 0 | H55: =G55+M55 -> 0 | I55: =F55-H55 -> 0 | J55: =IFERROR(I55/F55,0) -> 0 | K55: =IFERROR(VLOOKUP(B55,'WIP - Paste Data'!B:E,4,FALSE),"") | P55: =IFERROR(VLOOKUP(B55,'JTD Paste Data'!A:B,2,FALSE),"0") -> 1442192.9 | Q55: =SUM(P55+L55) -> 1442192.9 | R55: =IFERROR(VLOOKUP(B55,'JTD Paste Data'!A:C,3,FALSE),"0") -> 1065428.1 | S55: =SUM(R55+M55) -> 1065428.1 | T55: =SUM(Q55-S55) -> 376764.82 | U55: =IFERROR(T55/Q55,0) -> 0.2612444
A56: Ezee - 7979 Westheimer | B56: 22001 | C56: N/A | D56: =IFERROR(VLOOKUP(B56,'MTD Hours Paste Data'!A:C,3,FALSE),"") | E56: =IFERROR(VLOOKUP(B56,'ACDOCA - Paste Data'!B:G,6,FALSE),0) -> 0 | F56: =E56 +L56 -> 0 | G56: =IFERROR(VLOOKUP(B56,'ACDOCA - Paste Data'!B:H,7,FALSE),0) -> 432.68 | H56: =G56+M56 -> 432.68 | I56: =F56-H56 -> -432.68 | J56: =IFERROR(I56/F56,0) -> 0 | K56: =IFERROR(VLOOKUP(B56,'WIP - Paste Data'!B:E,4,FALSE),"") | P56: =IFERROR(VLOOKUP(B56,'JTD Paste Data'!A:B,2,FALSE),"0") -> 306092.3 | Q56: =SUM(P56+L56) -> 306092.3 | R56: =IFERROR(VLOOKUP(B56,'JTD Paste Data'!A:C,3,FALSE),"0") -> 239746.96 | S56: =SUM(R56+M56) -> 239746.96 | T56: =SUM(Q56-S56) -> 66345.34 | U56: =IFERROR(T56/Q56,0) -> 0.21674946
A57: =VLOOKUP(B57,'SAP Contracts'!A:J,10,FALSE) -> Ezee - San Antigua | B57: =VLOOKUP(C57,'Active North Sky Projects'!C:D,2,FALSE) -> 21906 | C57: 2445025 | D57: =IFERROR(VLOOKUP(B57,'MTD Hours Paste Data'!A:C,3,FALSE),"") | E57: =IFERROR(VLOOKUP(B57,'ACDOCA - Paste Data'!B:G,6,FALSE),0) -> 0 | F57: =E57 +L57 -> 0 | G57: =IFERROR(VLOOKUP(B57,'ACDOCA - Paste Data'!B:H,7,FALSE),0) -> 0 | H57: =G57+M57 -> 0 | I57: =F57-H57 -> 0 | J57: =IFERROR(I57/F57,0) -> 0 | K57: =IFERROR(VLOOKUP(B57,'WIP - Paste Data'!B:E,4,FALSE),"") | P57: =IFERROR(VLOOKUP(B57,'JTD Paste Data'!A:B,2,FALSE),"0") -> 150028.6 | Q57: =SUM(P57+L57) -> 150028.6 | R57: =IFERROR(VLOOKUP(B57,'JTD Paste Data'!A:C,3,FALSE),"0") -> 112090.02 | S57: =SUM(R57+M57) -> 112090.02 | T57: =SUM(Q57-S57) -> 37938.58 | U57: =IFERROR(T57/Q57,0) -> 0.25287565
A58: =VLOOKUP(B58,'SAP Contracts'!A:J,10,FALSE) -> Ezee Fiber - Azulejo Apartments | B58: =VLOOKUP(C58,'Active North Sky Projects'!C:D,2,FALSE) -> 21089 | C58: 2445023 | D58: =IFERROR(VLOOKUP(B58,'MTD Hours Paste Data'!A:C,3,FALSE),"") -> 0 | E58: =IFERROR(VLOOKUP(B58,'ACDOCA - Paste Data'!B:G,6,FALSE),0) -> 0 | F58: =E58 +L58 -> 0 | G58: =IFERROR(VLOOKUP(B58,'ACDOCA - Paste Data'!B:H,7,FALSE),0) -> 0 | H58: =G58+M58 -> 0 | I58: =F58-H58 -> 0 | J58: =IFERROR(I58/F58,0) -> 0 | K58: =IFERROR(VLOOKUP(B58,'WIP - Paste Data'!B:E,4,FALSE),"") | P58: =IFERROR(VLOOKUP(B58,'JTD Paste Data'!A:B,2,FALSE),"0") -> 62143.1 | Q58: =SUM(P58+L58) -> 62143.1 | R58: =IFERROR(VLOOKUP(B58,'JTD Paste Data'!A:C,3,FALSE),"0") -> 46128.07 | S58: =SUM(R58+M58) -> 46128.07 | T58: =SUM(Q58-S58) -> 16015.03 | U58: =IFERROR(T58/Q58,0) -> 0.25771212
A59: =VLOOKUP(B59,'SAP Contracts'!A:J,10,FALSE) -> Ezee Fiber - Janicsh Apartments | B59: =VLOOKUP(C59,'Active North Sky Projects'!C:D,2,FALSE) -> 21099 | C59: 2445024 | D59: =IFERROR(VLOOKUP(B59,'MTD Hours Paste Data'!A:C,3,FALSE),"") -> 0 | E59: =IFERROR(VLOOKUP(B59,'ACDOCA - Paste Data'!B:G,6,FALSE),0) -> 0 | F59: =E59 +L59 -> 0 | G59: =IFERROR(VLOOKUP(B59,'ACDOCA - Paste Data'!B:H,7,FALSE),0) -> 265.91 | H59: =G59+M59 -> 265.91 | I59: =F59-H59 -> -265.91 | J59: =IFERROR(I59/F59,0) -> 0 | K59: =IFERROR(VLOOKUP(B59,'WIP - Paste Data'!B:E,4,FALSE),"") | P59: =IFERROR(VLOOKUP(B59,'JTD Paste Data'!A:B,2,FALSE),"0") -> 64903 | Q59: =SUM(P59+L59) -> 64903 | R59: =IFERROR(VLOOKUP(B59,'JTD Paste Data'!A:C,3,FALSE),"0") -> 51073.93 | S59: =SUM(R59+M59) -> 51073.93 | T59: =SUM(Q59-S59) -> 13829.07 | U59: =IFERROR(T59/Q59,0) -> 0.21307289
A60: =VLOOKUP(B60,'SAP Contracts'!A:J,10,FALSE) -> Ezee Fiber Texas - Mallard Creek Apts | B60: =VLOOKUP(C60,'Active North Sky Projects'!C:D,2,FALSE) -> 21381 | C60: 2445007 | D60: =IFERROR(VLOOKUP(B60,'MTD Hours Paste Data'!A:C,3,FALSE),"") -> 0 | E60: =IFERROR(VLOOKUP(B60,'ACDOCA - Paste Data'!B:G,6,FALSE),0) -> 0 | F60: =E60 +L60 -> 0 | G60: =IFERROR(VLOOKUP(B60,'ACDOCA - Paste Data'!B:H,7,FALSE),0) -> 0 | H60: =G60+M60 -> 0 | I60: =F60-H60 -> 0 | J60: =IFERROR(I60/F60,0) -> 0 | K60: =IFERROR(VLOOKUP(B60,'WIP - Paste Data'!B:E,4,FALSE),"") | P60: =IFERROR(VLOOKUP(B60,'JTD Paste Data'!A:B,2,FALSE),"0") -> 215058.7 | Q60: =SUM(P60+L60) -> 215058.7 | R60: =IFERROR(VLOOKUP(B60,'JTD Paste Data'!A:C,3,FALSE),"0") -> 172333.21 | S60: =SUM(R60+M60) -> 172333.21 | T60: =SUM(Q60-S60) -> 42725.49 | U60: =IFERROR(T60/Q60,0) -> 0.19866897
A61: =VLOOKUP(B61,'SAP Contracts'!A:J,10,FALSE) -> Ezee Fiber-717 Lehman | B61: =VLOOKUP(C61,'Active North Sky Projects'!C:D,2,FALSE) -> 21078 | C61: 2445022 | D61: =IFERROR(VLOOKUP(B61,'MTD Hours Paste Data'!A:C,3,FALSE),"") -> 0 | E61: =IFERROR(VLOOKUP(B61,'ACDOCA - Paste Data'!B:G,6,FALSE),0) -> 0 | F61: =E61 +L61 -> 0 | G61: =IFERROR(VLOOKUP(B61,'ACDOCA - Paste Data'!B:H,7,FALSE),0) -> -205.54 | H61: =G61+M61 -> -205.54 | I61: =F61-H61 -> 205.54 | J61: =IFERROR(I61/F61,0) -> 0 | K61: =IFERROR(VLOOKUP(B61,'WIP - Paste Data'!B:E,4,FALSE),"") -> 18410 | P61: =IFERROR(VLOOKUP(B61,'JTD Paste Data'!A:B,2,FALSE),"0") -> 139128.08 | Q61: =SUM(P61+L61) -> 139128.08 | R61: =IFERROR(VLOOKUP(B61,'JTD Paste Data'!A:C,3,FALSE),"0") -> 97196.53 | S61: =SUM(R61+M61) -> 97196.53 | T61: =SUM(Q61-S61) -> 41931.55 | U61: =IFERROR(T61/Q61,0) -> 0.30138812
A62: =VLOOKUP(B62,'SAP Contracts'!A:J,10,FALSE) -> Ezee Fiber-Franklin Apts | B62: =VLOOKUP(C62,'Active North Sky Projects'!C:D,2,FALSE) -> 21072 | C62: 2445021 | D62: =IFERROR(VLOOKUP(B62,'MTD Hours Paste Data'!A:C,3,FALSE),"") -> 0 | E62: =IFERROR(VLOOKUP(B62,'ACDOCA - Paste Data'!B:G,6,FALSE),0) -> 0 | F62: =E62 +L62 -> 0 | G62: =IFERROR(VLOOKUP(B62,'ACDOCA - Paste Data'!B:H,7,FALSE),0) -> 0 | H62: =G62+M62 -> 0 | I62: =F62-H62 -> 0 | J62: =IFERROR(I62/F62,0) -> 0 | K62: =IFERROR(VLOOKUP(B62,'WIP - Paste Data'!B:E,4,FALSE),"") | P62: =IFERROR(VLOOKUP(B62,'JTD Paste Data'!A:B,2,FALSE),"0") -> 143426.55 | Q62: =SUM(P62+L62) -> 143426.55 | R62: =IFERROR(VLOOKUP(B62,'JTD Paste Data'!A:C,3,FALSE),"0") -> 106821.01 | S62: =SUM(R62+M62) -> 106821.01 | T62: =SUM(Q62-S62) -> 36605.54 | U62: =IFERROR(T62/Q62,0) -> 0.25522151
A63: Ezee - Vista Energy Corridor | B63: 21954 | C63: N/A | D63: =IFERROR(VLOOKUP(B63,'MTD Hours Paste Data'!A:C,3,FALSE),"") | E63: =IFERROR(VLOOKUP(B63,'ACDOCA - Paste Data'!B:G,6,FALSE),0) -> 0 | F63: =E63 +L63 -> 0 | G63: =IFERROR(VLOOKUP(B63,'ACDOCA - Paste Data'!B:H,7,FALSE),0) -> 0 | H63: =G63+M63 -> 0 | I63: =F63-H63 -> 0 | J63: =IFERROR(I63/F63,0) -> 0 | K63: =IFERROR(VLOOKUP(B63,'WIP - Paste Data'!B:E,4,FALSE),"") | P63: =IFERROR(VLOOKUP(B63,'JTD Paste Data'!A:B,2,FALSE),"0") -> 176310.6 | Q63: =SUM(P63+L63) -> 176310.6 | R63: =IFERROR(VLOOKUP(B63,'JTD Paste Data'!A:C,3,FALSE),"0") -> 140101.37 | S63: =SUM(R63+M63) -> 140101.37 | T63: =SUM(Q63-S63) -> 36209.23 | U63: =IFERROR(T63/Q63,0) -> 0.20537183
A64: Ezee - Casa Paz | B64: 22069 | C64: N/A | D64: =IFERROR(VLOOKUP(B64,'MTD Hours Paste Data'!A:C,3,FALSE),"") | E64: =IFERROR(VLOOKUP(B64,'ACDOCA - Paste Data'!B:G,6,FALSE),0) -> 0 | F64: =E64 +L64 -> 0 | G64: =IFERROR(VLOOKUP(B64,'ACDOCA - Paste Data'!B:H,7,FALSE),0) -> 0 | H64: =G64+M64 -> 0 | I64: =F64-H64 -> 0 | J64: =IFERROR(I64/F64,0) -> 0 | K64: =IFERROR(VLOOKUP(B64,'WIP - Paste Data'!B:E,4,FALSE),"") -> 80230 | P64: =IFERROR(VLOOKUP(B64,'JTD Paste Data'!A:B,2,FALSE),"0") -> 80230 | Q64: =SUM(P64+L64) -> 80230 | R64: =IFERROR(VLOOKUP(B64,'JTD Paste Data'!A:C,3,FALSE),"0") -> 51927.67 | S64: =SUM(R64+M64) -> 51927.67 | T64: =SUM(Q64-S64) -> 28302.33 | U64: =IFERROR(T64/Q64,0) -> 0.35276493
A65: Ezee - Eden Point | B65: 21963 | C65: N/A | D65: =IFERROR(VLOOKUP(B65,'MTD Hours Paste Data'!A:C,3,FALSE),"") | E65: =IFERROR(VLOOKUP(B65,'ACDOCA - Paste Data'!B:G,6,FALSE),0) -> 0 | F65: =E65 +L65 -> 0 | G65: =IFERROR(VLOOKUP(B65,'ACDOCA - Paste Data'!B:H,7,FALSE),0) -> 0 | H65: =G65+M65 -> 0 | I65: =F65-H65 -> 0 | J65: =IFERROR(I65/F65,0) -> 0 | K65: =IFERROR(VLOOKUP(B65,'WIP - Paste Data'!B:E,4,FALSE),"") -> 146967.8 | P65: =IFERROR(VLOOKUP(B65,'JTD Paste Data'!A:B,2,FALSE),"0") -> 146967.8 | Q65: =SUM(P65+L65) -> 146967.8 | R65: =IFERROR(VLOOKUP(B65,'JTD Paste Data'!A:C,3,FALSE),"0") -> 106547.66 | S65: =SUM(R65+M65) -> 106547.66 | T65: =SUM(Q65-S65) -> 40420.14 | U65: =IFERROR(T65/Q65,0) -> 0.27502718
A66: Ezee - Ridgepointe Apartments | B66: 22000 | C66: N/A | D66: =IFERROR(VLOOKUP(B66,'MTD Hours Paste Data'!A:C,3,FALSE),"") | E66: =IFERROR(VLOOKUP(B66,'ACDOCA - Paste Data'!B:G,6,FALSE),0) -> 0 | F66: =E66 +L66 -> 0 | G66: =IFERROR(VLOOKUP(B66,'ACDOCA - Paste Data'!B:H,7,FALSE),0) -> 0 | H66: =G66+M66 -> 0 | I66: =F66-H66 -> 0 | J66: =IFERROR(I66/F66,0) -> 0 | K66: =IFERROR(VLOOKUP(B66,'WIP - Paste Data'!B:E,4,FALSE),"") | P66: =IFERROR(VLOOKUP(B66,'JTD Paste Data'!A:B,2,FALSE),"0") -> 128539.8 | Q66: =SUM(P66+L66) -> 128539.8 | R66: =IFERROR(VLOOKUP(B66,'JTD Paste Data'!A:C,3,FALSE),"0") -> 99392.24 | S66: =SUM(R66+M66) -> 99392.24 | T66: =SUM(Q66-S66) -> 29147.56 | U66: =IFERROR(T66/Q66,0) -> 0.22675903
A67: Ezee - Summercrest Apartments | B67: 22002 | C67: N/A | D67: =IFERROR(VLOOKUP(B67,'MTD Hours Paste Data'!A:C,3,FALSE),"") | E67: =IFERROR(VLOOKUP(B67,'ACDOCA - Paste Data'!B:G,6,FALSE),0) -> 194446 | F67: =E67 +L67 -> 194446 | G67: =IFERROR(VLOOKUP(B67,'ACDOCA - Paste Data'!B:H,7,FALSE),0) -> 139034.16 | H67: =G67+M67 -> 139034.16 | I67: =F67-H67 -> 55411.84 | J67: =IFERROR(I67/F67,0) -> 0.2849729 | K67: =IFERROR(VLOOKUP(B67,'WIP - Paste Data'!B:E,4,FALSE),"") -> 206747 | P67: =IFERROR(VLOOKUP(B67,'JTD Paste Data'!A:B,2,FALSE),"0") -> 206747 | Q67: =SUM(P67+L67) -> 206747 | R67: =IFERROR(VLOOKUP(B67,'JTD Paste Data'!A:C,3,FALSE),"0") -> 149865.83 | S67: =SUM(R67+M67) -> 149865.83 | T67: =SUM(Q67-S67) -> 56881.17 | U67: =IFERROR(T67/Q67,0) -> 0.27512452
A68: =VLOOKUP(B68,'SAP Contracts'!A:J,10,FALSE) -> Google-Fiber FTTH Greenfields CO | B68: =VLOOKUP(C68,'Active North Sky Projects'!C:D,2,FALSE) -> 21628 | C68: 2065002 | D68: =IFERROR(VLOOKUP(B68,'MTD Hours Paste Data'!A:C,3,FALSE),"") -> 0 | E68: =IFERROR(VLOOKUP(B68,'ACDOCA - Paste Data'!B:G,6,FALSE),0) -> 2694 | F68: =E68 +L68 -> 2694 | G68: =IFERROR(VLOOKUP(B68,'ACDOCA - Paste Data'!B:H,7,FALSE),0) -> 330.3 | H68: =G68+M68 -> 330.3 | I68: =F68-H68 -> 2363.7 | J68: =IFERROR(I68/F68,0) -> 0.87739421 | K68: =IFERROR(VLOOKUP(B68,'WIP - Paste Data'!B:E,4,FALSE),"") -> 51293 | P68: =IFERROR(VLOOKUP(B68,'JTD Paste Data'!A:B,2,FALSE),"0") -> 240683 | Q68: =SUM(P68+L68) -> 240683 | R68: =IFERROR(VLOOKUP(B68,'JTD Paste Data'!A:C,3,FALSE),"0") -> 189455.13 | S68: =SUM(R68+M68) -> 189455.13 | T68: =SUM(Q68-S68) -> 51227.87 | U68: =IFERROR(T68/Q68,0) -> 0.21284374
A69: Google Fiber FTTH Installations | B69: 21635 | C69: 2065003 | D69: =IFERROR(VLOOKUP(B69,'MTD Hours Paste Data'!A:C,3,FALSE),"") -> 0 | E69: =IFERROR(VLOOKUP(B69,'ACDOCA - Paste Data'!B:G,6,FALSE),0) -> 9255.64 | F69: =E69 +L69 -> 9255.64 | G69: =IFERROR(VLOOKUP(B69,'ACDOCA - Paste Data'!B:H,7,FALSE),0) -> 8758.7 | H69: =G69+M69 -> 8758.7 | I69: =F69-H69 -> 496.94 | J69: =IFERROR(I69/F69,0) -> 0.053690507 | K69: =IFERROR(VLOOKUP(B69,'WIP - Paste Data'!B:E,4,FALSE),"") -> 12130.64 | P69: =IFERROR(VLOOKUP(B69,'JTD Paste Data'!A:B,2,FALSE),"0") -> 12130.64 | Q69: =SUM(P69+L69) -> 12130.64 | R69: =IFERROR(VLOOKUP(B69,'JTD Paste Data'!A:C,3,FALSE),"0") -> 8783.08 | S69: =SUM(R69+M69) -> 8783.08 | T69: =SUM(Q69-S69) -> 3347.56 | U69: =IFERROR(T69/Q69,0) -> 0.27595906
A70: =VLOOKUP(B70,'SAP Contracts'!A:J,10,FALSE) -> Google-Fiber FTTH MDU CO | B70: =VLOOKUP(C70,'Active North Sky Projects'!C:D,2,FALSE) -> 21247 | C70: 2065000 | D70: =IFERROR(VLOOKUP(B70,'MTD Hours Paste Data'!A:C,3,FALSE),"") -> 171.31 | E70: =IFERROR(VLOOKUP(B70,'ACDOCA - Paste Data'!B:G,6,FALSE),0) -> 41140.44 | F70: =E70 +L70 -> 41140.44 | G70: =IFERROR(VLOOKUP(B70,'ACDOCA - Paste Data'!B:H,7,FALSE),0) -> 38387.96 | H70: =G70+M70 -> 38387.96 | I70: =F70-H70 -> 2752.48 | J70: =IFERROR(I70/F70,0) -> 0.066904486 | K70: =IFERROR(VLOOKUP(B70,'WIP - Paste Data'!B:E,4,FALSE),"") -> 431858.13 | P70: =IFERROR(VLOOKUP(B70,'JTD Paste Data'!A:B,2,FALSE),"0") -> 2326600.9 | Q70: =SUM(P70+L70) -> 2326600.9 | R70: =IFERROR(VLOOKUP(B70,'JTD Paste Data'!A:C,3,FALSE),"0") -> 2214162.9 | S70: =SUM(R70+M70) -> 2214162.9 | T70: =SUM(Q70-S70) -> 112438.01 | U70: =IFERROR(T70/Q70,0) -> 0.048327159
A71: =VLOOKUP(B71,'SAP Contracts'!A:J,10,FALSE) -> Google-Fiber Greenfield TX | B71: =VLOOKUP(C71,'Active North Sky Projects'!C:D,2,FALSE) -> 21129 | C71: 2445099 | D71: =IFERROR(VLOOKUP(B71,'MTD Hours Paste Data'!A:C,3,FALSE),"") -> 0 | E71: =IFERROR(VLOOKUP(B71,'ACDOCA - Paste Data'!B:G,6,FALSE),0) -> 0 | F71: =E71 +L71 -> 0 | G71: =IFERROR(VLOOKUP(B71,'ACDOCA - Paste Data'!B:H,7,FALSE),0) -> 974.25 | H71: =G71+M71 -> 974.25 | I71: =F71-H71 -> -974.25 | J71: =IFERROR(I71/F71,0) -> 0 | K71: =IFERROR(VLOOKUP(B71,'WIP - Paste Data'!B:E,4,FALSE),"") -> 204700.4 | P71: =IFERROR(VLOOKUP(B71,'JTD Paste Data'!A:B,2,FALSE),"0") -> 516738.6 | Q71: =SUM(P71+L71) -> 516738.6 | R71: =IFERROR(VLOOKUP(B71,'JTD Paste Data'!A:C,3,FALSE),"0") -> 430691.71 | S71: =SUM(R71+M71) -> 430691.71 | T71: =SUM(Q71-S71) -> 86046.89 | U71: =IFERROR(T71/Q71,0) -> 0.16651918
A72: =VLOOKUP(B72,'SAP Contracts'!A:J,10,FALSE) -> Google-Google Fiber MSA (AZ) | B72: =VLOOKUP(C72,'Active North Sky Projects'!C:D,2,FALSE) -> 21672 | C72: 2036000 | D72: =IFERROR(VLOOKUP(B72,'MTD Hours Paste Data'!A:C,3,FALSE),"") -> 196.3 | E72: =IFERROR(VLOOKUP(B72,'ACDOCA - Paste Data'!B:G,6,FALSE),0) -> 45666 | F72: =E72 +L72 -> 45666 | G72: =IFERROR(VLOOKUP(B72,'ACDOCA - Paste Data'!B:H,7,FALSE),0) -> 38955.29 | H72: =G72+M72 -> 38955.29 | I72: =F72-H72 -> 6710.71 | J72: =IFERROR(I72/F72,0) -> 0.146952 | K72: =IFERROR(VLOOKUP(B72,'WIP - Paste Data'!B:E,4,FALSE),"") -> 581770 | P72: =IFERROR(VLOOKUP(B72,'JTD Paste Data'!A:B,2,FALSE),"0") -> 902969 | Q72: =SUM(P72+L72) -> 902969 | R72: =IFERROR(VLOOKUP(B72,'JTD Paste Data'!A:C,3,FALSE),"0") -> 849107.64 | S72: =SUM(R72+M72) -> 849107.64 | T72: =SUM(Q72-S72) -> 53861.36 | U72: =IFERROR(T72/Q72,0) -> 0.05964918
A73: =VLOOKUP(B73,'SAP Contracts'!A:J,10,FALSE) -> Google-Google Fiber MSA (TX) | B73: =VLOOKUP(C73,'Active North Sky Projects'!C:D,2,FALSE) -> 21595 | C73: 2443000 | D73: =IFERROR(VLOOKUP(B73,'MTD Hours Paste Data'!A:C,3,FALSE),"") -> 221.85 | E73: =IFERROR(VLOOKUP(B73,'ACDOCA - Paste Data'!B:G,6,FALSE),0) -> 159793.5 | F73: =E73 +L73 -> 159793.5 | G73: =IFERROR(VLOOKUP(B73,'ACDOCA - Paste Data'!B:H,7,FALSE),0) -> 129416.27 | H73: =G73+M73 -> 129416.27 | I73: =F73-H73 -> 30377.23 | J73: =IFERROR(I73/F73,0) -> 0.19010304 | K73: =IFERROR(VLOOKUP(B73,'WIP - Paste Data'!B:E,4,FALSE),"") -> 480460.1 | P73: =IFERROR(VLOOKUP(B73,'JTD Paste Data'!A:B,2,FALSE),"0") -> 5555238 | Q73: =SUM(P73+L73) -> 5555238 | R73: =IFERROR(VLOOKUP(B73,'JTD Paste Data'!A:C,3,FALSE),"0") -> 4896830.5 | S73: =SUM(R73+M73) -> 4896830.5 | T73: =SUM(Q73-S73) -> 658407.43 | U73: =IFERROR(T73/Q73,0) -> 0.11852011
A74: =VLOOKUP(B74,'SAP Contracts'!A:J,10,FALSE) -> Mereo 89, LLC Glenn Apts AZ | B74: 21674 | C74: 2036021 | D74: =IFERROR(VLOOKUP(B74,'MTD Hours Paste Data'!A:C,3,FALSE),"") -> 11.6 | E74: =IFERROR(VLOOKUP(B74,'ACDOCA - Paste Data'!B:G,6,FALSE),0) -> 9492 | F74: =E74 +L74 -> 9492 | G74: =IFERROR(VLOOKUP(B74,'ACDOCA - Paste Data'!B:H,7,FALSE),0) -> 1929.23 | H74: =G74+M74 -> 1929.23 | I74: =F74-H74 -> 7562.77 | J74: =IFERROR(I74/F74,0) -> 0.796752 | K74: =IFERROR(VLOOKUP(B74,'WIP - Paste Data'!B:E,4,FALSE),"") -> 89496 | P74: =IFERROR(VLOOKUP(B74,'JTD Paste Data'!A:B,2,FALSE),"0") -> 89496 | Q74: =SUM(P74+L74) -> 89496 | R74: =IFERROR(VLOOKUP(B74,'JTD Paste Data'!A:C,3,FALSE),"0") -> 26801.31 | S74: =SUM(R74+M74) -> 26801.31 | T74: =SUM(Q74-S74) -> 62694.69 | U74: =IFERROR(T74/Q74,0) -> 0.70053064
A75: =VLOOKUP(B75,'SAP Contracts'!A:J,10,FALSE) -> Mereo 89, LLC AZ | B75: 21673 | C75: 2036019 | D75: =IFERROR(VLOOKUP(B75,'MTD Hours Paste Data'!A:C,3,FALSE),"") | E75: =IFERROR(VLOOKUP(B75,'ACDOCA - Paste Data'!B:G,6,FALSE),0) -> 0 | F75: =E75 +L75 -> 0 | G75: =IFERROR(VLOOKUP(B75,'ACDOCA - Paste Data'!B:H,7,FALSE),0) -> 0 | H75: =G75+M75 -> 0 | I75: =F75-H75 -> 0 | J75: =IFERROR(I75/F75,0) -> 0 | K75: =IFERROR(VLOOKUP(B75,'WIP - Paste Data'!B:E,4,FALSE),"") | P75: =IFERROR(VLOOKUP(B75,'JTD Paste Data'!A:B,2,FALSE),"0") -> 0 | Q75: =SUM(P75+L75) -> 0 | R75: =IFERROR(VLOOKUP(B75,'JTD Paste Data'!A:C,3,FALSE),"0") -> 204.4 | S75: =SUM(R75+M75) -> 204.4 | T75: =SUM(Q75-S75) -> -204.4 | U75: =IFERROR(T75/Q75,0) -> 0
A76: Mereo 89, LLC Visconti Apts AZ | B76: 21044 | C76: 2036022 | D76: =IFERROR(VLOOKUP(B76,'MTD Hours Paste Data'!A:C,3,FALSE),"") -> 0 | E76: =IFERROR(VLOOKUP(B76,'ACDOCA - Paste Data'!B:G,6,FALSE),0) -> 12204 | F76: =E76 +L76 -> 12204 | G76: =IFERROR(VLOOKUP(B76,'ACDOCA - Paste Data'!B:H,7,FALSE),0) -> 1293.27 | H76: =G76+M76 -> 1293.27 | I76: =F76-H76 -> 10910.73 | J76: =IFERROR(I76/F76,0) -> 0.89402901 | K76: =IFERROR(VLOOKUP(B76,'WIP - Paste Data'!B:E,4,FALSE),"") -> 12204 | P76: =IFERROR(VLOOKUP(B76,'JTD Paste Data'!A:B,2,FALSE),"0") -> 12204 | Q76: =SUM(P76+L76) -> 12204 | R76: =IFERROR(VLOOKUP(B76,'JTD Paste Data'!A:C,3,FALSE),"0") -> 1293.27 | S76: =SUM(R76+M76) -> 1293.27 | T76: =SUM(Q76-S76) -> 10910.73 | U76: =IFERROR(T76/Q76,0) -> 0.89402901
A77: =VLOOKUP(B77,'SAP Contracts'!A:J,10,FALSE) -> Socket Telecom, LLC - MO (Installs) | B77: =VLOOKUP(C77,'Active North Sky Projects'!C:D,2,FALSE) -> 21189 | C77: 2660000 | D77: =IFERROR(VLOOKUP(B77,'MTD Hours Paste Data'!A:C,3,FALSE),"") -> 293.56 | E77: =IFERROR(VLOOKUP(B77,'ACDOCA - Paste Data'!B:G,6,FALSE),0) -> 4990.7 | F77: =E77 +L77 -> 4990.7 | G77: =IFERROR(VLOOKUP(B77,'ACDOCA - Paste Data'!B:H,7,FALSE),0) -> 20406.49 | H77: =G77+M77 -> 20406.49 | I77: =F77-H77 -> -15415.79 | J77: =IFERROR(I77/F77,0) -> -3.0889034 | K77: =IFERROR(VLOOKUP(B77,'WIP - Paste Data'!B:E,4,FALSE),"") -> 48955 | P77: =IFERROR(VLOOKUP(B77,'JTD Paste Data'!A:B,2,FALSE),"0") -> 276545 | Q77: =SUM(P77+L77) -> 276545 | R77: =IFERROR(VLOOKUP(B77,'JTD Paste Data'!A:C,3,FALSE),"0") -> 329088.45 | S77: =SUM(R77+M77) -> 329088.45 | T77: =SUM(Q77-S77) -> -52543.45 | U77: =IFERROR(T77/Q77,0) -> -0.18999964
A78: =VLOOKUP(B78,'SAP Contracts'!A:J,10,FALSE) -> Socket Telecom, LLC - MO (MDU) | B78: =VLOOKUP(C78,'Active North Sky Projects'!C:D,2,FALSE) -> 21202 | C78: 2660001 | D78: =IFERROR(VLOOKUP(B78,'MTD Hours Paste Data'!A:C,3,FALSE),"") -> 127.19 | E78: =IFERROR(VLOOKUP(B78,'ACDOCA - Paste Data'!B:G,6,FALSE),0) -> 13412.5 | F78: =E78 +L78 -> 13412.5 | G78: =IFERROR(VLOOKUP(B78,'ACDOCA - Paste Data'!B:H,7,FALSE),0) -> 14222.34 | H78: =G78+M78 -> 14222.34 | I78: =F78-H78 -> -809.84 | J78: =IFERROR(I78/F78,0) -> -0.060379497 | K78: =IFERROR(VLOOKUP(B78,'WIP - Paste Data'!B:E,4,FALSE),"") -> 129192.5 | P78: =IFERROR(VLOOKUP(B78,'JTD Paste Data'!A:B,2,FALSE),"0") -> 1550286 | Q78: =SUM(P78+L78) -> 1550286 | R78: =IFERROR(VLOOKUP(B78,'JTD Paste Data'!A:C,3,FALSE),"0") -> 1263189.5 | S78: =SUM(R78+M78) -> 1263189.5 | T78: =SUM(Q78-S78) -> 287096.5 | U78: =IFERROR(T78/Q78,0) -> 0.18518938
A79: =VLOOKUP(B79,'SAP Contracts'!A:J,10,FALSE) -> Ubiquity Serivces-Renaissance at Stoney | B79: =VLOOKUP(C79,'Active North Sky Projects'!C:D,2,FALSE) -> 21477 | C79: 2446104 | D79: =IFERROR(VLOOKUP(B79,'MTD Hours Paste Data'!A:C,3,FALSE),"") | E79: =IFERROR(VLOOKUP(B79,'ACDOCA - Paste Data'!B:G,6,FALSE),0) -> 0 | F79: =E79 +L79 -> 0 | G79: =IFERROR(VLOOKUP(B79,'ACDOCA - Paste Data'!B:H,7,FALSE),0) -> 0 | H79: =G79+M79 -> 0 | I79: =F79-H79 -> 0 | J79: =IFERROR(I79/F79,0) -> 0 | K79: =IFERROR(VLOOKUP(B79,'WIP - Paste Data'!B:E,4,FALSE),"") | P79: =IFERROR(VLOOKUP(B79,'JTD Paste Data'!A:B,2,FALSE),"0") -> 0 | Q79: =SUM(P79+L79) -> 0 | R79: =IFERROR(VLOOKUP(B79,'JTD Paste Data'!A:C,3,FALSE),"0") -> 0 | S79: =SUM(R79+M79) -> 0 | T79: =SUM(Q79-S79) -> 0 | U79: =IFERROR(T79/Q79,0) -> 0
A80: =VLOOKUP(B80,'SAP Contracts'!A:J,10,FALSE) -> Ubiquity Services - Bluffs at Brookside | B80: =VLOOKUP(C80,'Active North Sky Projects'!C:D,2,FALSE) -> 21467 | C80: 2446103 | D80: =IFERROR(VLOOKUP(B80,'MTD Hours Paste Data'!A:C,3,FALSE),"") | E80: =IFERROR(VLOOKUP(B80,'ACDOCA - Paste Data'!B:G,6,FALSE),0) -> 0 | F80: =E80 +L80 -> 0 | G80: =IFERROR(VLOOKUP(B80,'ACDOCA - Paste Data'!B:H,7,FALSE),0) -> 0 | H80: =G80+M80 -> 0 | I80: =F80-H80 -> 0 | J80: =IFERROR(I80/F80,0) -> 0 | K80: =IFERROR(VLOOKUP(B80,'WIP - Paste Data'!B:E,4,FALSE),"") | P80: =IFERROR(VLOOKUP(B80,'JTD Paste Data'!A:B,2,FALSE),"0") -> 0 | Q80: =SUM(P80+L80) -> 0 | R80: =IFERROR(VLOOKUP(B80,'JTD Paste Data'!A:C,3,FALSE),"0") -> 0 | S80: =SUM(R80+M80) -> 0 | T80: =SUM(Q80-S80) -> 0 | U80: =IFERROR(T80/Q80,0) -> 0
A81: =VLOOKUP(B81,'SAP Contracts'!A:J,10,FALSE) -> Ubiquity Services-Bay Colony Apt Homes | B81: =VLOOKUP(C81,'Active North Sky Projects'!C:D,2,FALSE) -> 21456 | C81: 2446101 | D81: =IFERROR(VLOOKUP(B81,'MTD Hours Paste Data'!A:C,3,FALSE),"") | E81: =IFERROR(VLOOKUP(B81,'ACDOCA - Paste Data'!B:G,6,FALSE),0) -> 0 | F81: =E81 +L81 -> 0 | G81: =IFERROR(VLOOKUP(B81,'ACDOCA - Paste Data'!B:H,7,FALSE),0) -> 0 | H81: =G81+M81 -> 0 | I81: =F81-H81 -> 0 | J81: =IFERROR(I81/F81,0) -> 0 | K81: =IFERROR(VLOOKUP(B81,'WIP - Paste Data'!B:E,4,FALSE),"") | P81: =IFERROR(VLOOKUP(B81,'JTD Paste Data'!A:B,2,FALSE),"0") -> 0 | Q81: =SUM(P81+L81) -> 0 | R81: =IFERROR(VLOOKUP(B81,'JTD Paste Data'!A:C,3,FALSE),"0") -> 0 | S81: =SUM(R81+M81) -> 0 | T81: =SUM(Q81-S81) -> 0 | U81: =IFERROR(T81/Q81,0) -> 0
A82: =VLOOKUP(B82,'SAP Contracts'!A:J,10,FALSE) -> Ubiquity Services-Heatherwilde Park | B82: =VLOOKUP(C82,'Active North Sky Projects'!C:D,2,FALSE) -> 21904 | C82: 2446105 | D82: =IFERROR(VLOOKUP(B82,'MTD Hours Paste Data'!A:C,3,FALSE),"") | E82: =IFERROR(VLOOKUP(B82,'ACDOCA - Paste Data'!B:G,6,FALSE),0) -> 0 | F82: =E82 +L82 -> 0 | G82: =IFERROR(VLOOKUP(B82,'ACDOCA - Paste Data'!B:H,7,FALSE),0) -> 0 | H82: =G82+M82 -> 0 | I82: =F82-H82 -> 0 | J82: =IFERROR(I82/F82,0) -> 0 | K82: =IFERROR(VLOOKUP(B82,'WIP - Paste Data'!B:E,4,FALSE),"") -> 7200 | P82: =IFERROR(VLOOKUP(B82,'JTD Paste Data'!A:B,2,FALSE),"0") -> 7200 | Q82: =SUM(P82+L82) -> 7200 | R82: =IFERROR(VLOOKUP(B82,'JTD Paste Data'!A:C,3,FALSE),"0") -> 9041 | S82: =SUM(R82+M82) -> 9041 | T82: =SUM(Q82-S82) -> -1841 | U82: =IFERROR(T82/Q82,0) -> -0.25569444
A83: =VLOOKUP(B83,'SAP Contracts'!A:J,10,FALSE) -> Ubiquity Services-Retreat at City Center | B83: =VLOOKUP(C83,'Active North Sky Projects'!C:D,2,FALSE) -> 21249 | C83: 2066100 | D83: =IFERROR(VLOOKUP(B83,'MTD Hours Paste Data'!A:C,3,FALSE),"") -> 0 | E83: =IFERROR(VLOOKUP(B83,'ACDOCA - Paste Data'!B:G,6,FALSE),0) -> 0 | F83: =E83 +L83 -> 0 | G83: =IFERROR(VLOOKUP(B83,'ACDOCA - Paste Data'!B:H,7,FALSE),0) -> 1860 | H83: =G83+M83 -> 1860 | I83: =F83-H83 -> -1860 | J83: =IFERROR(I83/F83,0) -> 0 | K83: =IFERROR(VLOOKUP(B83,'WIP - Paste Data'!B:E,4,FALSE),"") -> 45145.5 | P83: =IFERROR(VLOOKUP(B83,'JTD Paste Data'!A:B,2,FALSE),"0") -> 150485 | Q83: =SUM(P83+L83) -> 150485 | R83: =IFERROR(VLOOKUP(B83,'JTD Paste Data'!A:C,3,FALSE),"0") -> 131070.99 | S83: =SUM(R83+M83) -> 131070.99 | T83: =SUM(Q83-S83) -> 19414.01 | U83: =IFERROR(T83/Q83,0) -> 0.1290096
A84: Total Structured Wiring - Bryan | B84: PCC | E84: =SUM(E47:E83) -> 615293.78 | F84: =SUM(F47:F83) -> 615293.78 | G84: =SUM(G47:G83) -> 480267.75 | H84: =SUM(H47:H83) -> 480267.75 | I84: =F84-H84 -> 135026.03 | J84: =IFERROR(I84/F84,0) -> 0.21944969 | K84: =SUM(K47:K83) -> 2708409.1 | L84: =SUM(L48:L83) -> 0 | M84: =SUM(M48:M83) -> 0 | P84: =SUM(P47:P83) -> 18616127 | Q84: =SUM(Q47:Q83) -> 18616127 | R84: =SUM(R47:R83) -> 15604896 | S84: =SUM(S47:S83) -> 15604896 | T84: =SUM(T47:T83) -> 3011231.4 | U84: =IFERROR(T84/Q84,0) -> 0.16175391
A85: Total Division 2 Projects | E85: =E45+E37+E84 -> 938832.09 | F85: =F45+F37+F84 -> 938832.09 | G85: =G45+G37+G84 -> 794369.75 | H85: =H45+H37+H84 -> 794369.75 | I85: =F85-H85 -> 144462.34 | J85: =IFERROR(I85/F85,0) -> 0.15387452 | K85: =K45+K37+K84 -> 4949450 | L85: =L45+L37+L84 -> 0 | M85: =M45+M37+M84 -> 0
A86: June Prelim Forecast Division 2 | F86: 1850000 | I86: 315320 | J86: 0.15
A87: % Achieved for June to date (target 50+%) | F87: =IFERROR(F85/F86,0) -> 0.50747681 | I87: =IFERROR(I85/I86,0) -> 0.45814519
A89: Division 1 - Construction
A90: Region 1 - Lumen
A91: LE/Consumer
A92: =VLOOKUP(B92,'SAP Contracts'!A:J,10,FALSE) -> Lumen-Consumer NE WA (2022-25) | B92: =VLOOKUP(C92,'Active North Sky Projects'!C:D,2,FALSE) -> 21651 | C92: 1483077 | D92: =IFERROR(VLOOKUP(B92,'MTD Hours Paste Data'!A:C,3,FALSE),"") -> 141.92 | E92: =IFERROR(VLOOKUP(B92,'ACDOCA - Paste Data'!B:G,6,FALSE),0) -> 25914.38 | F92: =E92 +L92 -> 25914.38 | G92: =IFERROR(VLOOKUP(B92,'ACDOCA - Paste Data'!B:H,7,FALSE),0) -> 21140.4 | H92: =G92+M92 -> 21140.4 | I92: =F92-H92 -> 4773.98 | J92: =IFERROR(I92/F92,0) -> 0.18422127 | K92: =IFERROR(VLOOKUP(B92,'WIP - Paste Data'!B:E,4,FALSE),"") -> 475565.31 | P92: =IFERROR(VLOOKUP(B92,'JTD Paste Data'!A:B,2,FALSE),"0") -> 8902342.1 | Q92: =SUM(P92+L92) -> 8902342.1 | R92: =IFERROR(VLOOKUP(B92,'JTD Paste Data'!A:C,3,FALSE),"0") -> 8755043.6 | S92: =SUM(R92+M92) -> 8755043.6 | T92: =SUM(Q92-S92) -> 147298.49 | U92: =IFERROR(T92/Q92,0) -> 0.016546038
A93: =VLOOKUP(B93,'SAP Contracts'!A:J,10,FALSE) -> Lumen - Northeast WA Consumer (2026-28) | B93: =VLOOKUP(C93,'Active North Sky Projects'!C:D,2,FALSE) -> 21300 | C93: 1486278 | D93: =IFERROR(VLOOKUP(B93,'MTD Hours Paste Data'!A:C,3,FALSE),"") -> 1029.08 | E93: =IFERROR(VLOOKUP(B93,'ACDOCA - Paste Data'!B:G,6,FALSE),0) -> 146685.94 | F93: =E93 +L93 -> 146685.94 | G93: =IFERROR(VLOOKUP(B93,'ACDOCA - Paste Data'!B:H,7,FALSE),0) -> 151894.36 | H93: =G93+M93 -> 151894.36 | I93: =F93-H93 -> -5208.42 | J93: =IFERROR(I93/F93,0) -> -0.035507289 | K93: =IFERROR(VLOOKUP(B93,'WIP - Paste Data'!B:E,4,FALSE),"") -> 926118.99 | P93: =IFERROR(VLOOKUP(B93,'JTD Paste Data'!A:B,2,FALSE),"0") -> 1139669.8 | Q93: =SUM(P93+L93) -> 1139669.8 | R93: =IFERROR(VLOOKUP(B93,'JTD Paste Data'!A:C,3,FALSE),"0") -> 1060602.4 | S93: =SUM(R93+M93) -> 1060602.4 | T93: =SUM(Q93-S93) -> 79067.39 | U93: =IFERROR(T93/Q93,0) -> 0.069377455
A94: =VLOOKUP(B94,'SAP Contracts'!A:J,10,FALSE) -> Lumen-2023 San Juans Consumer | B94: =VLOOKUP(C94,'Active North Sky Projects'!C:D,2,FALSE) -> 21309 | C94: 1483098 | D94: =IFERROR(VLOOKUP(B94,'MTD Hours Paste Data'!A:C,3,FALSE),"") -> 0 | E94: =IFERROR(VLOOKUP(B94,'ACDOCA - Paste Data'!B:G,6,FALSE),0) -> 0 | F94: =E94 +L94 -> 0 | G94: =IFERROR(VLOOKUP(B94,'ACDOCA - Paste Data'!B:H,7,FALSE),0) -> 145.95 | H94: =G94+M94 -> 145.95 | I94: =F94-H94 -> -145.95 | J94: =IFERROR(I94/F94,0) -> 0 | K94: =IFERROR(VLOOKUP(B94,'WIP - Paste Data'!B:E,4,FALSE),"") -> 17348.69 | P94: =IFERROR(VLOOKUP(B94,'JTD Paste Data'!A:B,2,FALSE),"0") -> 337069.47 | Q94: =SUM(P94+L94) -> 337069.47 | R94: =IFERROR(VLOOKUP(B94,'JTD Paste Data'!A:C,3,FALSE),"0") -> 256091.34 | S94: =SUM(R94+M94) -> 256091.34 | T94: =SUM(Q94-S94) -> 80978.13 | U94: =IFERROR(T94/Q94,0) -> 0.24024166
A95: =VLOOKUP(B95,'SAP Contracts'!A:J,10,FALSE) -> Lumen - San Juans WA Consumer (2026-28) | B95: =VLOOKUP(C95,'Active North Sky Projects'!C:D,2,FALSE) -> 21642 | C95: 1486279 | D95: =IFERROR(VLOOKUP(B95,'MTD Hours Paste Data'!A:C,3,FALSE),"") -> 0 | E95: =IFERROR(VLOOKUP(B95,'ACDOCA - Paste Data'!B:G,6,FALSE),0) -> 0 | F95: =E95 +L95 -> 0 | G95: =IFERROR(VLOOKUP(B95,'ACDOCA - Paste Data'!B:H,7,FALSE),0) -> 0 | H95: =G95+M95 -> 0 | I95: =F95-H95 -> 0 | J95: =IFERROR(I95/F95,0) -> 0 | K95: =IFERROR(VLOOKUP(B95,'WIP - Paste Data'!B:E,4,FALSE),"") -> 962.74 | P95: =IFERROR(VLOOKUP(B95,'JTD Paste Data'!A:B,2,FALSE),"0") -> 962.74 | Q95: =SUM(P95+L95) -> 962.74 | R95: =IFERROR(VLOOKUP(B95,'JTD Paste Data'!A:C,3,FALSE),"0") -> 3209.37 | S95: =SUM(R95+M95) -> 3209.37 | T95: =SUM(Q95-S95) -> -2246.63 | U95: =IFERROR(T95/Q95,0) -> -2.3335792
A96: =VLOOKUP(B96,'SAP Contracts'!A:J,10,FALSE) -> Lumen-2023 WA Consumer | B96: =VLOOKUP(C96,'Active North Sky Projects'!C:D,2,FALSE) -> 21310 | C96: 1483099 | D96: =IFERROR(VLOOKUP(B96,'MTD Hours Paste Data'!A:C,3,FALSE),"") -> 355.18 | E96: =IFERROR(VLOOKUP(B96,'ACDOCA - Paste Data'!B:G,6,FALSE),0) -> 208669.69 | F96: =E96 +L96 -> 208669.69 | G96: =IFERROR(VLOOKUP(B96,'ACDOCA - Paste Data'!B:H,7,FALSE),0) -> 151348.5 | H96: =G96+M96 -> 151348.5 | I96: =F96-H96 -> 57321.19 | J96: =IFERROR(I96/F96,0) -> 0.27469821 | K96: =IFERROR(VLOOKUP(B96,'WIP - Paste Data'!B:E,4,FALSE),"") -> 9340613.7 | P96: =IFERROR(VLOOKUP(B96,'JTD Paste Data'!A:B,2,FALSE),"0") -> 60179589 | Q96: =SUM(P96+L96) -> 60179589 | R96: =IFERROR(VLOOKUP(B96,'JTD Paste Data'!A:C,3,FALSE),"0") -> 58374113 | S96: =SUM(R96+M96) -> 58374113 | T96: =SUM(Q96-S96) -> 1805476.1 | U96: =IFERROR(T96/Q96,0) -> 0.03000147
A97: =VLOOKUP(B97,'SAP Contracts'!A:J,10,FALSE) -> Lumen - West WA Consumer (2026-28) | B97: =VLOOKUP(C97,'Active North Sky Projects'!C:D,2,FALSE) -> 21666 | C97: 1486280 | D97: =IFERROR(VLOOKUP(B97,'MTD Hours Paste Data'!A:C,3,FALSE),"") -> 2047.72 | E97: =IFERROR(VLOOKUP(B97,'ACDOCA - Paste Data'!B:G,6,FALSE),0) -> 865935.83 | F97: =E97 +L97 -> 865935.83 | G97: =IFERROR(VLOOKUP(B97,'ACDOCA - Paste Data'!B:H,7,FALSE),0) -> 856676.49 | H97: =G97+M97 -> 856676.49 | I97: =F97-H97 -> 9259.34 | J97: =IFERROR(I97/F97,0) -> 0.010692871 | K97: =IFERROR(VLOOKUP(B97,'WIP - Paste Data'!B:E,4,FALSE),"") -> 5221154 | P97: =IFERROR(VLOOKUP(B97,'JTD Paste Data'!A:B,2,FALSE),"0") -> 6240379.3 | Q97: =SUM(P97+L97) -> 6240379.3 | R97: =IFERROR(VLOOKUP(B97,'JTD Paste Data'!A:C,3,FALSE),"0") -> 6022624.6 | S97: =SUM(R97+M97) -> 6022624.6 | T97: =SUM(Q97-S97) -> 217754.63 | U97: =IFERROR(T97/Q97,0) -> 0.034894454
A98: =VLOOKUP(B98,'SAP Contracts'!A:J,10,FALSE) -> Lumen - West WA Drops (2026-28) | B98: =VLOOKUP(C98,'Active North Sky Projects'!C:D,2,FALSE) -> 21301 | C98: 1486281 | D98: =IFERROR(VLOOKUP(B98,'MTD Hours Paste Data'!A:C,3,FALSE),"") -> 229.31 | E98: =IFERROR(VLOOKUP(B98,'ACDOCA - Paste Data'!B:G,6,FALSE),0) -> 41057.08 | F98: =E98 +L98 -> 41057.08 | G98: =IFERROR(VLOOKUP(B98,'ACDOCA - Paste Data'!B:H,7,FALSE),0) -> 36749.82 | H98: =G98+M98 -> 36749.82 | I98: =F98-H98 -> 4307.26 | J98: =IFERROR(I98/F98,0) -> 0.10490907 | K98: =IFERROR(VLOOKUP(B98,'WIP - Paste Data'!B:E,4,FALSE),"") -> 111518.87 | P98: =IFERROR(VLOOKUP(B98,'JTD Paste Data'!A:B,2,FALSE),"0") -> 138474.53 | Q98: =SUM(P98+L98) -> 138474.53 | R98: =IFERROR(VLOOKUP(B98,'JTD Paste Data'!A:C,3,FALSE),"0") -> 164993.97 | S98: =SUM(R98+M98) -> 164993.97 | T98: =SUM(Q98-S98) -> -26519.44 | U98: =IFERROR(T98/Q98,0) -> -0.19151132
A99: GPON & Enterprise | G99: =IFERROR(VLOOKUP(B99,'ACDOCA - Paste Data'!B:H,7,FALSE),0) -> 0 | T99: =SUM(Q99-S99) -> 0 | U99: =IFERROR(T99/Q99,0) -> 0
A100: =VLOOKUP(B100,'SAP Contracts'!A:J,10,FALSE) -> Lumen - 2025LE000148 Fiber Overbuild | B100: =VLOOKUP(C100,'Active North Sky Projects'!C:D,2,FALSE) -> 21677 | C100: 1486125 | D100: =IFERROR(VLOOKUP(B100,'MTD Hours Paste Data'!A:C,3,FALSE),"") -> 177.15 | E100: =IFERROR(VLOOKUP(B100,'ACDOCA - Paste Data'!B:G,6,FALSE),0) -> 231120.22 | F100: =E100 +L100 -> 231120.22 | G100: =IFERROR(VLOOKUP(B100,'ACDOCA - Paste Data'!B:H,7,FALSE),0) -> 168665.32 | H100: =G100+M100 -> 168665.32 | I100: =F100-H100 -> 62454.9 | J100: =IFERROR(I100/F100,0) -> 0.2702269 | K100: =IFERROR(VLOOKUP(B100,'WIP - Paste Data'!B:E,4,FALSE),"") -> 4200144.5 | P100: =IFERROR(VLOOKUP(B100,'JTD Paste Data'!A:B,2,FALSE),"0") -> 5115310 | Q100: =SUM(P100+L100) -> 5115310 | R100: =IFERROR(VLOOKUP(B100,'JTD Paste Data'!A:C,3,FALSE),"0") -> 4101468.6 | S100: =SUM(R100+M100) -> 4101468.6 | T100: =SUM(Q100-S100) -> 1013841.4 | U100: =IFERROR(T100/Q100,0) -> 0.19819745
A101: =VLOOKUP(B101,'SAP Contracts'!A:J,10,FALSE) -> Lumen-2023LE000081 Fiber Overbuild | B101: =VLOOKUP(C101,'Active North Sky Projects'!C:D,2,FALSE) -> 21302 | C101: 1483096 | D101: =IFERROR(VLOOKUP(B101,'MTD Hours Paste Data'!A:C,3,FALSE),"") | E101: =IFERROR(VLOOKUP(B101,'ACDOCA - Paste Data'!B:G,6,FALSE),0) -> 0 | F101: =E101 +L101 -> 0 | G101: =IFERROR(VLOOKUP(B101,'ACDOCA - Paste Data'!B:H,7,FALSE),0) -> 0 | H101: =G101+M101 -> 0 | I101: =F101-H101 -> 0 | J101: =IFERROR(I101/F101,0) -> 0 | K101: =IFERROR(VLOOKUP(B101,'WIP - Paste Data'!B:E,4,FALSE),"") | P101: =IFERROR(VLOOKUP(B101,'JTD Paste Data'!A:B,2,FALSE),"0") -> 4751484.1 | Q101: =SUM(P101+L101) -> 4751484.1 | R101: =IFERROR(VLOOKUP(B101,'JTD Paste Data'!A:C,3,FALSE),"0") -> 4534612.8 | S101: =SUM(R101+M101) -> 4534612.8 | T101: =SUM(Q101-S101) -> 216871.27 | U101: =IFERROR(T101/Q101,0) -> 0.045642849
...

Sheet CX
A3: Job No | B3: Description | C3: MGR Report
A4: 00EQUIP | B4: 00-Shop Equipment | C4: =VLOOKUP(A4,MGR!A:A,2,FALSE) -> #N/A
A5: 00INDOH | B5: 00 - Indirect Cost | C5: =VLOOKUP(A5,MGR!A:A,2,FALSE) -> #N/A
A6: 1055129 | B6: ATT-Douglas City Bridge | C6: =VLOOKUP(A6,MGR!A:A,2,FALSE) -> #N/A
A7: 1055133 | B7: Siskiyou Tel-Mugginsville | C7: =VLOOKUP(A7,MGR!A:A,2,FALSE) -> #N/A
A8: 1055134 | B8: Siskiyou Tel-West Horse Creek | C8: =VLOOKUP(A8,MGR!A:A,2,FALSE) -> #N/A
A9: 1055196 | B9: Siskiyou Tel-Rattlesnake | C9: =VLOOKUP(A9,MGR!A:A,2,FALSE) -> #N/A
A10: 1055210 | B10: CAL-Ore 2024 | C10: =VLOOKUP(A10,MGR!A:A,2,FALSE) -> #N/A
A11: 1056117 | B11: Siskiyou Tel- OSP Routine Maintenance 2 | C11: =VLOOKUP(A11,MGR!A:A,2,FALSE) -> #N/A
A12: 1134140 | B12: Lumen-2022LE000008 Idaho | C12: =VLOOKUP(A12,MGR!A:A,2,FALSE) -> #N/A
A13: 1135184 | B13: Ziply - ID FTTP MSA (Rob) | C13: =VLOOKUP(A13,MGR!A:A,2,FALSE) -> #N/A
A14: 1135204 | B14: Avista - Poleline Substation | C14: =VLOOKUP(A14,MGR!A:A,2,FALSE) -> #N/A
A15: 1135248 | B15: Cogent-14428 Meyers Rd | C15: =VLOOKUP(A15,MGR!A:A,2,FALSE) -> #N/A
... A163: #VALUE! | B163: #VALUE! | C163: =VLOOKUP(A163,MGR!A:A,2,FALSE) -> #N/A
C164: =VLOOKUP(A164,MGR!A:A,2,FALSE) -> #N/A
C165: =VLOOKUP(A165,MGR!A:A,2,FALSE) -> #N/A
C166: =VLOOKUP(A166,MGR!A:A,2,FALSE) -> #N/A
C167: =VLOOKUP(A167,MGR!A:A,2,FALSE) -> #N/A
C168: =VLOOKUP(A168,MGR!A:A,2,FALSE) -> #N/A
C169: =VLOOKUP(A169,MGR!A:A,2,FALSE) -> #N/A
C170: =VLOOKUP(A170,MGR!A:A,2,FALSE) -> #N/A
C171: =VLOOKUP(A171,MGR!A:A,2,FALSE) -> #N/A
C172: =VLOOKUP(A172,MGR!A:A,2,FALSE) -> #N/A
C173: =VLOOKUP(A173,MGR!A:A,2,FALSE) -> #N/A
C174: =VLOOKUP(A174,MGR!A:A,2,FALSE) -> #N/A
C175: =VLOOKUP(A175,MGR!A:A,2,FALSE) -> #N/A
... C197: =VLOOKUP(A197,MGR!A:A,2,FALSE) -> #N/A

Sheet Legacy Lookup Table
D3: This Period | K3: Job - To -Date
A4: Job No | B4: Description | C4: Job | D4: Earned Revenue | E4: Acutal Cost | F4: Gross Profit | G4: GP % | H4: Billed | I4: WIP | J4: Contract Value | K4: JTD Earned Rev | L4: Actual Cost2 | M4: JTD Gross Profit | N4: JTD GP % | O4: CV
A5: =LEFT(C5,FIND(" ",C5)-1) -> #VALUE! | B5: =RIGHT(C5,LEN(C5)-FIND(" ",C5)) -> #VALUE! | C5: 000000 | D5: Projects, Indirect
A6: =LEFT(C6,FIND(" ",C6)-1) -> #VALUE! | B6: =RIGHT(C6,LEN(C6)-FIND(" ",C6)) -> #VALUE!
A7: =LEFT(C7,FIND(" ",C7)-1) -> #VALUE! | B7: =RIGHT(C7,LEN(C7)-FIND(" ",C7)) -> #VALUE! | C7: 0 | D7: 0
A8: =LEFT(C8,FIND(" ",C8)-1) -> #VALUE! | B8: =RIGHT(C8,LEN(C8)-FIND(" ",C8)) -> #VALUE!
A9: =LEFT(C9,FIND(" ",C9)-1) -> #VALUE! | B9: =RIGHT(C9,LEN(C9)-FIND(" ",C9)) -> #VALUE! | D9: 0
A10: =LEFT(C10,FIND(" ",C10)-1) -> 00INDOH | B10: =RIGHT(C10,LEN(C10)-FIND(" ",C10)) -> 00 - Indirect Cost | C10: 00INDOH 00 - Indirect Cost | D10: 10153.5 | E10: 777175.44 | F10: -767021.94 | G10: -7554.2615 | H10: 112638 | I10: 0 | J10: 0 | K10: 112638 | L10: 43187998 | M10: -43075360 | N10: -38242.298
A11: =LEFT(C11,FIND(" ",C11)-1) -> #VALUE! | B11: =RIGHT(C11,LEN(C11)-FIND(" ",C11)) -> #VALUE! | C11: 000000 | D11: Projects, Indirect | E11: 10153.5 | F11: -767021.94 | G11: 112638 | H11: 112638 | I11: -43075360 | J11: 777175.44 | K11: -7554.2615 | L11: 0 | M11: 43187998 | N11: -38242.298
A12: =LEFT(C12,FIND(" ",C12)-1) -> #VALUE! | B12: =RIGHT(C12,LEN(C12)-FIND(" ",C12)) -> #VALUE! | C12: 070771 | D12: Cox, Randy
A13: =LEFT(C13,FIND(" ",C13)-1) -> #VALUE! | B13: =RIGHT(C13,LEN(C13)-FIND(" ",C13)) -> #VALUE!
A14: =LEFT(C14,FIND(" ",C14)-1) -> #VALUE! | B14: =RIGHT(C14,LEN(C14)-FIND(" ",C14)) -> #VALUE! | C14: 0 | D14: 0
A15: =LEFT(C15,FIND(" ",C15)-1) -> #VALUE! | B15: =RIGHT(C15,LEN(C15)-FIND(" ",C15)) -> #VALUE!
A16: =LEFT(C16,FIND(" ",C16)-1) -> #VALUE! | B16: =RIGHT(C16,LEN(C16)-FIND(" ",C16)) -> #VALUE! | D16: 0
A17: =LEFT(C17,FIND(" ",C17)-1) -> 1056119 | B17: =RIGHT(C17,LEN(C17)-FIND(" ",C17)) -> SierraTel - Coarsegold Yosemite - Ph 4A | C17: 1056119 SierraTel - Coarsegold Yosemite - Ph 4A | D17: -36000 | E17: -24771.6 | F17: -11228.4 | G17: 0 | H17: 2912357.4 | I17: -36000 | J17: 0 | K17: 2876357.4 | L17: 2891407.4 | M17: -15050.06 | N17: -0.52323332
A18: =LEFT(C18,FIND(" ",C18)-1) -> #VALUE! | B18: =RIGHT(C18,LEN(C18)-FIND(" ",C18)) -> #VALUE!
A19: =LEFT(C19,FIND(" ",C19)-1) -> #VALUE! | B19: =RIGHT(C19,LEN(C19)-FIND(" ",C19)) -> #VALUE! | C19: 0 | D19: 0
A20: =LEFT(C20,FIND(" ",C20)-1) -> #VALUE! | B20: =RIGHT(C20,LEN(C20)-FIND(" ",C20)) -> #VALUE!
A21: =LEFT(C21,FIND(" ",C21)-1) -> #VALUE! | B21: =RIGHT(C21,LEN(C21)-FIND(" ",C21)) -> #VALUE! | D21: 0
A22: =LEFT(C22,FIND(" ",C22)-1) -> 1056136 | B22: =RIGHT(C22,LEN(C22)-FIND(" ",C22)) -> Frontier - Maint SSP Valley (2025-27) | C22: 1056136 Frontier - Maint SSP Valley (2025-27) | D22: 241329.62 | E22: 219177.3 | F22: 22152.32 | G22: 9.1792794 | H22: 1271043.3 | I22: 463995.06 | J22: 0 | K22: 1735038.4 | L22: 1460289.7 | M22: 274748.64 | N22: 15.835306
A23: =LEFT(C23,FIND(" ",C23)-1) -> #VALUE! | B23: =RIGHT(C23,LEN(C23)-FIND(" ",C23)) -> #VALUE!
A24: =LEFT(C24,FIND(" ",C24)-1) -> #VALUE! | B24: =RIGHT(C24,LEN(C24)-FIND(" ",C24)) -> #VALUE! | C24: 1998809 | D24: 1998809
A25: =LEFT(C25,FIND(" ",C25)-1) -> #VALUE! | B25: =RIGHT(C25,LEN(C25)-FIND(" ",C25)) -> #VALUE!
A26: =LEFT(C26,FIND(" ",C26)-1) -> #VALUE! | B26: =RIGHT(C26,LEN(C26)-FIND(" ",C26)) -> #VALUE! | D26: 0
A27: =LEFT(C27,FIND(" ",C27)-1) -> 1056155 | B27: =RIGHT(C27,LEN(C27)-FIND(" ",C27)) -> Ponderosa - Reconnect 3 - Build 1 | C27: 1056155 Ponderosa - Reconnect 3 - Build 1 | D27: 0 | E27: 1566.25 | F27: -1566.25 | G27: 0 | H27: 1199115.3 | I27: 0 | J27: 1998809 | K27: 1199115.3 | L27: 921004.71 | M27: 278110.59 | N27: 23.192982
A28: =LEFT(C28,FIND(" ",C28)-1) -> #VALUE! | B28: =RIGHT(C28,LEN(C28)-FIND(" ",C28)) -> #VALUE!
A29: =LEFT(C29,FIND(" ",C29)-1) -> #VALUE! | B29: =RIGHT(C29,LEN(C29)-FIND(" ",C29)) -> #VALUE! | C29: 9016.3 | D29: 9016.3
A30: =LEFT(C30,FIND(" ",C30)-1) -> #VALUE! | B30: =RIGHT(C30,LEN(C30)-FIND(" ",C30)) -> #VALUE!
A31: =LEFT(C31,FIND(" ",C31)-1) -> #VALUE! | B31: =RIGHT(C31,LEN(C31)-FIND(" ",C31)) -> #VALUE! | D31: 0
A32: =LEFT(C32,FIND(" ",C32)-1) -> 1056168 | B32: =RIGHT(C32,LEN(C32)-FIND(" ",C32)) -> Lumen - Bakersfield to Delano II - Splic | C32: 1056168 Lumen - Bakersfield to Delano II - Splic | D32: 0 | E32: 0 | F32: 0 | G32: 0 | H32: 12555.3 | I32: -9.094947e-13 | J32: 9016.3 | K32: 12555.3 | L32: 8022.58 | M32: 4532.72 | N32: 36.102045
A33: =LEFT(C33,FIND(" ",C33)-1) -> #VALUE! | B33: =RIGHT(C33,LEN(C33)-FIND(" ",C33)) -> #VALUE!
A34: =LEFT(C34,FIND(" ",C34)-1) -> #VALUE! | B34: =RIGHT(C34,LEN(C34)-FIND(" ",C34)) -> #VALUE! | C34: 71930 | D34: 71930
A35: =LEFT(C35,FIND(" ",C35)-1) -> #VALUE! | B35: =RIGHT(C35,LEN(C35)-FIND(" ",C35)) -> #VALUE!
A36: =LEFT(C36,FIND(" ",C36)-1) -> #VALUE! | B36: =RIGHT(C36,LEN(C36)-FIND(" ",C36)) -> #VALUE! | D36: 0
A37: =LEFT(C37,FIND(" ",C37)-1) -> 1056218 | B37: =RIGHT(C37,LEN(C37)-FIND(" ",C37)) -> BNCSI - Pine Flat to Dam Aerial Feed | C37: 1056218 BNCSI - Pine Flat to Dam Aerial Feed | D37: 0 | E37: 0 | F37: 0 | G37: 0 | H37: 79190 | I37: 0 | J37: 71930 | K37: 79190 | L37: 45732.67 | M37: 33457.33 | N37: 42.249438
A38: =LEFT(C38,FIND(" ",C38)-1) -> #VALUE! | B38: =RIGHT(C38,LEN(C38)-FIND(" ",C38)) -> #VALUE!
A39: =LEFT(C39,FIND(" ",C39)-1) -> #VALUE! | B39: =RIGHT(C39,LEN(C39)-FIND(" ",C39)) -> #VALUE! | C39: 431760 | D39: 431760
A40: =LEFT(C40,FIND(" ",C40)-1) -> #VALUE! | B40: =RIGHT(C40,LEN(C40)-FIND(" ",C40)) -> #VALUE!
A41: =LEFT(C41,FIND(" ",C41)-1) -> #VALUE! | B41: =RIGHT(C41,LEN(C41)-FIND(" ",C41)) -> #VALUE! | D41: 0
A42: =LEFT(C42,FIND(" ",C42)-1) -> 1056282 | B42: =RIGHT(C42,LEN(C42)-FIND(" ",C42)) -> ATT - A05AJGW - Coulterville | C42: 1056282 ATT - A05AJGW - Coulterville | D42: 174232.11 | E42: 257849.01 | F42: -83616.9 | G42: -47.99167 | H42: 0 | I42: 354095.06 | J42: 431760 | K42: 354095.06 | L42: 425639.22 | M42: -71544.16 | N42: -20.204789
A43: =LEFT(C43,FIND(" ",C43)-1) -> #VALUE! | B43: =RIGHT(C43,LEN(C43)-FIND(" ",C43)) -> #VALUE!
A44: =LEFT(C44,FIND(" ",C44)-1) -> #VALUE! | B44: =RIGHT(C44,LEN(C44)-FIND(" ",C44)) -> #VALUE! | C44: 89270 | D44: 89270
A45: =LEFT(C45,FIND(" ",C45)-1) -> #VALUE! | B45: =RIGHT(C45,LEN(C45)-FIND(" ",C45)) -> #VALUE!
A46: =LEFT(C46,FIND(" ",C46)-1) -> #VALUE! | B46: =RIGHT(C46,LEN(C46)-FIND(" ",C46)) -> #VALUE! | D46: 0
A47: =LEFT(C47,FIND(" ",C47)-1) -> 2051013 | B47: =RIGHT(C47,LEN(C47)-FIND(" ",C47)) -> Sprint-Maintenance-Selma | C47: 2051013 Sprint-Maintenance-Selma | D47: 0 | E47: 2375 | F47: -2375 | G47: 0 | H47: 53180.25 | I47: -17122.56 | J47: 89270 | K47: 36057.69 | L47: 28022.39 | M47: 8035.3 | N47: 22.284567
A48: =LEFT(C48,FIND(" ",C48)-1) -> #VALUE! | B48: =RIGHT(C48,LEN(C48)-FIND(" ",C48)) -> #VALUE!
A49: =LEFT(C49,FIND(" ",C49)-1) -> #VALUE! | B49: =RIGHT(C49,LEN(C49)-FIND(" ",C49)) -> #VALUE! | C49: 0 | D49: 0
A50: =LEFT(C50,FIND(" ",C50)-1) -> #VALUE! | B50: =RIGHT(C50,LEN(C50)-FIND(" ",C50)) -> #VALUE!
A51: =LEFT(C51,FIND(" ",C51)-1) -> #VALUE! | B51: =RIGHT(C51,LEN(C51)-FIND(" ",C51)) -> #VALUE! | D51: 0
A52: =LEFT(C52,FIND(" ",C52)-1) -> 2052056 | B52: =RIGHT(C52,LEN(C52)-FIND(" ",C52)) -> Lumen - NAT OSP CENCAL MSA 2022-Selma | C52: 2052056 Lumen - NAT OSP CENCAL MSA 2022-Selma | D52: 0 | E52: 0 | F52: 0 | G52: 0 | H52: 178270.16 | I52: 11945.34 | J52: 0 | K52: 190215.5 | L52: 176044.71 | M52: 14170.79 | N52: 7.4498608
A53: =LEFT(C53,FIND(" ",C53)-1) -> #VALUE! | B53: =RIGHT(C53,LEN(C53)-FIND(" ",C53)) -> #VALUE!
A54: =LEFT(C54,FIND(" ",C54)-1) -> #VALUE! | B54: =RIGHT(C54,LEN(C54)-FIND(" ",C54)) -> #VALUE! | C54: 0 | D54: 0
A55: =LEFT(C55,FIND(" ",C55)-1) -> #VALUE! | B55: =RIGHT(C55,LEN(C55)-FIND(" ",C55)) -> #VALUE!
A56: =LEFT(C56,FIND(" ",C56)-1) -> #VALUE! | B56: =RIGHT(C56,LEN(C56)-FIND(" ",C56)) -> #VALUE! | D56: 0
A57: =LEFT(C57,FIND(" ",C57)-1) -> 2052069 | B57: =RIGHT(C57,LEN(C57)-FIND(" ",C57)) -> Frontier - Maint SSP Selma (2022-25) | C57: 2052069 Frontier - Maint SSP Selma (2022-25) | D57: 0 | E57: 212.28 | F57: -212.28 | G57: 0 | H57: 860253.47 | I57: -407976.44 | J57: 0 | K57: 452277.03 | L57: 374791.18 | M57: 77485.85 | N57: 17.132387
A58: =LEFT(C58,FIND(" ",C58)-1) -> #VALUE! | B58: =RIGHT(C58,LEN(C58)-FIND(" ",C58)) -> #VALUE!
A59: =LEFT(C59,FIND(" ",C59)-1) -> #VALUE! | B59: =RIGHT(C59,LEN(C59)-FIND(" ",C59)) -> #VALUE! | C59: 1320962 | D59: 1320962
A60: =LEFT(C60,FIND(" ",C60)-1) -> #VALUE! | B60: =RIGHT(C60,LEN(C60)-FIND(" ",C60)) -> #VALUE!
A61: =LEFT(C61,FIND(" ",C61)-1) -> #VALUE! | B61: =RIGHT(C61,LEN(C61)-FIND(" ",C61)) -> #VALUE! | D61: 0
A62: =LEFT(C62,FIND(" ",C62)-1) -> 2052108 | B62: =RIGHT(C62,LEN(C62)-FIND(" ",C62)) -> Ponderosa-Wishon Phase 2 | C62: 2052108 Ponderosa-Wishon Phase 2 | D62: 0 | E62: 0 | F62: 0 | G62: 0 | H62: 50745.72 | I62: -28222.5 | J62: 1320962 | K62: 22523.22 | L62: 2044 | M62: 20479.22 | N62: 90.924921
A63: =LEFT(C63,FIND(" ",C63)-1) -> #VALUE! | B63: =RIGHT(C63,LEN(C63)-FIND(" ",C63)) -> #VALUE!
A64: =LEFT(C64,FIND(" ",C64)-1) -> #VALUE! | B64: =RIGHT(C64,LEN(C64)-FIND(" ",C64)) -> #VALUE! | C64: 0 | D64: 0
A65: =LEFT(C65,FIND(" ",C65)-1) -> #VALUE! | B65: =RIGHT(C65,LEN(C65)-FIND(" ",C65)) -> #VALUE!
A66: =LEFT(C66,FIND(" ",C66)-1) -> #VALUE! | B66: =RIGHT(C66,LEN(C66)-FIND(" ",C66)) -> #VALUE! | D66: 0
A67: =LEFT(C67,FIND(" ",C67)-1) -> 2052135 | B67: =RIGHT(C67,LEN(C67)-FIND(" ",C67)) -> ATT - 2024 T&M Rates-Valley | C67: 2052135 ATT - 2024 T&M Rates-Valley | D67: 0 | E67: 0 | F67: 0 | G67: 0 | H67: 5719 | I67: 3320 | J67: 0 | K67: 9039 | L67: 3427.98 | M67: 5611.02 | N67: 62.075672
A68: =LEFT(C68,FIND(" ",C68)-1) -> #VALUE! | B68: =RIGHT(C68,LEN(C68)-FIND(" ",C68)) -> #VALUE!
A69: =LEFT(C69,FIND(" ",C69)-1) -> #VALUE! | B69: =RIGHT(C69,LEN(C69)-FIND(" ",C69)) -> #VALUE! | C69: 204703 | D69: 204703
A70: =LEFT(C70,FIND(" ",C70)-1) -> #VALUE! | B70: =RIGHT(C70,LEN(C70)-FIND(" ",C70)) -> #VALUE!
A71: =LEFT(C71,FIND(" ",C71)-1) -> #VALUE! | B71: =RIGHT(C71,LEN(C71)-FIND(" ",C71)) -> #VALUE! | D71: 0
A72: =LEFT(C72,FIND(" ",C72)-1) -> 2052144 | B72: =RIGHT(C72,LEN(C72)-FIND(" ",C72)) -> Ponderosa-Windwood & Silver Pine FTTH | C72: 2052144 Ponderosa-Windwood & Silver Pine FTTH | D72: -6153.5 | E72: -2418.94 | F72: -3734.56 | G72: 0 | H72: 165264.7 | I72: -157941.5 | J72: 204703 | K72: 7323.2 | L72: 6292.45 | M72: 1030.75 | N72: 14.075131
A73: =LEFT(C73,FIND(" ",C73)-1) -> #VALUE! | B73: =RIGHT(C73,LEN(C73)-FIND(" ",C73)) -> #VALUE!
A74: =LEFT(C74,FIND(" ",C74)-1) -> #VALUE! | B74: =RIGHT(C74,LEN(C74)-FIND(" ",C74)) -> #VALUE! | C74: 390000 | D74: 390000
A75: =LEFT(C75,FIND(" ",C75)-1) -> #VALUE! | B75: =RIGHT(C75,LEN(C75)-FIND(" ",C75)) -> #VALUE!
A76: =LEFT(C76,FIND(" ",C76)-1) -> #VALUE! | B76: =RIGHT(C76,LEN(C76)-FIND(" ",C76)) -> #VALUE! | D76: 0
A77: =LEFT(C77,FIND(" ",C77)-1) -> 2052148 | B77: =RIGHT(C77,LEN(C77)-FIND(" ",C77)) -> Ponderosa-Meadow Ranch SLC | C77: 2052148 Ponderosa-Meadow Ranch SLC | D77: 0 | E77: 0 | F77: 0 | G77: 0 | H77: 158018.6 | I77: -205411.6 | J77: 390000 | K77: -47393 | L77: -24552.52 | M77: -22840.48 | N77: 0
A78: =LEFT(C78,FIND(" ",C78)-1) -> #VALUE! | B78: =RIGHT(C78,LEN(C78)-FIND(" ",C78)) -> #VALUE!
A79: =LEFT(C79,FIND(" ",C79)-1) -> #VALUE! | B79: =RIGHT(C79,LEN(C79)-FIND(" ",C79)) -> #VALUE! | C79: 235000 | D79: 235000
A80: =LEFT(C80,FIND(" ",C80)-1) -> #VALUE! | B80: =RIGHT(C80,LEN(C80)-FIND(" ",C80)) -> #VALUE!
A81: =LEFT(C81,FIND(" ",C81)-1) -> #VALUE! | B81: =RIGHT(C81,LEN(C81)-FIND(" ",C81)) -> #VALUE! | D81: 0
A82: =LEFT(C82,FIND(" ",C82)-1) -> 2052149 | B82: =RIGHT(C82,LEN(C82)-FIND(" ",C82)) -> Ponderosa-Timberview SLC | C82: 2052149 Ponderosa-Timberview SLC | D82: 0 | E82: 0 | F82: 0 | G82: 0 | H82: 235152.8 | I82: -132846.8 | J82: 235000 | K82: 102306 | L82: 67574.44 | M82: 34731.56 | N82: 33.948703
A83: =LEFT(C83,FIND(" ",C83)-1) -> #VALUE! | B83: =RIGHT(C83,LEN(C83)-FIND(" ",C83)) -> #VALUE!
A84: =LEFT(C84,FIND(" ",C84)-1) -> #VALUE! | B84: =RIGHT(C84,LEN(C84)-FIND(" ",C84)) -> #VALUE! | C84: 0 | D84: 0
A85: =LEFT(C85,FIND(" ",C85)-1) -> #VALUE! | B85: =RIGHT(C85,LEN(C85)-FIND(" ",C85)) -> #VALUE!
A86: =LEFT(C86,FIND(" ",C86)-1) -> #VALUE! | B86: =RIGHT(C86,LEN(C86)-FIND(" ",C86)) -> #VALUE! | D86: 0
A87: =LEFT(C87,FIND(" ",C87)-1) -> NEDGSUFRS | B87: =RIGHT(C87,LEN(C87)-FIND(" ",C87)) -> VZ-Verizon-NED-Fresno | C87: NEDGSUFRS VZ-Verizon-NED-Fresno | D87: 0 | E87: 0 | F87: 0 | G87: 0 | H87: 289341.62 | I87: 993.24 | J87: 0 | K87: 290334.86 | L87: 189285.26 | M87: 101049.6 | N87: 34.804501
A88: =LEFT(C88,FIND(" ",C88)-1) -> #VALUE! | B88: =RIGHT(C88,LEN(C88)-FIND(" ",C88)) -> #VALUE! | C88: 070771 | D88: Cox, Randy | E88: 373408.23 | F88: -80581.07 | G88: 7470207.6 | H88: 7319034.9 | I88: 744008.67 | J88: 453989.3 | K88: -21.579886 | L88: -151172.7 | M88: 6575026.2 | N88: 1.3806411
A89: =LEFT(C89,FIND(" ",C89)-1) -> #VALUE! | B89: =RIGHT(C89,LEN(C89)-FIND(" ",C89)) -> #VALUE! | C89: 070878 | D89: Weston, Robert
A90: =LEFT(C90,FIND(" ",C90)-1) -> #VALUE! | B90: =RIGHT(C90,LEN(C90)-FIND(" ",C90)) -> #VALUE!
A91: =LEFT(C91,FIND(" ",C91)-1) -> #VALUE! | B91: =RIGHT(C91,LEN(C91)-FIND(" ",C91)) -> #VALUE! | C91: 391527.45 | D91: 391527.45
A92: =LEFT(C92,FIND(" ",C92)-1) -> #VALUE! | B92: =RIGHT(C92,LEN(C92)-FIND(" ",C92)) -> #VALUE!
A93: =LEFT(C93,FIND(" ",C93)-1) -> #VALUE! | B93: =RIGHT(C93,LEN(C93)-FIND(" ",C93)) -> #VALUE! | D93: 0
A94: =LEFT(C94,FIND(" ",C94)-1) -> 1056150 | B94: =RIGHT(C94,LEN(C94)-FIND(" ",C94)) -> Volcano - West Ferndale FTTH-Pioneer | C94: 1056150 Volcano - West Ferndale FTTH-Pioneer | D94: 0 | E94: 0 | F94: 0 | G94: 0 | H94: 316864.7 | I94: -6.3664629e-12 | J94: 391527.45 | K94: 316864.7 | L94: 269052.66 | M94: 47812.04 | N94: 15.089103
A95: =LEFT(C95,FIND(" ",C95)-1) -> #VALUE! | B95: =RIGHT(C95,LEN(C95)-FIND(" ",C95)) -> #VALUE!
A96: =LEFT(C96,FIND(" ",C96)-1) -> #VALUE! | B96: =RIGHT(C96,LEN(C96)-FIND(" ",C96)) -> #VALUE! | C96: 41466.58 | D96: 41466.58
A97: =LEFT(C97,FIND(" ",C97)-1) -> #VALUE! | B97: =RIGHT(C97,LEN(C97)-FIND(" ",C97)) -> #VALUE!
A98: =LEFT(C98,FIND(" ",C98)-1) -> #VALUE! | B98: =RIGHT(C98,LEN(C98)-FIND(" ",C98)) -> #VALUE! | D98: 0
A99: =LEFT(C99,FIND(" ",C99)-1) -> 1056189 | B99: =RIGHT(C99,LEN(C99)-FIND(" ",C99)) -> Volcano Telephone - OXBO 1 - Splicing | C99: 1056189 Volcano Telephone - OXBO 1 - Splicing | D99: 0 | E99: 0 | F99: 0 | G99: 0 | H99: 0 | I99: 36835 | J99: 41466.58 | K99: 36835 | L99: 24421.82 | M99: 12413.18 | N99: 33.699416
A100: =LEFT(C100,FIND(" ",C100)-1) -> #VALUE! | B100: =RIGHT(C100,LEN(C100)-FIND(" ",C100)) -> #VALUE!
A101: =LEFT(C101,FIND(" ",C101)-1) -> #VALUE! | B101: =RIGHT(C101,LEN(C101)-FIND(" ",C101)) -> #VALUE! | C101: 37137 | D101: 37137
A102: =LEFT(C102,FIND(" ",C102)-1) -> #VALUE! | B102: =RIGHT(C102,LEN(C102)-FIND(" ",C102)) -> #VALUE!
...

Sheet ACDOCA - Paste Data
B2: Contract | C2: REVN | D2: COER | E2: D&A | F2: G&A | G2: Total Revenue | H2: Total Expense
A3: Paste into orange cell | C3: 0 | D3: 50002.06 | E3: 0 | F3: 346210.55 | G3: =SUM(Table1[[#This Row],[REVN]]*-1) -> 0 | H3: =Table1[[#This Row],[COER]] -> 50002.06
B4: 21041 | C4: 0 | D4: 211.9 | E4: 0 | F4: 0 | G4: =SUM(Table1[[#This Row],[REVN]]*-1) -> 0 | H4: =Table1[[#This Row],[COER]] -> 211.9
B5: 21044 | C5: -12204 | D5: 1293.27 | E5: 0 | F5: 0 | G5: =SUM(Table1[[#This Row],[REVN]]*-1) -> 12204 | H5: =Table1[[#This Row],[COER]] -> 1293.27
B6: 21047 | C6: -2750 | D6: 782.42 | E6: 0 | F6: 0 | G6: =SUM(Table1[[#This Row],[REVN]]*-1) -> 2750 | H6: =Table1[[#This Row],[COER]] -> 782.42
B7: 21048 | C7: 0 | D7: 0 | E7: 0 | F7: 0 | G7: =SUM(Table1[[#This Row],[REVN]]*-1) -> 0 | H7: =Table1[[#This Row],[COER]] -> 0
B8: 21053 | C8: 0 | D8: 0 | E8: 0 | F8: 0 | G8: =SUM(Table1[[#This Row],[REVN]]*-1) -> 0 | H8: =Table1[[#This Row],[COER]] -> 0
B9: 21056 | C9: 0 | D9: 0 | E9: 0 | F9: 0 | G9: =SUM(Table1[[#This Row],[REVN]]*-1) -> 0 | H9: =Table1[[#This Row],[COER]] -> 0
B10: 21057 | C10: 0 | D10: 0 | E10: 0 | F10: 0 | G10: =SUM(Table1[[#This Row],[REVN]]*-1) -> 0 | H10: =Table1[[#This Row],[COER]] -> 0
B11: 21060 | C11: 4652 | D11: -951.62 | E11: 0 | F11: 0 | G11: =SUM(Table1[[#This Row],[REVN]]*-1) -> -4652 | H11: =Table1[[#This Row],[COER]] -> -951.62
B12: 21061 | C12: 0 | D12: 0 | E12: 0 | F12: 0 | G12: =SUM(Table1[[#This Row],[REVN]]*-1) -> 0 | H12: =Table1[[#This Row],[COER]] -> 0
B13: 21064 | C13: 0 | D13: 0 | E13: 0 | F13: 0 | G13: =SUM(Table1[[#This Row],[REVN]]*-1) -> 0 | H13: =Table1[[#This Row],[COER]] -> 0
B14: 21065 | C14: -903 | D14: 959.37 | E14: 0 | F14: 0 | G14: =SUM(Table1[[#This Row],[REVN]]*-1) -> 903 | H14: =Table1[[#This Row],[COER]] -> 959.37
B15: 21067 | C15: -129240.96 | D15: 183712.32 | E15: 0 | F15: 0 | G15: =SUM(Table1[[#This Row],[REVN]]*-1) -> 129240.96 | H15: =Table1[[#This Row],[COER]] -> 183712.32
... B309: 22952 | C309: 0 | D309: 2787.77 | E309: 0 | F309: 0 | G309: =SUM(Table1[[#This Row],[REVN]]*-1) -> 0 | H309: =Table1[[#This Row],[COER]] -> 2787.77
C312: =SUM(Table1[REVN]) -> -11773491 | D312: =SUM(Table1[COER]) -> 10329748 | G312: =SUM(Table1[Total Revenue]) -> 11773491 | H312: =SUM(Table1[Total Expense]) -> 10329748

Sheet WIP - Paste Data
A1: Legacy Project # | B1: SAP Conract | C1: Project Description | D1: Profit Center | E1: Total | F1: 0-30 Days | G1: 31-60 Days | H1: 61-90 Days | I1: 91-120 Days | J1: 121-180 Days | K1: 181-360 Days | L1: 361-1080 Days | M1: 1081+ Days
B2: 21496 | C2: 1056203 | E2: 30785 | F2: 30785 | G2: 0 | H2: 0 | I2: 0 | J2: 0 | K2: 0 | L2: 0 | M2: 0
B3: 21044 | C3: 2036022 | E3: 12204 | F3: 12204 | G3: 0 | H3: 0 | I3: 0 | J3: 0 | K3: 0 | L3: 0 | M3: 0
B4: 21668 | C4: Adams County - Othello FTTH | E4: 2090212.4 | F4: 949164.25 | G4: 608166.36 | H4: 531816.76 | I4: 1065 | J4: 0 | K4: 0 | L4: 0 | M4: 0
B5: 21545 | C5: Alyrica - Webfoot | D5: PC8 - Washington (Kotulan) | E5: 486893.12 | F5: 0 | G5: 10551.28 | H5: 35105.7 | I5: 0 | J5: 0.34 | K5: 441235.8 | L5: 0 | M5: 0
B6: 21484 | C6: Arcadian - Redwood Segment 5-1 | E6: 2798213 | F6: 2777563 | G6: 20650 | H6: 0 | I6: 0 | J6: 0 | K6: 0 | L6: 0 | M6: 0
B7: 21655 | C7: Astound - Clallam County PWB Phase | D7: PC8 - Washington (Kotulan) | E7: 179735.34 | F7: 0 | G7: 8112 | H7: 34872.95 | I7: 81533.54 | J7: 55216.85 | K7: 0 | L7: 0 | M7: 0
B8: 21654 | C8: Astound - Clallam County WSBO Phase | D8: PC8 - Washington (Kotulan) | E8: 1675861.2 | F8: 705710.68 | G8: 737773.61 | H8: 232376.96 | I8: 0 | J8: 0 | K8: 0 | L8: 0 | M8: 0
B9: 21586 | C9: Astound - OR Wave Broadband | D9: PCA - Wireless (Shaffer) | E9: 11862.94 | F9: 0 | G9: 182.02 | H9: 7100 | I9: 0 | J9: 885.48 | K9: 3695.44 | L9: 0 | M9: 0
B10: 21387 | C10: Astound - WA- Oak Harbor | D10: PCA - Wireless (Shaffer) | E10: 8400 | F10: 0 | G10: 0 | H10: 0 | I10: 0 | J10: 0 | K10: 8400 | L10: 0 | M10: 0
B11: 21398 | C11: Astound - WA Wave Broadband | D11: PCA - Wireless (Shaffer) | E11: 159215.92 | F11: 22000 | G11: 28500 | H11: 21500 | I11: 15488.35 | J11: 31000 | K11: 40727.57 | L11: 0 | M11: 0
B12: 21565 | C12: AT&T - CDA Bridge Cable Pulling | E12: 64886 | F12: 0 | G12: 0 | H12: 64886 | I12: 0 | J12: 0 | K12: 0 | L12: 0 | M12: 0
B13: 21071 | C13: ATT - A02QY7S - Reno NV | D13: PC12 - CA Bay Area (Mullins) | E13: 502068.99 | F13: 49395.95 | G13: 64546.75 | H13: 211577.76 | I13: 23592.74 | J13: 138582.33 | K13: 14373.46 | L13: 0 | M13: 0
B14: 21077 | C14: ATT - A02PJDR - Kings Row | D14: PC12 - CA Bay Area (Mullins) | E14: 665309 | F14: 346660.59 | G14: 259798.73 | H14: 38179.07 | I14: 0 | J14: 20670.61 | K14: 0 | L14: 0 | M14: 0
B15: 21552 | C15: ATT - A051KQ2 - Carson City NV | D15: PC12 - CA Bay Area (Mullins) | E15: 344007.76 | F15: 0 | G15: 11938.15 | H15: 77199.81 | I15: 95150.6 | J15: 159719.2 | K15: 0 | L15: 0 | M15: 0
B16: 21283 | C16: ATT - A051W9F - 2101 Kala Bagai Way | E16: 6838.89 | F16: 0 | G16: 0 | H16: 0 | I16: 6838.89 | J16: 0 | K16: 0 | L16: 0 | M16: 0
B17: 21061 | C17: ATT - A0558LC - Sparks NV | D17: PC12 - CA Bay Area (Mullins) | E17: 568646.43 | F17: 0 | G17: 146508.23 | H17: 20824.91 | I17: 164625.66 | J17: 79403.83 | K17: 157283.8 | L17: 0 | M17: 0
B18: 21269 | C18: ATT - A055QP3 - Various | D18: PC12 - CA Bay Area (Mullins) | E18: 274166 | F18: 0 | G18: 0 | H18: 0 | I18: 71315 | J18: 28035 | K18: 174816 | L18: 0 | M18: 0
B19: 21878 | C19: ATT - A057WYA - San Rafael | E19: 484502 | F19: 92400 | G19: 315052 | H19: 77050 | I19: 0 | J19: 0 | K19: 0 | L19: 0 | M19: 0
B20: 22017 | C20: ATT - A0580A6 - Tehachapi | E20: 190304.42 | F20: 93149.07 | G20: 97155.35 | H20: 0 | I20: 0 | J20: 0 | K20: 0 | L20: 0 | M20: 0
B21: 21850 | C21: ATT - A058D26 - Greeley Hill | E21: 1085586.6 | F21: 49491.2 | G21: 0 | H21: 957080.77 | I21: 79014.58 | J21: 0 | K21: 0 | L21: 0 | M21: 0
B22: 21509 | C22: ATT - A058EV8 - Martinez | D22: PC12 - CA Bay Area (Mullins) | E22: 169757.96 | F22: 0 | G22: 0 | H22: 58792.7 | I22: 0 | J22: 110965.26 | K22: 0 | L22: 0 | M22: 0
B23: 21041 | C23: ATT - A058FR3 - 2 Paseo Linares | E23: 125373.1 | F23: 0 | G23: 82613.3 | H23: 0 | I23: 0 | J23: 0 | K23: 42759.8 | L23: 0 | M23: 0
B24: 21533 | C24: ATT - A058FR3 - Moraga | D24: PC12 - CA Bay Area (Mullins) | E24: 264289 | F24: 0 | G24: 91200 | H24: 23550 | I24: 0 | J24: 0 | K24: 149539 | L24: 0 | M24: 0
B25: 22077 | C25: ATT - A058LPX - Salinas | E25: 65297.85 | F25: 35148.46 | G25: 30149.39 | H25: 0 | I25: 0 | J25: 0 | K25: 0 | L25: 0 | M25: 0
B26: 21079 | C26: ATT - A058N3T - Moraga Dig Ups | D26: PC12 - CA Bay Area (Mullins) | E26: 20988 | F26: 0 | G26: 0 | H26: 0 | I26: 0 | J26: 0 | K26: 20988 | L26: 0 | M26: 0
B27: 21074 | C27: ATT - A058N3W - Harvard Circle | D27: PC12 - CA Bay Area (Mullins) | E27: 112064 | F27: 0 | G27: 0 | H27: 0 | I27: 69210 | J27: 0 | K27: 42854 | L27: 0 | M27: 0
B28: 21889 | C28: ATT - A058NZT - Reno NV | E28: 37101.75 | F28: 0 | G28: 37101.75 | H28: 0 | I28: 0 | J28: 0 | K28: 0 | L28: 0 | M28: 0
B29: 21893 | C29: ATT - A058YLP FTTH - Ceres | E29: 522950.61 | F29: 0 | G29: 8552 | H29: 290935.46 | I29: 223463.15 | J29: 0 | K29: 0 | L29: 0 | M29: 0
B30: 22016 | C30: ATT - A059EQC - Alameda | E30: 102109.22 | F30: 22066.5 | G30: 80042.72 | H30: 0 | I30: 0 | J30: 0 | K30: 0 | L30: 0 | M30: 0
B31: 21502 | C31: ATT - A059FVL - Alameda Rod and Rope | D31: PC12 - CA Bay Area (Mullins) | E31: 13334.1 | F31: 0 | G31: 0 | H31: 0 | I31: 0 | J31: 13334.1 | K31: 0 | L31: 0 | M31: 0
B32: 22076 | C32: ATT - A05AVJF - Stead | E32: 206709.24 | F32: 206709.24 | G32: 0 | H32: 0 | I32: 0 | J32: 0 | K32: 0 | L32: 0 | M32: 0
B33: 21946 | C33: ATT - A05BEYM - Fernley | E33: 78444.56 | F33: 78444.56 | G33: 0 | H33: 0 | I33: 0 | J33: 0 | K33: 0 | L33: 0 | M33: 0
B34: 21945 | C34: ATT - A05CD07 FTTH - Los Banos | E34: 708723.39 | F34: 26997.6 | G34: 570378.86 | H34: 111346.93 | I34: 0 | J34: 0 | K34: 0 | L34: 0 | M34: 0
B35: 21953 | C35: ATT - Blossom Hill Rd - HH Placement | E35: 21817.5 | F35: 18175 | G35: 3642.5 | H35: 0 | I35: 0 | J35: 0 | K35: 0 | L35: 0 | M35: 0
B36: 21527 | C36: ATT - BSW - Bay Area | E36: 41849.61 | F36: 23194.42 | G36: 18655.19 | H36: 0 | I36: 0 | J36: 0 | K36: 0 | L36: 0 | M36: 0
B37: 21265 | C37: ATT - BSW - Northern | E37: 4864.07 | F37: 4864.07 | G37: 0 | H37: 0 | I37: 0 | J37: 0 | K37: 0 | L37: 0 | M37: 0
B38: 21486 | C38: ATT - Dig MSA - Bay Area | D38: PC12 - CA Bay Area (Mullins) | E38: 59414.71 | F38: 44171.25 | G38: 13747.39 | H38: 1047.2 | I38: 448.87 | J38: 0 | K38: 0 | L38: 0 | M38: 0
B39: 21518 | C39: ATT - Dig MSA - Northern Areas | D39: PC12 - CA Bay Area (Mullins) | E39: 12021.9 | F39: 8276.24 | G39: 2760.16 | H39: 985.5 | I39: 0 | J39: 0 | K39: 0 | L39: 0 | M39: 0
B40: 22075 | C40: ATT - Joint Pole Bundle - Carson City | E40: 15386.7 | F40: 15386.7 | G40: 0 | H40: 0 | I40: 0 | J40: 0 | K40: 0 | L40: 0 | M40: 0
B41: 22102 | C41: ATT - Joint Pole Bundle - Tehachapi | E41: 24534 | F41: 16920 | G41: 7614 | H41: 0 | I41: 0 | J41: 0 | K41: 0 | L41: 0 | M41: 0
B42: 21880 | C42: ATT - NB01 - San Francisco Downtown | E42: 13040.15 | F42: 10999.99 | G42: 1069.85 | H42: 970.31 | I42: 0 | J42: 0 | K42: 0 | L42: 0 | M42: 0
B43: 21881 | C43: ATT - NB02 - San Francisco Outside | E43: 95398.24 | F43: 27156.71 | G43: 63840.22 | H43: 4401.31 | I43: 0 | J43: 0 | K43: 0 | L43: 0 | M43: 0
B44: 21882 | C44: ATT - NB03 - Oakland-Franklin | E44: 295.87 | F44: 0 | G44: 295.87 | H44: 0 | I44: 0 | J44: 0 | K44: 0 | L44: 0 | M44: 0
B45: 21883 | C45: ATT - NB04 - Hayward-Oakland | E45: 4391.82 | F45: 0 | G45: 1123.23 | H45: 3268.59 | I45: 0 | J45: 0 | K45: 0 | L45: 0 | M45: 0
B46: 21884 | C46: ATT - NB05 - Richmond-Berkeley | E46: 18899.85 | F46: 14248.66 | G46: 4651.19 | H46: 0 | I46: 0 | J46: 0 | K46: 0 | L46: 0 | M46: 0
B47: 21885 | C47: ATT - NB06 - Antioch-Martinez | E47: 39995.06 | F47: 28756.17 | G47: 8885.63 | H47: 2353.26 | I47: 0 | J47: 0 | K47: 0 | L47: 0 | M47: 0
B48: 21886 | C48: ATT - NB07 - Oakley-Brentwood | E48: 24521.4 | F48: 20572.4 | G48: 3949 | H48: 0 | I48: 0 | J48: 0 | K48: 0 | L48: 0 | M48: 0
B49: 21887 | C49: ATT - NB08 - Livermore-San Ramon | E49: 12656.15 | F49: 7234.69 | G49: 2371.01 | H49: 3050.45 | I49: 0 | J49: 0 | K49: 0 | L49: 0 | M49: 0
B50: 22870 | C50: ATT - ORCA - Alameda - A059N34 | E50: 15384.04 | F50: 15384.04 | G50: 0 | H50: 0 | I50: 0 | J50: 0 | K50: 0 | L50: 0 | M50: 0
B51: 21621 | C51: ATT - WE12 CSVA 3 (2024-26) | D51: PC12 - CA Bay Area (Mullins) | E51: 2258180.8 | F51: 641548.77 | G51: 575777.79 | H51: 465985.76 | I51: 463363.62 | J51: 99179.96 | K51: 12324.87 | L51: 0 | M51: 0
B52: 21165 | C52: Avista - Dalton sub to CDA Call Center | D52: PC12 - CA Bay Area (Mullins) | E52: 65059 | F52: 0 | G52: 0 | H52: 5580 | I52: 59479 | J52: 0 | K52: 0 | L52: 0 | M52: 0
B53: 21549 | C53: AWS - Reno Data Center - Campus | E53: 489447.16 | F53: 226791.31 | G53: 40248.34 | H53: 222407.51 | I53: 0 | J53: 0 | K53: 0 | L53: 0 | M53: 0
B54: 21280 | C54: AWS - Reno Data Center - OSP | D54: PC12 - CA Bay Area (Mullins) | E54: 82709.94 | F54: 82709.94 | G54: 0 | H54: 0 | I54: 0 | J54: 0 | K54: 0 | L54: 0 | M54: 0
B55: 21375 | C55: BCT - Hourly Maintenance | E55: 15857.38 | F55: 6756.13 | G55: 0 | H55: 0 | I55: 9101.25 | J55: 0 | K55: 0 | L55: 0 | M55: 0
B56: 21113 | C56: City of Portland-Splicing Maintenance 31 | D56: PCA - Wireless (Shaffer) | E56: 4380.6 | F56: 0 | G56: 0 | H56: 4380.6 | I56: 0 | J56: 0 | K56: 0 | L56: 0 | M56: 0
B57: 21067 | C57: City of Sherwood - Broadband Expansion | D57: PC12 - CA Bay Area (Mullins) | E57: 1566186 | F57: 237839.57 | G57: 630296.45 | H57: 138940.82 | I57: 252693.77 | J57: 244713.73 | K57: 61701.67 | L57: 0 | M57: 0
B58: 21949 | C58: City of Sherwood - Parrett Mountain & Kruger Rd | D58: PC12 - CA Bay Area (Mullins) | E58: 274656 | F58: 15980 | G58: 0 | H58: 258676 | I58: 0 | J58: 0 | K58: 0 | L58: 0 | M58: 0
B59: 22834 | C59: City of Wilsonville - Town Center Park | E59: 410.38 | F59: 410.38 | G59: 0 | H59: 0 | I59: 0 | J59: 0 | K59: 0 | L59: 0 | M59: 0
B60: 21494 | C60: Clackamas County-Marmot Road | D60: PC12 - CA Bay Area (Mullins) | E60: 499096.95 | F60: 87861.95 | G60: 271397.35 | H60: 90343.7 | I60: 49493.95 | J60: 0 | K60: 0 | L60: 0 | M60: 0
B61: 21897 | C61: Clear Creek - OSP Phase 4 | E61: 498025.55 | F61: 92603.6 | G61: 203329.02 | H61: 121265.33 | I61: 80827.6 | J61: 0 | K61: 0 | L61: 0 | M61: 0
B62: 21221 | C62: Clear Creek OSP Phase 3-1 | D62: PC12 - CA Bay Area (Mullins) | E62: 99523.79 | F62: 19924.2 | G62: 36315.95 | H62: 39974.34 | I62: 1824.64 | J62: 1484.66 | K62: 0 | L62: 0 | M62: 0
B63: 22917 | C63: Cogent - 2026 T&E Rates | E63: 23629 | F63: 23629 | G63: 0 | H63: 0 | I63: 0 | J63: 0 | K63: 0 | L63: 0 | M63: 0
B64: 22108 | C64: Cogent - Chumstick Hwy - Pothole | E64: 11871.35 | F64: 0 | G64: 11871.35 | H64: 0 | I64: 0 | J64: 0 | K64: 0 | L64: 0 | M64: 0
B65: 21415 | C65: Colville Tribes - MAT Solar | D65: PCA - Wireless (Shaffer) | E65: 308463 | F65: 25307 | G65: 72146 | H65: 66747 | I65: 11320 | J65: 132943 | K65: 0 | L65: 0 | M65: 0
B66: 21402 | C66: Colville Tribes - Twin Lakes FTTH | E66: 1203866.1 | F66: 160069.85 | G66: 519682.71 | H66: 524113.56 | I66: 0 | J66: 0 | K66: 0 | L66: 0 | M66: 0
B67: 21407 | C67: Colville Tribes - Wireless Sites | E67: 524157.86 | F67: 197931 | G67: 326226.86 | H67: 0 | I67: 0 | J67: 0 | K67: 0 | L67: 0 | M67: 0
B68: 21554 | C68: CommPro Services, LLC - IN | E68: 4750 | F68: 0 | G68: 4750 | H68: 0 | I68: 0 | J68: 0 | K68: 0 | L68: 0 | M68: 0
B69: 21273 | C69: CommPro Services, LLC (MS) | E69: 156899 | F69: 156899 | G69: 0 | H69: 0 | I69: 0 | J69: 0 | K69: 0 | L69: 0 | M69: 0
B70: 21450 | C70: Consolidated Communications - 11407 Elks | D70: PC12 - CA Bay Area (Mullins) | E70: 26082 | F70: 0 | G70: 18294 | H70: 7788 | I70: 0 | J70: 0 | K70: 0 | L70: 0 | M70: 0
B71: 21501 | C71: Consumer Power - Marval Rd Joint Trench | E71: 70590.6 | F71: 0 | G71: 19350 | H71: 9675 | I71: 0 | J71: 41565.6 | K71: 0 | L71: 0 | M71: 0
B72: 21220 | C72: CPI - 17340 Little Lobster Valley Rd | D72: PCA - Wireless (Shaffer) | E72: 19665.5 | F72: 0 | G72: 0 | H72: 0 | I72: 19665.5 | J72: 0 | K72: 0 | L72: 0 | M72: 0
B73: 21065 | C73: DirectLink - Hourly Work | E73: 2256 | F73: 903 | G73: 1353 | H73: 0 | I73: 0 | J73: 0 | K73: 0 | L73: 0 | M73: 0
B74: 22069 | C74: Ezee - Casa Paz | E74: 80230 | F74: 0 | G74: 80230 | H74: 0 | I74: 0 | J74: 0 | K74: 0 | L74: 0 | M74: 0
B75: 21963 | C75: Ezee - Eden Point | E75: 146967.8 | F75: 89222.8 | G75: 57745 | H75: 0 | I75: 0 | J75: 0 | K75: 0 | L75: 0 | M75: 0
B76: 22002 | C76: Ezee - Summercrest Apartments | E76: 206747 | F76: 199847 | G76: 6900 | H76: 0 | I76: 0 | J76: 0 | K76: 0 | L76: 0 | M76: 0
B77: 21078 | C77: Ezee Fiber-717 Lehman | E77: 18410 | F77: 18410 | G77: 0 | H77: 0 | I77: 0 | J77: 0 | K77: 0 | L77: 0 | M77: 0
B78: 21622 | C78: Frontier - FTTH - Kenwood | D78: PC14 - CA North Valley (Haskins) | E78: 725206.33 | F78: 6079.32 | G78: 28516.06 | H78: 214497.44 | I78: 180214.15 | J78: 295899.36 | K78: 0 | L78: 0 | M78: 0
B79: 21583 | C79: Frontier - FTTH Elk Grove | D79: PC14 - CA North Valley (Haskins) | E79: 1858658.5 | F79: 669789.71 | G79: 486999.63 | H79: 407529.88 | I79: 217365.33 | J79: 42311.23 | K79: 34662.76 | L79: 0 | M79: 0
B80: 21596 | C80: Frontier - FTTH Morgan Hill | D80: PC13 - CA South Bay (Birdsall) | E80: 566977.87 | F80: 253185.11 | G80: 157106.49 | H80: 108104.5 | I80: 48581.77 | J80: 0 | K80: 0 | L80: 0 | M80: 0
B81: 21178 | C81: Frontier - FTTH Northern CA Communities | D81: PC14 - CA North Valley (Haskins) | E81: 568665.09 | F81: 233413.8 | G81: 214698.56 | H81: 83020.12 | I81: 37532.61 | J81: 0 | K81: 0 | L81: 0 | M81: 0
B82: 21614 | C82: Frontier - FTTH Redding | D82: PC14 - CA North Valley (Haskins) | E82: 3078359.1 | F82: 586251.14 | G82: 625451.31 | H82: 551412.88 | I82: 495091.59 | J82: 530580.4 | K82: 289571.83 | L82: 0 | M82: 0
B83: 21620 | C83: Frontier - FTTH Susanville | D83: PC15 - CA Central Valley (Weston) | E83: 274844.25 | F83: 194623.75 | G83: 80220.5 | H83: 0 | I83: 0 | J83: 0 | K83: 0 | L83: 0 | M83: 0
B84: 21541 | C84: Frontier - Maint SSP South Bay (2025-27) | D84: PC13 - CA South Bay (Birdsall) | E84: 402478.12 | F84: 83078.14 | G84: 97410.59 | H84: 109997.23 | I84: 51149.15 | J84: 23262.34 | K84: 37580.67 | L84: 0 | M84: 0
B85: 21172 | C85: Frontier - Maint SSP Valley (2025-27) | D85: PC16 - CA South Valley (Cox) | E85: 1523569.5 | F85: 267602.84 | G85: 528831.43 | H85: 488519.98 | I85: 138541.07 | J85: 100074.19 | K85: 0 | L85: 0 | M85: 0
B86: 21075 | C86: Frontier - Middle Mile Segment (Fire) | E86: 1818896.2 | F86: 493071.75 | G86: 1026072.7 | H86: 299751.75 | I86: 0 | J86: 0 | K86: 0 | L86: 0 | M86: 0
B87: 21624 | C87: Frontier- FTTH Valley | D87: PC15 - CA Central Valley (Weston) | E87: 1344843.1 | F87: 299396.73 | G87: 102030.28 | H87: 43222.38 | I87: 135043.95 | J87: 589771.31 | K87: 175378.44 | L87: 0 | M87: 0
B88: 21895 | C88: Frontier-FTTH-Bishop, Mammoth, June Lake | E88: 72445.31 | F88: 72445.31 | G88: 0 | H88: 0 | I88: 0 | J88: 0 | K88: 0 | L88: 0 | M88: 0
B89: 21635 | C89: Google Fiber FTTH Installations | E89: 12130.64 | F89: 7205.64 | G89: 2050 | H89: 2875 | I89: 0 | J89: 0 | K89: 0 | L89: 0 | M89: 0
B90: 21628 | C90: Google-Fiber FTTH Greenfields CO | D90: PCC - Struct Wiring TX (Johnson) | E90: 51293 | F90: 0 | G90: 2694 | H90: 0 | I90: 2245 | J90: 14368 | K90: 31986 | L90: 0 | M90: 0
B91: 21247 | C91: Google-Fiber FTTH MDU CO | D91: PCC - Struct Wiring TX (Johnson) | E91: 431858.13 | F91: 183379.56 | G91: 187043.26 | H91: 47814.28 | I91: 0 | J91: 9975.1 | K91: 3645.93 | L91: 0 | M91: 0
B92: 21129 | C92: Google-Fiber Greenfield TX | D92: PCC - Struct Wiring TX (Johnson) | E92: 204700.4 | F92: 0 | G92: 10627.1 | H92: 45527.8 | I92: 1069.2 | J92: 95337 | K92: 52139.3 | L92: 0 | M92: 0
B93: 21672 | C93: Google-Google Fiber MSA (AZ) | D93: PCC - Struct Wiring TX (Johnson) | E93: 581770 | F93: 217712 | G93: 257247 | H93: 96451 | I93: 10360 | J93: 0 | K93: 0 | L93: 0 | M93: 0
B94: 21595 | C94: Google-Google Fiber MSA (TX) | D94: PCC - Struct Wiring TX (Johnson) | E94: 480460.1 | F94: 233685.4 | G94: 54352.95 | H94: 50649.35 | I94: 104845.5 | J94: 10912 | K94: 4448.9 | L94: 21566 | M94: 0
B95: 21453 | C95: Grant County PUD (2026-27) | D95: PCA - Wireless (Shaffer) | E95: 86865.92 | F95: 51226.07 | G95: 35639.85 | H95: 0 | I95: 0 | J95: 0 | K95: 0 | L95: 0 | M95: 0
B96: 21558 | C96: Idaho County - DIGB2 Phase II - Np - Grv | D96: PC9 - West WA/OR (Forte) | E96: 891967.76 | F96: 692108.46 | G96: 467822.73 | H96: 0 | I96: -217432.92 | J96: -50530.51 | K96: 0 | L96: 0 | M96: 0
B97: 21143 | C97: Jefferson PUD-Olympic Fiber Build | D97: PC8 - Washington (Kotulan) | E97: 19635.3 | F97: 791.22 | G97: 16528.19 | H97: 2315.89 | I97: 0 | J97: 0 | K97: 0 | L97: 0 | M97: 0
B98: 21677 | C98: Lumen - 2025LE000148 Fiber Overbuild | D98: PC9 - West WA/OR (Forte) | E98: 4200144.5 | F98: 442934.24 | G98: 678915.76 | H98: 458070.67 | I98: 793550.81 | J98: 961384.25 | K98: 865288.72 | L98: 0 | M98: 0
B99: 22072 | C99: Lumen - CDT-0655 - 180 Spears St | E99: 1098 | F99: 0 | G99: 1098 | H99: 0 | I99: 0 | J99: 0 | K99: 0 | L99: 0 | M99: 0
B100: 21289 | C100: Lumen - COCAL Bay Area MSA (2025-26) | D100: PC9 - West WA/OR (Forte) | E100: 95847.2 | F100: 0 | G100: 12834.52 | H100: 30910.84 | I100: 0 | J100: 46973.64 | K100: 5128.2 | L100: 0 | M100: 0
...

Sheet JTD Paste Data
A1: Contract | B1: JTD Revenue | C1: JTD Cost
A2: 21041 | B2: 125373.1 | C2: 84107.62
A3: 21044 | B3: 12204 | C3: 1293.27
A4: 21047 | B4: 2750 | C4: 782.42
A5: 21048 | B5: 0 | C5: 774.46
A6: 21053 | B6: 6500 | C6: 4309.11
A7: 21056 | B7: 33205.15 | C7: 25679.26
A8: 21057 | B8: 48099.55 | C8: 44805.26
A9: 21060 | B9: 37381 | C9: 31694.84
A10: 21061 | B10: 568646.43 | C10: 648982.12
A11: 21064 | B11: 4822163.1 | C11: 4171829.9
A12: 21065 | B12: 157023.23 | C12: 128331.51
A13: 21067 | B13: 5359735.1 | C13: 5568534.4
... A307: 22952 | B307: 0 | C307: 2787.77

Sheet MTD Hours Paste Data
A1: Contract | B1: MTD Revenue Amt | C1: MTD Hours | D1: MTD PROD | E1: MTD Direct Labor Cost | F1: MTD Direct Labor Cost Per Hour | G1: MTD Cost/Revenue Ratio | H1: QTD Revenue Amt | I1: QTD Hours | J1: QTD PROD | K1: QTD Direct Labor Cost | L1: QTD Direct Labor Cost Per Hour | M1: QTD Cost/Revenue Ratio | N1: YTD Revenue Amt | O1: YTD Hours | P1: YTD PROD | Q1: YTD Direct Labor Cost | R1: YTD Direct Labor Cost Per Hour | S1: YTD Cost/Revenue Ratio
A2: 20016 | B2: 25634 | C2: 84.11 | D2: 304.76756628224945 | E2: 8615.08 | F2: 102.42634645107597 | G2: 0.33608020597643756 | H2: 54188 | I2: 269.75 | J2: 200.8822984244671 | K2: 24051.24 | L2: 89.161223 | M2: 0.44384808444674095 | N2: 55368.5 | O2: 400.22 | P2: 138.34516016191094 | Q2: 26590.12 | R2: 66.438759 | S2: 0.48023912513432726
A3: 20017 | B3: 0 | C3: 0 | D3: 0 | E3: 0 | F3: 0 | G3: 0 | H3: 0 | I3: 0 | J3: 0 | K3: 0 | L3: 0 | M3: 0 | N3: -321277.47 | O3: 0 | P3: 0 | Q3: 0 | R3: 0 | S3: 0
A4: 20021 | B4: 0 | C4: 0 | D4: 0 | E4: 0 | F4: 0 | G4: 0 | H4: 0 | I4: 0 | J4: 0 | K4: 0 | L4: 0 | M4: 0 | N4: -116936.26 | O4: 193.78 | P4: -603.44855 | Q4: 9148.62 | R4: 47.21137372277841 | S4: -0.078235955
A5: 20025 | B5: 33464.96 | C5: 601.88 | D5: 55.60071775104672 | E5: 21498.52 | F5: 35.71894729846481 | G5: 0.6424188165771003 | H5: 110295.34 | I5: 1347.18 | J5: 81.87127184192164 | K5: 48768.53 | L5: 36.20045576686115 | M5: 0.4421631049870285 | N5: 138533.77 | O5: 1564.77 | P5: 88.53299206912197 | Q5: 56541.3 | R5: 36.13393661688299 | S5: 0.4081409175538932
A6: 20040 | B6: 9821.88 | C6: 19.76 | D6: 497.0587044534413 | E6: 538.71 | F6: 27.26265182186235 | G6: 0.054847951715964766 | H6: 12798.21 | I6: 165.66 | J6: 77.25588554871423 | K6: 5249.55 | L6: 31.68869974646867 | M6: 0.4101784546432665 | N6: 38893.29 | O6: 585.73 | P6: 66.40139654789749 | Q6: 18639.26 | R6: 31.82227306096666 | S6: 0.4792410207519086
A7: 20042 | B7: 0 | C7: 0 | D7: 0 | E7: 0 | F7: 0 | G7: 0 | H7: 0 | I7: 0 | J7: 0 | K7: 0 | L7: 0 | M7: 0 | N7: -766.95 | O7: 0 | P7: 0 | Q7: 0 | R7: 0 | S7: 0
A8: 20045 | B8: 0 | C8: 0 | D8: 0 | E8: 0 | F8: 0 | G8: 0 | H8: 0 | I8: 0 | J8: 0 | K8: 0 | L8: 0 | M8: 0 | N8: -97777.93 | O8: 38.58 | P8: -2534.4202 | Q8: 6543.16 | R8: 169.59979263867288 | S8: -0.066918578
A9: 20047 | B9: 0 | C9: 0 | D9: 0 | E9: 0 | F9: 0 | G9: 0 | H9: 0 | I9: 0 | J9: 0 | K9: 0 | L9: 0 | M9: 0 | N9: 3159.33 | O9: 0 | P9: 0 | Q9: 0 | R9: 0 | S9: 0
A10: 20049 | B10: 0 | C10: 80 | D10: 0 | E10: 4796.06 | F10: 59.95075 | G10: 0 | H10: 28658 | I10: 124.99 | J10: 229.28234 | K10: 4796.06 | L10: 38.37154972397792 | M10: 0.16735501430665084 | N10: 53261 | O10: 261.73 | P10: 203.4959691284912 | Q10: -5755.18 | R10: -21.988996 | S10: -0.10805618
A11: 20053 | B11: 437.57 | C11: 29.17 | D11: 15.000685635927322 | E11: 871.78 | F11: 29.88618443606445 | G11: 1.9923212286034235 | H11: 2207.1 | I11: 55.86 | J11: 39.51127819548872 | K11: 1707.24 | L11: 30.56283566058002 | M11: 0.7735218159575914 | N11: 6618.3 | O11: 189.46 | P11: 34.93244 | Q11: 5753.32 | R11: 30.36693761216088 | S11: 0.8693048063702159
A12: 20055 | B12: 0 | C12: 0 | D12: 0 | E12: 0 | F12: 0 | G12: 0 | H12: 0 | I12: 0 | J12: 0 | K12: 0 | L12: 0 | M12: 0 | N12: -863.17 | O12: 0 | P12: 0 | Q12: 0 | R12: 0 | S12: 0
A13: 20059 | B13: 0 | C13: 0 | D13: 0 | E13: 0 | F13: 0 | G13: 0 | H13: 0 | I13: 0 | J13: 0 | K13: 0 | L13: 0 | M13: 0 | N13: -1116.95 | O13: 0 | P13: 0 | Q13: 0 | R13: 0 | S13: 0
A14: 20060 | B14: 0 | C14: 0 | D14: 0 | E14: 0 | F14: 0 | G14: 0 | H14: 0 | I14: 0 | J14: 0 | K14: 0 | L14: 0 | M14: 0 | N14: -12848.08 | O14: 0 | P14: 0 | Q14: 0 | R14: 0 | S14: 0
A15: 20064 | B15: 0 | C15: 0 | D15: 0 | E15: 0 | F15: 0 | G15: 0 | H15: 0 | I15: 0 | J15: 0 | K15: 0 | L15: 0 | M15: 0 | N15: -8012.89 | O15: 0 | P15: 0 | Q15: 0 | R15: 0 | S15: 0
A16: 20069 | B16: 181772.02 | C16: 1857.58 | D16: 97.85420816330925 | E16: 58855.76 | F16: 31.684105126024182 | G16: 0.32378888676045964 | H16: 675919.19 | I16: 4651.88 | J16: 145.30022055599028 | K16: 150399.4 | L16: 32.33088557744396 | M16: 0.22251091879785215 | N16: 691401.37 | O16: 5055.61 | P16: 136.75923775765932 | Q16: 166642.4 | R16: 32.96187799296227 | S16: 0.24102121753099795
A17: 20073 | B17: 0 | C17: 0 | D17: 0 | E17: 0 | F17: 0 | G17: 0 | H17: 0 | I17: 0 | J17: 0 | K17: 0 | L17: 0 | M17: 0 | N17: -4384.76 | O17: 0 | P17: 0 | Q17: 0 | R17: 0 | S17: 0
A18: 20077 | B18: 0 | C18: 0 | D18: 0 | E18: 0 | F18: 0 | G18: 0 | H18: 0 | I18: 0 | J18: 0 | K18: 0 | L18: 0 | M18: 0 | N18: -237579.33 | O18: 0 | P18: 0 | Q18: 0 | R18: 0 | S18: 0
A19: 20080 | B19: 0 | C19: 0 | D19: 0 | E19: 0 | F19: 0 | G19: 0 | H19: 0 | I19: 0 | J19: 0 | K19: 0 | L19: 0 | M19: 0 | N19: -100362.2 | O19: 0 | P19: 0 | Q19: 0 | R19: 0 | S19: 0
A20: 20081 | B20: 11042.05 | C20: 220.52 | D20: 50.07278251405768 | E20: 6618.53 | F20: 30.013286776709595 | G20: 0.5993932286124406 | H20: 11042.05 | I20: 220.52 | J20: 50.07278251405768 | K20: 6618.53 | L20: 30.013286776709595 | M20: 0.5993932286124406 | N20: 11042.05 | O20: 220.52 | P20: 50.07278251405768 | Q20: 6618.53 | R20: 30.013286776709595 | S20: 0.5993932286124406
A21: 20082 | B21: 9839.7 | C21: 70.61 | D21: 139.35278289194164 | E21: 2283.28 | F21: 32.336496246990514 | G21: 0.23204772503226725 | H21: 9839.7 | I21: 18.54 | J21: 530.7281553398059 | K21: 4281.35 | L21: 230.92502696871628 | M21: 0.43510981025844286 | N21: 24552.6 | O21: 4867.37 | P21: 5.044325785793971 | Q21: 113532.86 | R21: 23.325298878038858 | S21: 4.624066697620618
A22: 20083 | B22: 0 | C22: 0 | D22: 0 | E22: 0 | F22: 0 | G22: 0 | H22: 0 | I22: 0 | J22: 0 | K22: 0 | L22: 0 | M22: 0 | N22: -134732.62 | O22: 0 | P22: 0 | Q22: 0 | R22: 0 | S22: 0
A23: 20086 | B23: 4023.32 | C23: 143.72 | D23: 27.994155301976065 | E23: 4316.59 | F23: 30.034720289451712 | G23: 1.0728925365121342 | H23: 9806.3 | I23: 318.47 | J23: 30.79191132602757 | K23: 9081.76 | L23: 28.51684617075392 | M23: 0.92611484 | N23: 57423.41 | O23: 862.26 | P23: 66.59639783823904 | Q23: 27842.88 | R23: 32.290585206318276 | S23: 0.4848698466357188
A24: 20087 | B24: 0 | C24: 0 | D24: 0 | E24: 0 | F24: 0 | G24: 0 | H24: 3555.68 | I24: 0 | J24: 0 | K24: 0 | L24: 0 | M24: 0 | N24: 44454.45 | O24: 701.48 | P24: 63.37236984661003 | Q24: 10902.2 | R24: 15.541711809317443 | S24: 0.24524428937935347
A25: 20088 | B25: 0 | C25: 16.62 | D25: 0 | E25: 478.32 | F25: 28.779783393501805 | G25: 0 | H25: 45 | I25: 36.12 | J25: 1.2458471760797343 | K25: 1039.53 | L25: 28.779900332225914 | M25: 23.100666666666665 | N25: 960 | O25: 117.76 | P25: 8.152173913043478 | Q25: 3619.23 | R25: 30.733950407608695 | S25: 3.7700313
A26: 20091 | B26: -2444.75 | C26: 0 | D26: 0 | E26: 0 | F26: 0 | G26: 0 | H26: -2444.75 | I26: 0 | J26: 0 | K26: 0 | L26: 0 | M26: 0 | N26: -3994.75 | O26: 0 | P26: 0 | Q26: 0 | R26: 0 | S26: 0
A27: 20092 | B27: 0 | C27: 0 | D27: 0 | E27: 0 | F27: 0 | G27: 0 | H27: 0 | I27: 0 | J27: 0 | K27: 0 | L27: 0 | M27: 0 | N27: -21167.8 | O27: 0 | P27: 0 | Q27: 0 | R27: 0 | S27: 0
A28: 20097 | B28: 0 | C28: 0 | D28: 0 | E28: 0 | F28: 0 | G28: 0 | H28: 0 | I28: 0 | J28: 0 | K28: 0 | L28: 0 | M28: 0 | N28: -119536.26 | O28: 112.52 | P28: -1062.3557 | Q28: 4040.88 | R28: 35.912548880199076 | S28: -0.033804638
A29: 20100 | B29: 94.38 | C29: 21.41 | D29: 4.408220457730033 | E29: 541.71 | F29: 25.301728164409155 | G29: 5.739669421487603 | H29: 7678.28 | I29: 158.9 | J29: 48.32146 | K29: 4421.07 | L29: 27.822970421648836 | M29: 0.5757891090192074 | N29: 20708.17 | O29: 409.41 | P29: 50.580518306831785 | Q29: 12553.23 | R29: 30.66175716274639 | S29: 0.6061969744308647
A30: 20101 | B30: 0 | C30: 0 | D30: 0 | E30: 0 | F30: 0 | G30: 0 | H30: 0 | I30: 0 | J30: 0 | K30: 0 | L30: 0 | M30: 0 | N30: -65552.95 | O30: 0 | P30: 0 | Q30: 0 | R30: 0 | S30: 0
A31: 20106 | B31: 0 | C31: 0 | D31: 0 | E31: 0 | F31: 0 | G31: 0 | H31: 303 | I31: 8.94 | J31: 33.89261744966443 | K31: 494.26 | L31: 55.28635346756152 | M31: 1.6312211221122113 | N31: 26201.08 | O31: 112.54 | P31: 232.81570996978851 | Q31: 7260.49 | R31: 64.51475031100053 | S31: 0.2771065162199421
A32: 20109 | B32: 0 | C32: 0 | D32: 0 | E32: 0 | F32: 0 | G32: 0 | H32: 0 | I32: 0 | J32: 0 | K32: 0 | L32: 0 | M32: 0 | N32: -18200.7 | O32: 15.28 | P32: -1191.1453 | Q32: 885.54 | R32: 57.954188481675395 | S32: -0.048654173
A33: 20111 | B33: 0 | C33: 0 | D33: 0 | E33: 0 | F33: 0 | G33: 0 | H33: 0 | I33: 0 | J33: 0 | K33: 0 | L33: 0 | M33: 0 | N33: -96954.05 | O33: 14.65 | P33: -6618.0239 | Q33: 1868.02 | R33: 127.5098976109215 | S33: -0.019267065
A34: 20113 | B34: 0 | C34: 0 | D34: 0 | E34: 0 | F34: 0 | G34: 0 | H34: -19218.78 | I34: 0 | J34: 0 | K34: 0 | L34: 0 | M34: 0 | N34: -19218.78 | O34: 0 | P34: 0 | Q34: 0 | R34: 0 | S34: 0
A35: 20115 | B35: 0 | C35: 0 | D35: 0 | E35: 0 | F35: 0 | G35: 0 | H35: 0 | I35: 0 | J35: 0 | K35: 0 | L35: 0 | M35: 0 | N35: -7790.21 | O35: 0 | P35: 0 | Q35: 0 | R35: 0 | S35: 0
A36: 20116 | B36: 0 | C36: 0 | D36: 0 | E36: 0 | F36: 0 | G36: 0 | H36: 0 | I36: 0 | J36: 0 | K36: 0 | L36: 0 | M36: 0 | N36: 3668.4 | O36: 71.87 | P36: 51.04215945457075 | Q36: 1996.06 | R36: 27.773201614025325 | S36: 0.5441227783229746
A37: 20120 | B37: 0 | C37: 0 | D37: 0 | E37: 0 | F37: 0 | G37: 0 | H37: 0 | I37: 0 | J37: 0 | K37: 0 | L37: 0 | M37: 0 | N37: -14621.25 | O37: 92.63 | P37: -157.84573 | Q37: 2640.1 | R37: 28.501565367591493 | S37: -0.18056596
A38: 20121 | B38: 7398 | C38: 22.71 | D38: 325.75957727873185 | E38: 785.55 | F38: 34.59048877146631 | G38: 0.10618410381184104 | H38: 7398 | I38: 22.71 | J38: 325.75957727873185 | K38: 785.55 | L38: 34.59048877146631 | M38: 0.10618410381184104 | N38: 7398 | O38: 22.71 | P38: 325.75957727873185 | Q38: 785.55 | R38: 34.59048877146631 | S38: 0.10618410381184104
A39: 20124 | B39: 0 | C39: 0 | D39: 0 | E39: 0 | F39: 0 | G39: 0 | H39: -39.11 | I39: 0 | J39: 0 | K39: 0 | L39: 0 | M39: 0 | N39: 0 | O39: 0 | P39: 0 | Q39: 0 | R39: 0 | S39: 0
A40: 20126 | B40: 0 | C40: 0 | D40: 0 | E40: 0 | F40: 0 | G40: 0 | H40: 0 | I40: 0 | J40: 0 | K40: 0 | L40: 0 | M40: 0 | N40: -134581.36 | O40: 7.55 | P40: -17825.346 | Q40: 259.08 | R40: 34.31523178807947 | S40: -0.0019250809
A41: 20127 | B41: 0 | C41: 0 | D41: 0 | E41: 0 | F41: 0 | G41: 0 | H41: 0 | I41: 0 | J41: 0 | K41: 0 | L41: 0 | M41: 0 | N41: -47353.69 | O41: 0 | P41: 0 | Q41: 0 | R41: 0 | S41: 0
A42: 20129 | B42: 0 | C42: 0 | D42: 0 | E42: 0 | F42: 0 | G42: 0 | H42: 0 | I42: 0 | J42: 0 | K42: 0 | L42: 0 | M42: 0 | N42: -169056.67 | O42: 0 | P42: 0 | Q42: 0 | R42: 0 | S42: 0
A43: 20130 | B43: 0 | C43: 0 | D43: 0 | E43: 0 | F43: 0 | G43: 0 | H43: 0 | I43: 0 | J43: 0 | K43: 0 | L43: 0 | M43: 0 | N43: -5160 | O43: 0 | P43: 0 | Q43: 0 | R43: 0 | S43: 0
A44: 20134 | B44: 0 | C44: 0 | D44: 0 | E44: 0 | F44: 0 | G44: 0 | H44: 0 | I44: 0 | J44: 0 | K44: 0 | L44: 0 | M44: 0 | N44: -4601.89 | O44: 0 | P44: 0 | Q44: 0 | R44: 0 | S44: 0
A45: 20135 | B45: 0 | C45: 0 | D45: 0 | E45: 0 | F45: 0 | G45: 0 | H45: 11063.5 | I45: 25.22 | J45: 438.67961934972243 | K45: 257.25 | L45: 10.200237906423473 | M45: 0.023252135400189812 | N45: 38662.72 | O45: 286.7 | P45: 134.85427275898152 | Q45: 6027.65 | R45: 21.024241367282873 | S45: 0.1559034129000753
A46: 20136 | B46: 0 | C46: 0 | D46: 0 | E46: 0 | F46: 0 | G46: 0 | H46: -577.95 | I46: 0 | J46: 0 | K46: 0 | L46: 0 | M46: 0 | N46: 1510.8 | O46: 67.6 | P46: 22.349112426035504 | Q46: 2314.95 | R46: 34.244822 | S46: 1.5322676727561557
A47: 20138 | B47: 0 | C47: 0 | D47: 0 | E47: 0 | F47: 0 | G47: 0 | H47: 0 | I47: 0 | J47: 0 | K47: 0 | L47: 0 | M47: 0 | N47: -55759.58 | O47: 0 | P47: 0 | Q47: 0 | R47: 0 | S47: 0
A48: 20139 | B48: 12919.21 | C48: 516.6 | D48: 25.008149438637243 | E48: 17035.43 | F48: 32.97605497483546 | G48: 1.3186123609725362 | H48: 44362.29 | I48: 1877.95 | J48: 23.622721584706728 | K48: 72474.46 | L48: 38.592326739263555 | M48: 1.6336951947250695 | N48: 307965.79 | O48: 5435.26 | P48: 56.66072828162774 | Q48: 222703.95 | R48: 40.97392765019521 | S48: 0.7231450934858706
A49: 20140 | B49: 0 | C49: 0 | D49: 0 | E49: 0 | F49: 0 | G49: 0 | H49: 0 | I49: 0 | J49: 0 | K49: 0 | L49: 0 | M49: 0 | N49: -9154.27 | O49: 0 | P49: 0 | Q49: 0 | R49: 0 | S49: 0
A50: 20141 | B50: 0 | C50: 0 | D50: 0 | E50: 0 | F50: 0 | G50: 0 | H50: 0 | I50: 0 | J50: 0 | K50: 0 | L50: 0 | M50: 0 | N50: -550 | O50: 0 | P50: 0 | Q50: 0 | R50: 0 | S50: 0
A51: 20142 | B51: 610 | C51: 0 | D51: 0 | E51: 0 | F51: 0 | G51: 0 | H51: 610 | I51: 0 | J51: 0 | K51: 0 | L51: 0 | M51: 0 | N51: 610 | O51: 0 | P51: 0 | Q51: 0 | R51: 0 | S51: 0
A52: 20143 | B52: 0 | C52: 0 | D52: 0 | E52: 0 | F52: 0 | G52: 0 | H52: 2194 | I52: 17.52 | J52: 125.22831050228311 | K52: 533.9 | L52: 30.47374429223744 | M52: 0.24334548769371012 | N52: 20115 | O52: 128.71 | P52: 156.28156320410224 | Q52: 7063.46 | R52: 54.878874990288246 | S52: 0.35115386527467063
A53: 20144 | B53: 0 | C53: 0 | D53: 0 | E53: 0 | F53: 0 | G53: 0 | H53: 0 | I53: 0 | J53: 0 | K53: 0 | L53: 0 | M53: 0 | N53: -126116.81 | O53: 0 | P53: 0 | Q53: 0 | R53: 0 | S53: 0
A54: 20145 | B54: 0 | C54: 0 | D54: 0 | E54: 0 | F54: 0 | G54: 0 | H54: 0 | I54: 0 | J54: 0 | K54: 0 | L54: 0 | M54: 0 | N54: -9170.97 | O54: 0 | P54: 0 | Q54: 0 | R54: 0 | S54: 0
A55: 20146 | B55: 1736.86 | C55: 152.71 | D55: 11.373583917228734 | E55: 4146.88 | F55: 27.155261606967454 | G55: 2.3875729765208478 | H55: 35569.48 | I55: 644.5 | J55: 55.18926299456943 | K55: 19343.19 | L55: 30.012707525213344 | M55: 0.5438142474953247 | N55: 57079.05 | O55: 1173.47 | P55: 48.641252013259816 | Q55: 33835.04 | R55: 28.833323391309534 | S55: 0.5927751075044171
A56: 20147 | B56: 0 | C56: 0 | D56: 0 | E56: 0 | F56: 0 | G56: 0 | H56: 0 | I56: 0 | J56: 0 | K56: 0 | L56: 0 | M56: 0 | N56: 126 | O56: 0 | P56: 0 | Q56: 0 | R56: 0 | S56: 0
A57: 20152 | B57: 0 | C57: 0 | D57: 0 | E57: 0 | F57: 0 | G57: 0 | H57: -331.98 | I57: 69.24 | J57: -4.7946274 | K57: 1856.55 | L57: 26.813258 | M57: -5.592355 | N57: 5324.48 | O57: 236.03 | P57: 22.558488327754947 | Q57: 9117.51 | R57: 38.62860653306783 | S57: 1.7123756686098923
A58: 20153 | B58: -716 | C58: 91.51 | D58: -7.8242815 | E58: 3784.06 | F58: 41.35132772374604 | G58: -5.285 | H58: -716 | I58: 91.51 | J58: -7.8242815 | K58: 3784.06 | L58: 41.35132772374604 | M58: -5.285 | N58: 5409.18 | O58: 447.87 | P58: 12.077567151182263 | Q58: 15914.04 | R58: 35.53272154866367 | S58: 2.942042971393076
A59: 20157 | B59: 0 | C59: 0 | D59: 0 | E59: 0 | F59: 0 | G59: 0 | H59: 0 | I59: 0 | J59: 0 | K59: 0 | L59: 0 | M59: 0 | N59: 0.1 | O59: 0 | P59: 0 | Q59: 0 | R59: 0 | S59: 0
A60: 20162 | B60: 0 | C60: 61.16 | D60: 0 | E60: 1746.66 | F60: 28.558862001308043 | G60: 0 | H60: 120086.8 | I60: 1142.58 | J60: 105.10143709849639 | K60: 34144.83 | L60: 29.883973113480018 | M60: 0.2843345813195122 | N60: 120086.8 | O60: 1142.58 | P60: 105.10143709849639 | Q60: 34144.83 | R60: 29.883973113480018 | S60: 0.2843345813195122
A61: 20163 | B61: 0 | C61: 104.06 | D61: 0 | E61: 2918.57 | F61: 28.04699211993081 | G61: 0 | H61: 1032.5 | I61: 104.06 | J61: 9.9221603 | K61: 2918.57 | L61: 28.04699211993081 | M61: 2.8267021791767553 | N61: 59699.44 | O61: 1048.79 | P61: 56.922205589298144 | Q61: 26855.65 | R61: 25.606317756652906 | S61: 0.4498476032606001
A62: 20165 | B62: 37752.78 | C62: 751.22 | D62: 50.25529139266793 | E62: 23243.98 | F62: 30.941641596336627 | G62: 0.61568923 | H62: 123838.02 | I62: 1792.22 | J62: 69.09755498766893 | K62: 54445.49 | L62: 30.37879836180826 | M62: 0.4396508439007665 | N62: 245829.29 | O62: 3221.83 | P62: 76.30113631073024 | Q62: 104647.1 | R62: 32.48063988478597 | S62: 0.4256901201642815
A63: 20166 | B63: 0 | C63: 38.56 | D63: 0 | E63: 3334.12 | F63: 86.46576763485477 | G63: 0 | H63: 19036 | I63: 98.89 | J63: 192.4967135200728 | K63: 11402.15 | L63: 115.30134492870867 | M63: 0.5989782517335575 | N63: 62144.26 | O63: 1491.05 | P63: 41.678186512860066 | Q63: 46505.39 | R63: 31.189691827906508 | S63: 0.7483457040119232
A64: 20167 | B64: -12820.74 | C64: 41.65 | D64: -307.82089 | E64: 1395.12 | F64: 33.49627851140456 | G64: -0.10881743 | H64: 15521.64 | I64: 293.46 | J64: 52.89184215906768 | K64: 9533.04 | L64: 32.48497239828256 | M64: 0.6141773678554586 | N64: 81333.73 | O64: 965.18 | P64: 84.26793965892372 | Q64: 28862.45 | R64: 29.90369671978284 | S64: 0.35486445783317694
A65: 20169 | B65: 0 | C65: 19.83 | D65: 0 | E65: 552.12 | F65: 27.842662632375188 | G65: 0 | H65: 5675.14 | I65: 241.64 | J65: 23.48592948187386 | K65: 6630.16 | L65: 27.438172487998674 | M65: 1.1682813111218402 | N65: 29398.92 | O65: 889.24 | P65: 33.06072601322477 | Q65: 25169.95 | R65: 28.305013269758444 | S65: 0.8561521987882548
A66: 20170 | B66: 0 | C66: 0 | D66: 0 | E66: 0 | F66: 0 | G66: 0 | H66: 0 | I66: 3.5 | J66: 0 | K66: 306.7 | L66: 87.62857142857143 | M66: 0 | N66: 0 | O66: 3.5 | P66: 0 | Q66: 306.7 | R66: 87.62857142857143 | S66: 0
A67: 20171 | B67: 28554 | C67: 116.32 | D67: 245.47799174690508 | E67: 15630.16 | F67: 134.37207702888583 | G67: 0.5473895075996358 | H67: 38072 | I67: 274.06 | J67: 138.91848500328396 | K67: 24004.1 | L67: 87.58702473910823 | M67: 0.63049223 | N67: 27321.42 | O67: 1738.37 | P67: 15.716688622100014 | Q67: 57339.99 | R67: 32.98491690491667 | S67: 2.0987192466570184
A68: 20172 | B68: 0 | C68: 0 | D68: 0 | E68: 0 | F68: 0 | G68: 0 | H68: 5020.96 | I68: 0 | J68: 0 | K68: 0 | L68: 0 | M68: 0 | N68: 5020.96 | O68: 0 | P68: 0 | Q68: 0 | R68: 0 | S68: 0
A69: 20175 | B69: 0 | C69: 29.61 | D69: 0 | E69: 998.33 | F69: 33.71597433299561 | G69: 0 | H69: 50741.84 | I69: 270.83 | J69: 187.35679208359488 | K69: 8441.95 | L69: 31.17066056197615 | M69: 0.1663705927889095 | N69: 75296.41 | O69: 492.65 | P69: 152.8395615548564 | Q69: 21977.21 | R69: 44.61019 | S69: 0.29187593405847634
A70: 20181 | B70: 0 | C70: 0 | D70: 0 | E70: 0 | F70: 0 | G70: 0 | H70: 8296.42 | I70: 142.62 | J70: 58.17150469779835 | K70: 4741.56 | L70: 33.24610854017669 | M70: 0.5715187996750406 | N70: 36704.72 | O70: 882.87 | P70: 41.57432011507923 | Q70: 28647.42 | R70: 32.448061435998504 | S70: 0.7804832729959525
A71: 20182 | B71: 0 | C71: 0 | D71: 0 | E71: 0 | F71: 0 | G71: 0 | H71: 2100 | I71: 1.55 | J71: 1354.8387096774193 | K71: 68.08 | L71: 43.92258064516129 | M71: 0.032419048 | N71: 2100 | O71: 1.55 | P71: 1354.8387096774193 | Q71: 68.08 | R71: 43.92258064516129 | S71: 0.032419048
A72: 20183 | B72: 0 | C72: 0 | D72: 0 | E72: 0 | F72: 0 | G72: 0 | H72: 2408.43 | I72: 70.31 | J72: 34.254444602474756 | K72: 2557.73 | L72: 36.37789788081354 | M72: 1.0619905913811072 | N72: 22226.11 | O72: 239.53 | P72: 92.79050640838308 | Q72: 7517.25 | R72: 31.383334 | S72: 0.3382170789220426
A73: 20185 | B73: 12513.11 | C73: 225.69 | D73: 55.44379458549338 | E73: 7425.58 | F73: 32.901679294607646 | G73: 0.5934240168910846 | H73: 35810.72 | I73: 331.64 | J73: 107.98070196598721 | K73: 11246.59 | L73: 33.912043 | M73: 0.3140565171546397 | N73: 81749.38 | O73: 964.9 | P73: 84.72316302207483 | Q73: 29379.05 | R73: 30.447766607938647 | S73: 0.3593794839789611
A74: 20186 | B74: 0 | C74: 0 | D74: 0 | E74: 0 | F74: 0 | G74: 0 | H74: 0 | I74: 0 | J74: 0 | K74: 0 | L74: 0 | M74: 0 | N74: -193669.75 | O74: 0 | P74: 0 | Q74: 0 | R74: 0 | S74: 0
A75: 20189 | B75: 0 | C75: 0 | D75: 0 | E75: 0 | F75: 0 | G75: 0 | H75: 0 | I75: 0 | J75: 0 | K75: 0 | L75: 0 | M75: 0 | N75: -153662.77 | O75: 0 | P75: 0 | Q75: 0 | R75: 0 | S75: 0
A76: 20195 | B76: 0 | C76: 0 | D76: 0 | E76: 0 | F76: 0 | G76: 0 | H76: 0 | I76: 0 | J76: 0 | K76: 0 | L76: 0 | M76: 0 | N76: -933.4 | O76: 0 | P76: 0 | Q76: 0 | R76: 0 | S76: 0
A77: 20198 | B77: 0 | C77: 0 | D77: 0 | E77: 0 | F77: 0 | G77: 0 | H77: 0 | I77: 0 | J77: 0 | K77: 0 | L77: 0 | M77: 0 | N77: -1541.14 | O77: 101.71 | P77: -15.152296 | Q77: 641.54 | R77: 6.307541048077868 | S77: -0.41627626
A78: 20199 | B78: 21842.54 | C78: 63.73 | D78: 342.7356033265338 | E78: 1708.7 | F78: 26.811548721167426 | G78: 0.078228082 | H78: 42204.83 | I78: 431.4 | J78: 97.832244 | K78: 11089.44 | L78: 25.705702364394995 | M78: 0.2627528650156866 | N78: 403397.32 | O78: 7157.72 | P78: 56.35835433629703 | Q78: 225689.93 | R78: 31.530980535701314 | S78: 0.5594730525230064
A79: 20200 | B79: 48694.44 | C79: 322.88 | D79: 150.81280971258673 | E79: 11840.31 | F79: 36.67093037661051 | G79: 0.2431552760438358 | H79: 83382.74 | I79: 517.76 | J79: 161.04515605686032 | K79: 18677.38 | L79: 36.07343170580964 | M79: 0.22399575739535543 | N79: 244040.46 | O79: 2794.24 | P79: 87.33697177049932 | Q79: 77757.81 | R79: 27.82789237860742 | S79: 0.3186267146029802
A80: 20201 | B80: 24842.32 | C80: 469.83 | D80: 52.875125045229126 | E80: 14372.56 | F80: 30.590979716067515 | G80: 0.57855144 | H80: 106653.64 | I80: 1340.12 | J80: 79.58514162910784 | K80: 42906.48 | L80: 32.016894009491686 | M80: 0.40229738056760184 | N80: 271961.12 | O80: 5304.12 | P80: 51.27356092999404 | Q80: 147737.21 | R80: 27.853293288990447 | S80: 0.5432291571677599
A81: 20202 | B81: 32618.7 | C81: 319.96 | D81: 101.94618077259658 | E81: 6716.02 | F81: 20.99018627328416 | G81: 0.20589477814873064 | H81: 32618.7 | I81: 655.22 | J81: 49.782821037208876 | K81: 16264.68 | L81: 24.82323494398828 | M81: 0.4986305401502819 | N81: 53916.7 | O81: 1644.68 | P81: 32.782486562735606 | Q81: 37088.46 | R81: 22.550563027458228 | S81: 0.68788446
A82: 20209 | B82: 0 | C82: 0 | D82: 0 | E82: 0 | F82: 0 | G82: 0 | H82: 0 | I82: 0 | J82: 0 | K82: 0 | L82: 0 | M82: 0 | N82: 0 | O82: 19.54 | P82: 0 | Q82: 332.09 | R82: 16.99539406345957 | S82: 0
A83: 20211 | B83: 68839.54 | C83: 625.35 | D83: 110.0816182937555 | E83: 20002.19 | F83: 31.985592068441672 | G83: 0.29056251683262263 | H83: 114973.91 | I83: 1368.58 | J83: 84.00963772669482 | K83: 42568.48 | L83: 31.10412252115331 | M83: 0.37024469290467726 | N83: 336068.1 | O83: 4875.67 | P83: 68.92757303098855 | Q83: 140674.24 | R83: 28.852289018739988 | S83: 0.4185884944152688
A84: 20212 | B84: 18887.45 | C84: 303.52 | D84: 62.22802451238798 | E84: 8841.09 | F84: 29.128525303110173 | G84: 0.46809336358269643 | H84: 114692.31 | I84: 1807.47 | J84: 63.454613 | K84: 57149.15 | L84: 31.618312 | M84: 0.4982823172713149 | N84: 268328.4 | O84: 4546.42 | P84: 59.019712213125935 | Q84: 145900.95 | R84: 32.091392788171795 | S84: 0.5437402451622713
A85: 20215 | B85: 0 | C85: 0 | D85: 0 | E85: 0 | F85: 0 | G85: 0 | H85: 0 | I85: 0 | J85: 0 | K85: 0 | L85: 0 | M85: 0 | N85: 0 | O85: 39.36 | P85: 0 | Q85: 100 | R85: 2.540650406504065 | S85: 0
A86: 20216 | B86: 58756.98 | C86: 634.4 | D86: 92.61819041614123 | E86: 21428.97 | F86: 33.778325977301385 | G86: 0.36470509546270075 | H86: 163385.41 | I86: 1612.05 | J86: 101.35256970937625 | K86: 54508.06 | L86: 33.81288421575013 | M86: 0.3336164471478818 | N86: 560274.69 | O86: 5857.33 | P86: 95.65359814113256 | Q86: 178207.03 | R86: 30.42461838414431 | S86: 0.3180708198687326
A87: 20218 | B87: -15815.71 | C87: 330.12 | D87: -47.908972 | E87: 11578.76 | F87: 35.074397 | G87: -0.73210498 | H87: -2744.84 | I87: 639.69 | J87: -4.2908909 | K87: 22527.44 | L87: 35.21618283856243 | M87: -8.207196 | N87: 6486.23 | O87: 2852.67 | P87: 2.273740040032671 | Q87: 96569.11 | R87: 33.85218409419947 | S87: 14.88832650091039
A88: 20219 | B88: -395.1 | C88: 25.3 | D88: -15.616601 | E88: 796.97 | F88: 31.50079051383399 | G88: -2.0171349 | H88: -10528.37 | I88: 60.23 | J88: -174.80276 | K88: 1914.73 | L88: 31.790303835298023 | M88: -0.18186386 | N88: -21413.17 | O88: 389.92 | P88: -54.916829 | Q88: 11440.93 | R88: 29.34173676651621 | S88: -0.53429408
A89: 20221 | B89: 0 | C89: 0 | D89: 0 | E89: 0 | F89: 0 | G89: 0 | H89: 0 | I89: 0 | J89: 0 | K89: 0 | L89: 0 | M89: 0 | N89: 6000.44 | O89: 0 | P89: 0 | Q89: 0 | R89: 0 | S89: 0
A90: 20222 | B90: 1318.49 | C90: 142.38 | D90: 9.260359601067565 | E90: 4262.81 | F90: 29.939668492765836 | G90: 3.233099985589576 | H90: 181649.49 | I90: 1597.91 | J90: 113.67942499890482 | K90: 52249.58 | L90: 32.698700177106346 | M90: 0.2876395634251437 | N90: 279532.55 | O90: 3285.78 | P90: 85.07342244459458 | Q90: 108711.37 | R90: 33.08540742228634 | S90: 0.38890415
A91: 20223 | B91: 582.28 | C91: 52.42 | D91: 11.107974055703929 | E91: 1407.79 | F91: 26.855971003433805 | G91: 2.4177199972521812 | H91: -675.64 | I91: 80.19 | J91: -8.4254895 | K91: 2408 | L91: 30.028681880533732 | M91: -3.5640282 | N91: 90094.93 | O91: 1260.56 | P91: 71.47214729961287 | Q91: 41857.42 | R91: 33.20541664022339 | S91: 0.46459240270234964
A92: 20225 | B92: 2107.47 | C92: 47.82 | D92: 44.070890840652446 | E92: 1763.07 | F92: 36.86888331242158 | G92: 0.8365813036484505 | H92: 2909.84 | I92: 536.87 | J92: 5.420008568182242 | K92: 19129.67 | L92: 35.631847560862035 | M92: 6.5741312237098946 | N92: -3883.19 | O92: 4599.9 | P92: -0.84419009 | Q92: 126524.31 | R92: 27.50588273658123 | S92: -32.58257
A93: 20226 | B93: 0 | C93: 377.52 | D93: 0 | E93: 10943.85 | F93: 28.98879529561348 | G93: 0 | H93: -4708.58 | I93: 839.88 | J93: -5.6062533 | K93: 25528.34 | L93: 30.395223127113397 | M93: -5.4216643 | N93: 30979.99 | O93: 2608.07 | P93: 11.878511696388518 | Q93: 79209.78 | R93: 30.37103298607783 | S93: 2.556804569659319
A94: 20229 | B94: 0 | C94: 5.95 | D94: 0 | E94: 698.54 | F94: 117.40168067226891 | G94: 0 | H94: 4050.64 | I94: 272.45 | J94: 14.867461919618279 | K94: 8392.03 | L94: 30.802092126995777 | M94: 2.0717787806371337 | N94: 40150.94 | O94: 1726.57 | P94: 23.254742060848965 | Q94: 48312.2 | R94: 27.981605147778545 | S94: 1.2032644814791384
A95: 20230 | B95: 2641.9 | C95: 0 | D95: 0 | E95: 0 | F95: 0 | G95: 0 | H95: 26107.37 | I95: 504.9 | J95: 51.70800158447217 | K95: 15598.06 | L95: 30.893365022776788 | M95: 0.5974581124027429 | N95: 107079.05 | O95: 1724.92 | P95: 62.077690559562186 | Q95: 52878.34 | R95: 30.655532 | S95: 0.49382526
A96: 20232 | B96: -1422.75 | C96: 80.01 | D96: -17.782152 | E96: 2156.32 | F96: 26.950631171103613 | G96: -1.5156001 | H96: 12061.3 | I96: 531.55 | J96: 22.690809895588373 | K96: 16232.43 | L96: 30.537917411344182 | M96: 1.3458275641929145 | N96: 96226.22 | O96: 4773.5 | P96: 20.15842044621347 | Q96: 117973.4 | R96: 24.71423483816906 | S96: 1.226000564087418
A97: 20233 | B97: 3076.97 | C97: 713.36 | D97: 4.313348099136481 | E97: 23522.79 | F97: 32.97464113491085 | G97: 7.644790166949954 | H97: 111878.64 | I97: 3167.69 | J97: 35.31868333075522 | K97: 108788.51 | L97: 34.34316804990387 | M97: 0.9723796249221478 | N97: 525435.81 | O97: 11562 | P97: 45.445062272963156 | Q97: 372336.08 | R97: 32.20343193219166 | S97: 0.7086233425925043
A98: 20234 | B98: -443.14 | C98: 27.43 | D98: -16.155304 | E98: 905.83 | F98: 33.02333211811885 | G98: -2.044117 | H98: -7365.46 | I98: 457.6 | J98: -16.095848 | K98: 14994.14 | L98: 32.76691433566434 | M98: -2.0357371 | N98: -16108.18 | O98: 1588.26 | P98: -10.14203 | Q98: 50588.74 | R98: 31.85167415914271 | S98: -3.1405621
A99: 20236 | B99: 12646.66 | C99: 505.15 | D99: 25.035454815401366 | E99: 16703.96 | F99: 33.067326536672276 | G99: 1.3208198844596122 | H99: 76414.3 | I99: 2666.94 | J99: 28.652425626373297 | K99: 79399.84 | L99: 29.771888381440903 | M99: 1.0390704357692213 | N99: 409694.14 | O99: 10625.37 | P99: 38.55810574125889 | Q99: 293918.1 | R99: 27.661916714429708 | S99: 0.7174086014508286
A100: 20239 | B100: 45657.16 | C100: 0 | D100: 0 | E100: 0 | F100: 0 | G100: 0 | H100: 46466.77 | I100: 0 | J100: 0 | K100: 0 | L100: 0 | M100: 0 | N100: -58395.28 | O100: 0 | P100: 0 | Q100: 0 | R100: 0 | S100: 0
...

Sheet Sheet3
A2: Printed: 2/28/2026 2:52:30PM
F4: Unbilled Aging
A7: Customer Code: ALL
B8: Job Number: All
B10: Contract Code: All
B11: Cut Off Date: 02/28/2026
B13: Record Type: R
B14: Exclude Drafts: No
A15: UserID: 4395
A22: Cut Off Date: | B22: 02/28/2026 | C22: Total | D22: 0-30 Days | E22: 31-60 Days | F22: 61-90 Days | G22: 91-120 Days | H22: 121-180 Days | I22: 181-360 Days | J22: 361-1080 Days | K22: 1081+ Days
A24: Project Manager: Birdsall, Ron
A26: 1056143 | B26: Frontier - Maint SSP South Bay (2025-27) | C26: 284867.69 | D26: 98451.385 | E26: 52707.71 | F26: 25804.25 | G26: 52289.698 | H26: 41131.99 | I26: 14482.66 | J26: 0 | K26: 0
A28: 1056275 | B28: ATT - A058K7T - Salinas | C28: 109714.58 | D28: 7643.7 | E28: 102070.88 | F28: 0 | G28: 0 | H28: 0 | I28: 0 | J28: 0 | K28: 0
A30: 1252077 | B30: Frontier - FTTH Morgan Hill | C30: 223093.6 | D30: 222613.6 | E30: 480 | F30: 0 | G30: 0 | H30: 0 | I30: 0 | J30: 0 | K30: 0
A32: 1252082 | B32: Frontier - FTTH - Kenwood | C32: 611690.33 | D32: 438069.54 | E32: 120116.35 | F32: 52836.9 | G32: 667.54 | H32: 0 | I32: 0 | J32: 0 | K32: 0
C35: 1229366.2 | D35: 766778.22 | E35: 275374.94 | F35: 78641.15 | G35: 52957.238 | H35: 41131.99 | I35: 14482.66 | J35: 0 | K35: 0
A38: Project Manager: Bochsler, Dustin
A40: 1385258 | B40: Clear Creek-2024 OSP Phase III | C40: 39573.25 | D40: 18045.48 | E40: 20267.77 | F40: 1260 | G40: 0 | H40: 0 | I40: 0 | J40: 0 | K40: 0
A42: 1386138 | B42: Clear Creek - OSP Phase 3-1 | C42: 27372.44 | D42: 27266.72 | E42: 105.72 | F42: 0 | G42: 0 | H42: 0 | I42: 0 | J42: 0 | K42: 0
C45: 66945.69 | D45: 45312.2 | E45: 20373.49 | F45: 1260 | G45: 0 | H45: 0 | I45: 0 | J45: 0 | K45: 0
A48: Project Manager: Cox, Randy
A50: 1056136 | B50: Frontier - Maint SSP Valley (2025-27) | C50: 463995.06 | D50: 251398.53 | E50: 185266.68 | F50: 4170.74 | G50: 6437.21 | H50: 16721.9 | I50: 0 | J50: 0 | K50: 0
A52: 1056282 | B52: ATT - A05AJGW - Coulterville | C52: 354095.06 | D52: 198391.14 | E52: 155703.92 | F52: 0 | G52: 0 | H52: 0 | I52: 0 | J52: 0 | K52: 0
A54: 2051013 | B54: Sprint-Maintenance-Selma | C54: 15432.177 | D54: 0 | E54: 15432.177 | F54: 0 | G54: 0 | H54: 0 | I54: 0 | J54: 0 | K54: 0
A56: 2052056 | B56: Lumen - NAT OSP CENCAL MSA 2022-Selma | C56: 11945.34 | D56: 0 | E56: 2546.11 | F56: 9399.23 | G56: 0 | H56: 0 | I56: 0 | J56: 0 | K56: 0
A58: 2052135 | B58: ATT - 2024 T&M Rates-Valley | C58: 3320 | D58: 0 | E58: 0 | F58: 0 | G58: 0 | H58: 0 | I58: 3320 | J58: 0 | K58: 0
A60: NEDGSUFRS | B60: VZ-Verizon-NED-Fresno | C60: 993.24 | D60: 0 | E60: 0 | F60: 0 | G60: 0 | H60: 0 | I60: 993.24 | J60: 0 | K60: 0
C63: 849780.88 | D63: 449789.67 | E63: 358948.89 | F63: 13569.97 | G63: 6437.21 | H63: 16721.9 | I63: 4313.24 | J63: 0 | K63: 0
A66: Project Manager: Doran, Dennis
A68: 1380049 | B68: Stayton Telephone - Unit Rates | C68: 14569.78 | D68: 14569.78 | E68: 0 | F68: 0 | G68: 0 | H68: 0 | I68: 0 | J68: 0 | K68: 0
A70: 1380050 | B70: Peoples Telephone - Unit Rates | C70: 5963 | D70: 5963 | E70: 0 | F70: 0 | G70: 0 | H70: 0 | I70: 0 | J70: 0 | K70: 0
C73: 20532.78 | D73: 20532.78 | E73: 0 | F73: 0 | G73: 0 | H73: 0 | I73: 0 | J73: 0 | K73: 0
A76: Project Manager: Haskins, Dwayne
A78: 1056144 | B78: Consolidated Communications MSA | C78: 37802.972 | D78: 2292.972 | E78: 35510 | F78: 0 | G78: 0 | H78: 0 | I78: 0 | J78: 0 | K78: 0
A80: 1056268 | B80: Consolidated Communications - 8320 Belve | C80: 22280 | D80: 0 | E80: 7520 | F80: 14760 | G80: 0 | H80: 0 | I80: 0 | J80: 0 | K80: 0
A82: 1056272 | B82: Sprint - Rancho Cordova Sunrise Blvd | C82: 5030 | D82: 5030 | E82: 0 | F82: 0 | G82: 0 | H82: 0 | I82: 0 | J82: 0 | K82: 0
A84: 1252046 | B84: Frontier - FTTH Elk Grove | C84: 2017959 | D84: 495398.36 | E84: 587840.49 | F84: 203382.28 | G84: 239326.07 | H84: 279349.36 | I84: 212662.42 | J84: 0 | K84: 0
A86: 1252078 | B86: Frontier - FTTH Redding | C86: 4233556.3 | D86: 1205151.2 | E86: 1671181.6 | F86: 1027091.7 | G86: 234059.54 | H86: 80805.44 | I86: 15266.94 | J86: 0 | K86: 0
A88: 1252080 | B88: Frontier - FTTH Northern CA Communities | C88: 94828.39 | D88: 54065.49 | E88: 8352.42 | F88: 32410.48 | G88: 0 | H88: 0 | I88: 0 | J88: 0 | K88: 0
C91: 6411456.7 | D91: 1761938 | E91: 2310404.5 | F91: 1277644.4 | G91: 473385.61 | H91: 360154.8 | I91: 227929.36 | J91: 0 | K91: 0
A94: Project Manager: Higgins, James
A96: 1296002 | B96: AWS - Reno Data Center - OSP | C96: 377486.03 | D96: 97804.306 | E96: 52143.612 | F96: 227538.11 | G96: 0 | H96: 0 | I96: 0 | J96: 0 | K96: 0
A98: 1296171 | B98: VZ-Verizon Business - 98743F - Mill St | C98: 3122.5 | D98: 0 | E98: 0 | F98: 0 | G98: 0 | H98: 0 | I98: 3122.5 | J98: 0 | K98: 0
A100: 1296172 | B100: VZ-Verizon Business - MARC - Reno | C100: 350770.31 | D100: 50756.7 | E100: 29417.79 | F100: 0 | G100: 51224.25 | H100: 82867.57 | I100: 136504 | J100: 0 | K100: 0
A102: 1296249 | B102: ATT - A051KQ2 - Carson City NV | C102: 186061.73 | D102: 128862.68 | E102: 57199.05 | F102: 0 | G102: 0 | H102: 0 | I102: 0 | J102: 0 | K102: 0
A104: 1296267 | B104: ATT - A02QY7S - Reno NV | C104: 152955.79 | D104: 26295.71 | E104: 112286.62 | F104: 14373.46 | G104: 0 | H104: 0 | I104: 0 | J104: 0 | K104: 0
A106: 1296277 | B106: ATT - A02PJDR - Kings Row | C106: 20670.61 | D106: 20670.61 | E106: 0 | F106: 0 | G106: 0 | H106: 0 | I106: 0 | J106: 0 | K106: 0
A108: 18131 | B108: NFS - Wasatch Electric - Moana Ln - Reno | C108: 22093 | D108: 0 | E108: 0 | F108: 22093 | G108: 0 | H108: 0 | I108: 0 | J108: 0 | K108: 0
C111: 1113160 | D111: 324390.01 | E111: 251047.07 | F111: 264004.57 | G111: 51224.25 | H111: 82867.57 | I111: 139626.5 | J111: 0 | K111: 0
A114: Project Manager: Johnson, Bryan
A116: 2036000 | B116: Google-Google Fiber MSA (AZ) | C116: 150705 | D116: 144225 | E116: 6480 | F116: 0 | G116: 0 | H116: 0 | I116: 0 | J116: 0 | K116: 0
A118: 2065000 | B118: Google-Fiber FTTH MDU CO | C118: 516913.67 | D118: 80265 | E118: 94240.41 | F118: 88272.7 | G118: 124492.3 | H118: 129643.26 | I118: 0 | J118: 0 | K118: 0
A120: 2065002 | B120: Google-Fiber FTTH Greenfields CO | C120: 47476.5 | D120: 1122.5 | E120: 14368 | F120: 0 | G120: 23170 | H120: 8816 | I120: 0 | J120: 0 | K120: 0
A122: 2066100 | B122: Ubiquity Services-Retreat at City Center | C122: 150485 | D122: 22925 | E122: 35860 | F122: 91700 | G122: 0 | H122: 0 | I122: 0 | J122: 0 | K122: 0
A124: 2443000 | B124: Google-Google Fiber MSA (TX) | C124: 280134.5 | D124: 213209.5 | E124: 0 | F124: 0 | G124: 0 | H124: 0 | I124: 44819 | J124: 22106 | K124: 0
A126: 2445021 | B126: Ezee Fiber-Franklin Apts | C126: 143426.55 | D126: 13362.05 | E126: 0 | F126: 15678.5 | G126: 114386 | H126: 0 | I126: 0 | J126: 0 | K126: 0
A128: 2445022 | B128: Ezee Fiber-717 Lehman | C128: 87354.4 | D128: 0 | E128: 0 | F128: 5204.48 | G128: 37793.28 | H128: 44356.64 | I128: 0 | J128: 0 | K128: 0
A130: 2445024 | B130: Ezee Fiber - Janicsh Apartments | C130: 64903 | D130: 9065 | E130: 19860 | F130: 35978 | G130: 0 | H130: 0 | I130: 0 | J130: 0 | K130: 0
A132: 2445025 | B132: Ezee - San Antigua | C132: 12365 | D132: 12365 | E132: 0 | F132: 0 | G132: 0 | H132: 0 | I132: 0 | J132: 0 | K132: 0
A134: 2445099 | B134: Google-Fiber Greenfield TX | C134: 199332.5 | D134: 72468 | E134: 54945 | F134: 21906.5 | G134: 39798 | H134: 0 | I134: 10215 | J134: 0 | K134: 0
A136: 2446105 | B136: Ubiquity Services-Heatherwilde Park | C136: 7200 | D136: 7200 | E136: 0 | F136: 0 | G136: 0 | H136: 0 | I136: 0 | J136: 0 | K136: 0
A138: 2660000 | B138: Socket Telecom, LLC - MO (Installs) | C138: 200 | D138: 200 | E138: 0 | F138: 0 | G138: 0 | H138: 0 | I138: 0 | J138: 0 | K138: 0
A140: 2660001 | B140: Socket Telecom, LLC - MO (MDU) | C140: 265524 | D140: 30002.5 | E140: 189201.5 | F140: 45840 | G140: 480 | H140: 0 | I140: 0 | J140: 0 | K140: 0
C143: 1926020.1 | D143: 606409.55 | E143: 414954.91 | F143: 304580.18 | G143: 340119.58 | H143: 182815.9 | I143: 55034 | J143: 22106 | K143: 0
A146: Project Manager: Kotulan, Eric
A148: 1482096 | B148: Lumen - West WA Enterprise MSA (2022-24) | C148: 177944.35 | D148: 0 | E148: 0 | F148: 0 | G148: 0 | H148: 0 | I148: 16252.02 | J148: 159169.71 | K148: 2522.62
A150: 1483077 | B150: Lumen - Northeast WA Consumer (2022-25) | C150: 421670.2 | D150: 59468.39 | E150: 98643.569 | F150: 94716.598 | G150: 78025.75 | H150: 44182.81 | I150: 33409.549 | J150: 13223.54 | K150: 0
A152: 1483098 | B152: Lumen - San Juans Consumer (2023-25) | C152: 40996.25 | D152: 6803.17 | E152: 17981.5 | F152: 0 | G152: 5264.22 | H152: 9456 | I152: 0 | J152: 1491.36 | K152: 0
A154: 1483099 | B154: Lumen - West WA Consumer (2023-25) | C154: 10317650 | D154: 1548521 | E154: 944464.92 | F154: 1185850.2 | G154: 863578.61 | H154: 1550000.7 | I154: 2538029.1 | J154: 1683693.6 | K154: 3511.46
A156: 1485254 | B156: Lumen - WA Enterprise MSA (2025-27) | C156: 434011.67 | D156: 190446.32 | E156: 35293.52 | F156: 11874.34 | G156: 98375.98 | H156: 65586.25 | I156: 32435.263 | J156: 0 | K156: 0
A158: 1486125 | B158: Lumen - 2025LE000148 Fiber Overbuild | C158: 2597329.1 | D158: 893824.58 | E158: 412129.03 | F158: 190003.54 | G158: 422857.02 | H158: 617564.19 | I158: 60950.78 | J158: 0 | K158: 0
A160: 1486278 | B160: Lumen - Northeast WA Consumer (2026-28) | C160: 223599.72 | D160: 111330.65 | E160: 112269.07 | F160: 0 | G160: 0 | H160: 0 | I160: 0 | J160: 0 | K160: 0
A162: 1486279 | B162: Lumen - San Juans WA Consumer (2026-28) | C162: 962.74 | D162: 962.74 | E162: 0 | F162: 0 | G162: 0 | H162: 0 | I162: 0 | J162: 0 | K162: 0
A164: 1486280 | B164: Lumen - West WA Consumer (2026-28) | C164: 1181270.6 | D164: 798152.2 | E164: 383118.35 | F164: 0 | G164: 0 | H164: 0 | I164: 0 | J164: 0 | K164: 0
A166: 1486281 | B166: Lumen - West WA Drops (2026-28) | C166: 10584.335 | D166: 10584.335 | E166: 0 | F166: 0 | G166: 0 | H166: 0 | I166: 0 | J166: 0 | K166: 0
C169: 15406019 | D169: 3620093.4 | E169: 2003900 | F169: 1482444.7 | G169: 1468101.6 | H169: 2286790 | I169: 2681076.7 | J169: 1857578.2 | K169: 6034.08
A172: Project Manager: Lyon, Stewart
A174: 1136235 | B174: Idaho County - DIGB2 Phase II - Np - Grv | C174: 362593.72 | D174: 177198.9 | E174: 185394.82 | F174: 0 | G174: 0 | H174: 0 | I174: 0 | J174: 0 | K174: 0
A176: 1136238 | B176: Avista - Dalton sub to CDA Call Center | C176: 1216 | D176: 1216 | E176: 0 | F176: 0 | G176: 0 | H176: 0 | I176: 0 | J176: 0 | K176: 0
A178: 1386118 | B178: Alyrica - Webfoot | C178: 581319.88 | D178: 0 | E178: 0 | F178: 1260 | G178: 107096.1 | H178: 160973.59 | I178: 311990.19 | J178: 0 | K178: 0
A180: 1485141 | B180: Jefferson PUD-Olympic Fiber Build | C180: 93446.178 | D180: 37756.42 | E180: 43118.118 | F180: 12571.64 | G180: 0 | H180: 0 | I180: 0 | J180: 0 | K180: 0
A182: 1485262 | B182: Astound - Clallam County WSBO Phase | C182: 570296.66 | D182: 553883.31 | E182: 16413.35 | F182: 0 | G182: 0 | H182: 0 | I182: 0 | J182: 0 | K182: 0
A184: 1485263 | B184: Astound - Clallam County PWB Phase | C184: 55020.85 | D184: 37232.75 | E184: 17788.1 | F184: 0 | G184: 0 | H184: 0 | I184: 0 | J184: 0 | K184: 0
A186: 1486271 | B186: Grant County PUD (2026-27) | C186: 25967.175 | D186: 25967.175 | E186: 0 | F186: 0 | G186: 0 | H186: 0 | I186: 0 | J186: 0 | K186: 0
A188: 1486285 | B188: Adams County - Othello FTTH | C188: 648392.32 | D188: 648392.32 | E188: 0 | F188: 0 | G188: 0 | H188: 0 | I188: 0 | J188: 0 | K188: 0
C191: 2338252.8 | D191: 1481646.9 | E191: 262714.39 | F191: 13831.64 | G191: 107096.1 | H191: 160973.59 | I191: 311990.19 | J191: 0 | K191: 0
A194: Project Manager: McElyea, Grant
A196: 1056117 | B196: Siskiyou Tel - OSP Routine Maint (25-26) | C196: 48655.8 | D196: 48655.8 | E196: 0 | F196: 0 | G196: 0 | H196: 0 | I196: 0 | J196: 0 | K196: 0
A198: 1056140 | B198: Siskiyou Tel - MMBI OSP | C198: 358865.37 | D198: 287465.62 | E198: 50679.41 | F198: 5446.5 | G198: 3635.8 | H198: 11638.04 | I198: 0 | J198: 0 | K198: 0
C201: 407521.17 | D201: 336121.42 | E201: 50679.41 | F201: 5446.5 | G201: 3635.8 | H201: 11638.04 | I201: 0 | J201: 0 | K201: 0
A204: Project Manager: Mullins, Jonathan
A206: 1056162 | B206: ATT - A055YA7 - Williams St San Leandro | C206: 3967.6 | D206: 0 | E206: 0 | F206: 0 | G206: 0 | H206: 0 | I206: 3967.6 | J206: 0 | K206: 0
A208: 1056205 | B208: ATT - A02TN2E - B St Hayward | C208: 21107.85 | D208: 0 | E208: 0 | F208: 4221.57 | G208: 0 | H208: 4221.57 | I208: 12664.71 | J208: 0 | K208: 0
A210: 1056212 | B210: ATT - A058VW3 - 1075 40th St Emeryville | C210: 30576.38 | D210: 0 | E210: 13202.13 | F210: 0 | G210: 0 | H210: 17374.25 | I210: 0 | J210: 0 | K210: 0
A212: 1056215 | B212: ATT - A054P5Z - 493 Walsh Rd Atherton | C212: 199561.94 | D212: 0 | E212: 51209.338 | F212: 0 | G212: 0 | H212: 148352.6 | I212: 0 | J212: 0 | K212: 0
A214: 1056220 | B214: ATT - A051MPE - 1518 Rishell Dr Concord | C214: 124536.5 | D214: 0 | E214: 0 | F214: 12384.35 | G214: 21150.8 | H214: 91001.35 | I214: 0 | J214: 0 | K214: 0
A216: 1056227 | B216: ATT - Dig MSA - Bay Area | C216: 118947.72 | D216: 77164.3 | E216: 35621.03 | F216: 5264.65 | G216: 0 | H216: 897.74 | I216: 0 | J216: 0 | K216: 0
A218: 1056228 | B218: ATT - Dig MSA - Northern Areas | C218: 20265.25 | D218: 17208.14 | E218: 2108.84 | F218: 948.27 | G218: 0 | H218: 0 | I218: 0 | J218: 0 | K218: 0
A220: 1056230 | B220: ATT - BSW - Bay Area | C220: 16321.31 | D220: 10317.34 | E220: 667.7 | F220: 3672.18 | G220: 1664.09 | H220: 0 | I220: 0 | J220: 0 | K220: 0
A222: 1056231 | B222: ATT - BSW - Northern | C222: 2162.35 | D222: 2162.35 | E222: 0 | F222: 0 | G222: 0 | H222: 0 | I222: 0 | J222: 0 | K222: 0
...

Sheet SAP Contracts
A1: Sales Contract | B1: Sold-to Party | C1: Customer Reference | D1: Valid-From Date | E1: Valid-To Date | F1: Overall Status | G1: Approval Status | H1: Net Value | I1: Document Date | J1: Description
A2: 21922 | B2: T-Mobile USA, Inc (C000756) | C2: 2386061 | D2: 46023 | E2: 46174 | F2: Open | G2: Not Relevant | H2: 0 | I2: 46081 | J2: T-Mobile-Eastern OR Market 2026-2027
A3: 21921 | B3: Unwired Broadband, LLC (C001939) | C3: 1056298 | D3: 46062 | E3: 46203 | F3: Open | G3: Not Relevant | H3: 0 | I3: 46080 | J3: Unwired Broadband - Gustine
A4: 21920 | B4: Unwired Broadband, LLC (C001939) | C4: 1056297 | D4: 46063 | E4: 46203 | F4: Open | G4: Not Relevant | H4: 0 | I4: 46080 | J4: Unwired Broadband - Coalinga
A5: 21906 | B5: Ezee Fiber Texas, LLC (C001484) | C5: 2445025 | D5: 46076 | E5: 46441 | F5: Open | G5: Not Relevant | H5: 0 | I5: 46080 | J5: Ezee - San Antigua
A6: 21904 | B6: Ubiquity Services, LLC (C001047) | C6: 2446105 | D6: 46075 | E6: 46440 | F6: Open | G6: Not Relevant | H6: 0 | I6: 46080 | J6: Ubiquity Services-Heatherwilde Park
A7: 21903 | B7: Verizon Sourcing LLC (C000810) | C7: 2387000 | D7: 46065 | E7: 46275 | F7: Open | G7: Not Relevant | H7: 0 | I7: 46080 | J7: VZ-Verizon OR Ruch
A8: 21902 | B8: Portland General Electric Company (C000906) | C8: 1386310 | D8: 46079 | E8: 46173 | F8: Open | G8: Not Relevant | H8: 0 | I8: 46080 | J8: PGE - Salem Fiber Reclosure
A9: 21901 | B9: Portland General Electric Company (C000906) | C9: 1386309 | D9: 46078 | E9: 46173 | F9: Open | G9: Not Relevant | H9: 0 | I9: 46080 | J9: PGE - Rhododendron Sub
A10: 21900 | B10: Sprint/United Management Company (C000696) | C10: 1056308 | D10: 46076 | E10: 46203 | F10: Open | G10: Not Relevant | H10: 0 | I10: 46080 | J10: Sprint - Manning and Carneal Rd
A11: 21899 | B11: Fidium Enterprise Services LLC (C000224) | C11: 1056305 | D11: 46076 | E11: 46203 | F11: Open | G11: Not Relevant | H11: 0 | I11: 46079 | J11: Consolidated Communications - Zinfandel
A12: 21898 | B12: Canby Telephone Association (C000919) | C12: 1386204 | D12: 46072 | E12: 46142 | F12: Open | G12: Not Relevant | H12: 0 | I12: 46079 | J12: Directlink - Blount Rd Ped Removals
A13: 21897 | B13: Clear Creek Mutual Telephone Company (C001455) | C13: 1386302 | D13: 46069 | E13: 46173 | F13: Open | G13: Not Relevant | H13: 15.95 | I13: 46079 | J13: Clear Creek - OSP Phase 4
... A692: 21030 | B692: Cablecom, LLC (IC2600) | C692: 011101 | D692: 45658 | E692: 45659 | F692: Open | G692: Not Relevant | H692: 0 | I692: 46066 | J692: IC-CCI-San Mateo Old County Rd Pole Repl

Sheet Active North Sky Projects
A1: contract | B1: Contract Description | C1: Legacy Project # | D1: SAP Contract # | E1: project description | F1: project status | G1: customer name | H1: start date | I1: end date | J1: contract type | L1: SAP Project #
A2: ADAMSNSC2026O190 | B2: NSC--Othello FTTH | C2: 1486285 | D2: =VLOOKUP(C2,'[1]SAP Contract #s'!A:B,2,FALSE) -> 21668 | E2: Adams County - Othello FTTH | F2: A | G2: Adams County, Washington | H2: 46021 | I2: 46386 | J2: BIDC
A3: ALYRINSC2025O147 | B3: NSC--Alyrica Webfoot FTTH CSA | C3: 1386118 | D3: =VLOOKUP(C3,'[1]SAP Contract #s'!A:B,2,FALSE) -> 21545 | E3: Alyrica - Webfoot | F3: A | G3: Alyrica Networks | H3: 45747 | I3: 46235 | J3: BIDC
A4: AMAZONSC2025O180 | B4: NSC--Amazon PO US59072694 | C4: 1296001 | D4: =VLOOKUP(C4,'[1]SAP Contract #s'!A:B,2,FALSE) -> 21279 | E4: AWS - Reno Data Center - OSP ENG | F4: A | G4: Point to Point Communications, Inc. | H4: 45992 | I4: 46752 | J4: INCO
A5: AMAZONSC2025O180 | B5: NSC--Amazon PO US59072694 | C5: 1296002 | D5: =VLOOKUP(C5,'[1]SAP Contract #s'!A:B,2,FALSE) -> 21280 | E5: AWS - Reno Data Center - OSP | F5: A | G5: Point to Point Communications, Inc. | H5: 45992 | I5: 46752 | J5: INCO
A6: AMAZONSC2025O180 | B6: NSC--Amazon PO US59072694 | C6: 1296243 | D6: =VLOOKUP(C6,'[1]SAP Contract #s'!A:B,2,FALSE) -> 21549 | E6: AWS - Reno Data Center - Campus | F6: A | G6: Amazon Data Services, Inc. | H6: 45943 | I6: 46387 | J6: BIDC
A7: AMERINSC2018O021 | B7: MCS 06.06.18 Division 2 | C7: 2484115 | D7: =VLOOKUP(C7,'[1]SAP Contract #s'!A:B,2,FALSE) -> 21171 | E7: American Tower Corporation-WA | F7: A | G7: American Tower Corporation | H7: 45089 | I7: 46112 | J7: WIOT
A8: ARCADNSC2025O158 | B8: NSC--Arcadian Master Construction Contract/ MSA | C8: 1056135 | D8: =VLOOKUP(C8,'[1]SAP Contract #s'!A:B,2,FALSE) -> 21484 | E8: Arcadian - Redwood Segment 5-1 | F8: A | G8: Arcadian Infracom, Inc. | H8: 45839 | I8: 46598 | J8: BIDC
A9: AT&TSGSU2022095 | B9: GSU--AT&T CMSA # CGA2022.1077 | C9: 4052152 | D9: =VLOOKUP(C9,'[1]SAP Contract #s'!A:B,2,FALSE) -> 21621 | E9: ATT - WE12 CSVA 3 (2024-26) | F9: A | G9: AT&T Services, Inc | H9: 45597 | I9: 46326 | J9: TCMS
A10: AT&TSNSC2025O173 | B10: NSC--AT&T ABWS Agmt. # 30100884 | C10: 1056227 | D10: =VLOOKUP(C10,'[1]SAP Contract #s'!A:B,2,FALSE) -> 21486 | E10: ATT - Dig MSA - Bay Area | F10: A | G10: AT&T Services, Inc | H10: 45915 | I10: 46752 | J10: TCMS
A11: AT&TSNSC2025O173 | B11: NSC--AT&T ABWS Agmt. # 30100884 | C11: 1056228 | D11: =VLOOKUP(C11,'[1]SAP Contract #s'!A:B,2,FALSE) -> 21518 | E11: ATT - Dig MSA - Northern Areas | F11: A | G11: AT&T Services, Inc | H11: 45915 | I11: 46752 | J11: TCMS
A12: AT&TSNSC2025O177 | B12: NSC--AT&T BSW Cont. # 30100905 | C12: 1056231 | D12: =VLOOKUP(C12,'[1]SAP Contract #s'!A:B,2,FALSE) -> 21265 | E12: ATT - BSW - Northern | F12: A | G12: AT&T Services, Inc | H12: 45915 | I12: 46752 | J12: TCMS
A13: AT&TSNSC2025O177 | B13: NSC--AT&T BSW Cont. # 30100905 | C13: 1056230 | D13: =VLOOKUP(C13,'[1]SAP Contract #s'!A:B,2,FALSE) -> 21527 | E13: ATT - BSW - Bay Area | F13: A | G13: AT&T Services, Inc | H13: 45915 | I13: 46752 | J13: TCMS
... A57: ATT00GSU2015O009 | B57: AT&T ACAS Agreement | C57: 2052135 | D57: =VLOOKUP(C57,'[1]SAP Contract #s'!A:B,2,FALSE) -> 21623 | E57: ATT - 2024 T&M Rates-Valley | F57: A | G57: AT&T Services, Inc | H57: 45365 | I57: 46112 | J57: TCMS
A58: ATT00GSU2015O009 | B58: AT&T ACAS Agreement | C58: 1056296 | D58: 21878 | E58: ATT - A057WYA - San Rafael | F58: A | G58: AT&T Services, Inc | H58: 46069 | I58: 46113 | J58: BIDC
A59: ATT00GSU2015O009 | B59: AT&T ACAS Agreement | C59: 1056299 | D59: 21888 | E59: ATT - A0578EH - Tulare MH T331 Cable Dam | F59: A | G59: AT&T Services, Inc | H59: 46063 | I59: 46066 | J59: BIDC
A60: ATT00GSU2015O009 | B60: AT&T ACAS Agreement | C60: 1056301 | D60: 21850 | E60: ATT - A058D26 - Greeley Hill | F60: A | G60: AT&T Services, Inc | H60: 46071 | I60: 46387 | J60: BIDC
A61: ATT00GSU2015O009 | B61: AT&T ACAS Agreement | C61: 1056307 | D61: 21891 | E61: ATT - 525 Market St - PO 06600653 | F61: A | G61: AT&T Services, Inc | H61: 46076 | I61: 46203 | J61: BIDC
A62: ATT00GSU2015O009 | B62: AT&T ACAS Agreement | C62: 1056311 | D62: 21893 | E62: ATT - A058YLP FTTH - Ceres | F62: A | G62: AT&T Services, Inc | H62: 46082 | I62: 46387 | J62: BIDC
A63: ATT00GSU2015O009 | B63: AT&T ACAS Agreement | C63: 1056312 | D63: 21879 | E63: ATT - A056VEP - Franklin Bridge Splicing | F63: A | G63: AT&T Services, Inc | H63: 46082 | I63: 46387 | J63: BIDC
A64: ATT00GSU2015O009 | B64: AT&T ACAS Agreement | C64: 1056313 | D64: 21880 | E64: ATT - NB01 - San Francisco Downtown | F64: A | G64: AT&T Services, Inc | H64: 46076 | I64: 46752 | J64: TCMS
A65: ATT00GSU2015O009 | B65: AT&T ACAS Agreement | C65: 1056314 | D65: 21881 | E65: ATT - NB02 - San Francisco Outside | F65: A | G65: AT&T Services, Inc | H65: 46076 | I65: 46752 | J65: TCMS
A66: ATT00GSU2015O009 | B66: AT&T ACAS Agreement | C66: 1056315 | D66: 21882 | E66: ATT - NB03 - Oakland-Franklin | F66: A | G66: AT&T Services, Inc | H66: 46076 | I66: 46752 | J66: TCMS
A67: ATT00GSU2015O009 | B67: AT&T ACAS Agreement | C67: 1056316 | D67: 21883 | E67: ATT - NB04 - Hayward-Oakland | F67: A | G67: AT&T Services, Inc | H67: 46076 | I67: 46752 | J67: TCMS
A68: ATT00GSU2015O009 | B68: AT&T ACAS Agreement | C68: 1056317 | D68: 21884 | E68: ATT - NB05 - Richmond-Berkeley | F68: A | G68: AT&T Services, Inc | H68: 46076 | I68: 46752 | J68: TCMS
A69: ATT00GSU2015O009 | B69: AT&T ACAS Agreement | C69: 1056318 | D69: 21885 | E69: ATT - NB06 - Antioch-Martinez | F69: A | G69: AT&T Services, Inc | H69: 46076 | I69: 46752 | J69: TCMS
... A74: ATT00GSU2015O009 | B74: AT&T ACAS Agreement | C74: 1296306 | D74: 21890 | E74: ATT - A0510AX - Carson City | F74: A | G74: AT&T Services, Inc | H74: 46076 | I74: 46387 | J74: BIDC
A75: ATT00NSC2015O010 | B75: AT&T ACAS Agreement | C75: 1486265 | D75: =VLOOKUP(C75,'[1]SAP Contract #s'!A:B,2,FALSE) -> 21157 | E75: AT&T - Foster Rd | F75: A | G75: AT&T Services, Inc | H75: 45978 | I75: 46112 | J75: BIDC
A76: ATT00NSC2015O010 | B76: AT&T ACAS Agreement | C76: 1136264 | D76: =VLOOKUP(C76,'[1]SAP Contract #s'!A:B,2,FALSE) -> 21565 | E76: AT&T - CDA Bridge Cable Pulling | F76: A | G76: AT&T Services, Inc | H76: 45978 | I76: 46108 | J76: BIDC
A77: AVISTNSC2024O128 | B77: NSC--Avista Cont. # R-42077 | C77: 1136238 | D77: =VLOOKUP(C77,'[1]SAP Contract #s'!A:B,2,FALSE) -> 21165 | E77: Avista - Dalton sub to CDA Call Center | F77: A | G77: Avista Corporation | H77: 45936 | I77: 46142 | J77: BIDC
A78: BOOTHGSU2023O087 | B78: GSU--Booth Short Form Agmt | C78: 1056218 | D78: =VLOOKUP(C78,'[1]SAP Contract #s'!A:B,2,FALSE) -> 21263 | E78: BNCSI - Pine Flat to Dam Aerial Feed | F78: A | G78: Booth Network Consulting Services, Inc. | H78: 45905 | I78: 46112 | J78: BIDC
A79: CALORNSC2024O129 | B79: NSC--Cal-Ore J.O.#IDR2402 OSP | C79: 1055210 | D79: =VLOOKUP(C79,'[1]SAP Contract #s'!A:B,2,FALSE) -> 21421 | E79: CAL-Ore 2024 | F79: A | G79: Cal-Ore Telephone Company | H79: 45555 | I79: 45808 | J79: BIDC
A80: CANBYNSC2017O018 | B80: Canby Telephone dba DirectLink | C80: 1387065 | D80: =VLOOKUP(C80,'[1]SAP Contract #s'!A:B,2,FALSE) -> 21065 | E80: DirectLink - Hourly Work | F80: A | G80: Canby Telephone Association | H80: 42370 | I80: 46387 | J80: TEOT
A81: CANBYNSC2017O018 | B81: Canby Telephone dba DirectLink | C81: 1386274 | D81: =VLOOKUP(C81,'[1]SAP Contract #s'!A:B,2,FALSE) -> 21219 | E81: Directlink - Molalla Forest Ped Removals | F81: A | G81: Canby Telephone Association | H81: 46013 | I81: 46080 | J81: BIDC
A82: CANBYNSC2025O138 | B82: NSC--Directlink - WO#845-2024-0001 | C82: 1386100 | D82: =VLOOKUP(C82,'[1]SAP Contract #s'!A:B,2,FALSE) -> 21526 | E82: Directlink - Mt Angel Town FTTH | F82: A | G82: Canby Telephone Association | H82: 45684 | I82: 46022 | J82: BIDC
A83: CCPUDNSC2019O032 | B83: Clark PUD Cont Q2367 | C83: 1486293 | D83: =VLOOKUP(C83,'[1]SAP Contract #s'!A:B,2,FALSE) -> 21303 | E83: Clark PUD - Jones Substation | F83: A | G83: Clark Public Utilities | H83: 46052 | I83: 46080 | J83: TEOT
A84: CCPUDNSC2019O032 | B84: Clark PUD Cont Q2367 | C84: 148704401 | D84: =VLOOKUP(C84,'[1]SAP Contract #s'!A:B,2,FALSE) -> 21670 | E84: Clark PUD-Small Works Project | F84: A | G84: Clark Public Utilities | H84: 42736 | I84: 46022 | J84: TEOT
A85: CCPUDNSC2019O032 | B85: Clark PUD Cont Q2367 | C85: 1486295 | D85: 21875 | E85: Clark PUD - NE 179th St Fiber Relocation | F85: A | G85: Clark Public Utilities | H85: 46057 | I85: 46142 | J85: TEOT
A86: CHILLNSC2025O167 | B86: NSC--Hillsboro Cont. #6596 | C86: 1386198 | D86: =VLOOKUP(C86,'[1]SAP Contract #s'!A:B,2,FALSE) -> 21183 | E86: City of Hillsboro - HiLight Network MSA | F86: A | G86: City of Hillsboro | H86: 45857 | I86: 46934 | J86: TCMS
A87: CLACKNSC2024O132 | B87: NSC--Clackamas Cty Cont #1049 CBX Marmot | C87: 1385256 | D87: =VLOOKUP(C87,'[1]SAP Contract #s'!A:B,2,FALSE) -> 21494 | E87: Clackamas County-Marmot Road | F87: A | G87: Clackamas County | H87: 45663 | I87: 46418 | J87: BIDC
A88: CLEARNSC2023O087 | B88: NSC--Clear Creek JO #623-2023-0005 | C88: 1384180 | D88: =VLOOKUP(C88,'[1]SAP Contract #s'!A:B,2,FALSE) -> 21119 | E88: Clear Creek-FTTH P1 Project | F88: A | G88: Clear Creek Mutual Telephone Company | H88: 45173 | I88: 46022 | J88: TEOT
A89: CLEARNSC2024O110 | B89: NSC-- Clear Creek PH II | C89: 1385143 | D89: =VLOOKUP(C89,'[1]SAP Contract #s'!A:B,2,FALSE) -> 21488 | E89: Clear Creek-FTTH Phase II | F89: A | G89: Clear Creek Mutual Telephone Company | H89: 45369 | I89: 45869 | J89: BIDC
A90: CLEARNSC2024O137 | B90: NSC--Clear Creek 2024 OSP - Phase III | C90: 1385258 | D90: =VLOOKUP(C90,'[1]SAP Contract #s'!A:B,2,FALSE) -> 21514 | E90: Clear Creek-2024 OSP Phase III | F90: A | G90: Clear Creek Mutual Telephone Company | H90: 45663 | I90: 46022 | J90: BIDC
A91: CLEARNSC2025O153 | B91: NSC--Clear Creek OSP Phase 3.1 | C91: 1386138 | D91: =VLOOKUP(C91,'[1]SAP Contract #s'!A:B,2,FALSE) -> 21221 | E91: Clear Creek OSP Phase 3-1 | F91: A | G91: Clear Creek Mutual Telephone Company | H91: 45784 | I91: 46053 | J91: BIDC
A92: CLEARNSC2026O192 | B92: NSC--Clear Creek OSP Phase 4 | C92: 1386302 | D92: 21897 | E92: Clear Creek - OSP Phase 4 | F92: A | G92: Clear Creek Mutual Telephone Company | H92: 46069 | I92: 46173 | J92: BIDC
A93: COLVINSC2023O091 | B93: NSC--Colville Reservation Maint. Cont. | C93: 2484120 | D93: =VLOOKUP(C93,'[1]SAP Contract #s'!A:B,2,FALSE) -> 21412 | E93: Colville Tribes - Wireless Maintenance | F93: A | G93: Confederated Tribes of the Colville Reservation | H93: 45224 | I93: 46142 | J93: WIMS
A94: COLVINSC2025O166 | B94: NSC--Colville Tribes Wireless Site Proj. | C94: 2486025 | D94: =VLOOKUP(C94,'[1]SAP Contract #s'!A:B,2,FALSE) -> 21407 | E94: Colville Tribes - Wireless Sites | F94: A | G94: Confederated Tribes of the Colville Reservation | H94: 45868 | I94: 46320 | J94: WIOT
A95: COLVINSC2025O183 | B95: NSC--CTCR Twin Lakes FTTH | C95: 1486266 | D95: =VLOOKUP(C95,'[1]SAP Contract #s'!A:B,2,FALSE) -> 21402 | E95: Colville Tribes - Twin Lakes FTTH | F95: A | G95: Confederated Tribes of the Colville Reservation | H95: 46006 | I95: 46265 | J95: BIDC
A96: COLVINSC2026O191 | B96: NSC--Colville PO 187656 | C96: 2486026 | D96: =VLOOKUP(C96,'[1]SAP Contract #s'!A:B,2,FALSE) -> 21415 | E96: Colville Tribes - MAT Solar | F96: A | G96: Confederated Tribes of the Colville Reservation | H96: 45943 | I96: 46327 | J96: WIOT
A97: COMMPNSC2022O055 | B97: NSC--MCA 308515.C-CommPro | C97: 2254000 | D97: =VLOOKUP(C97,'[1]SAP Contract #s'!A:B,2,FALSE) -> 21273 | E97: CommPro Services, LLC (MS) | F97: A | G97: CommPro Services, LLC | H97: 45047 | I97: 46203 | J97: TCMS
A98: COMMPNSC2022O055 | B98: NSC--MCA 308515.C-CommPro | C98: 2434000 | D98: =VLOOKUP(C98,'[1]SAP Contract #s'!A:B,2,FALSE) -> 21290 | E98: CommPro Services, LLC - TN | F98: A | G98: CommPro Services, LLC | H98: 45006 | I98: 46387 | J98: TCMS
A99: COMMPNSC2022O055 | B99: NSC--MCA 308515.C-CommPro | C99: 2014000 | D99: =VLOOKUP(C99,'[1]SAP Contract #s'!A:B,2,FALSE) -> 21307 | E99: CommPro Services, LLC - AL | F99: A | G99: CommPro Services, LLC | H99: 45000 | I99: 46387 | J99: TCMS
A100: COMMPNSC2022O055 | B100: NSC--MCA 308515.C-CommPro | C100: 2156000 | D100: =VLOOKUP(C100,'[1]SAP Contract #s'!A:B,2,FALSE) -> 21554 | E100: CommPro Services, LLC - IN | F100: A | G100: CommPro Services, LLC | H100: 45772 | I100: 46387 | J100: TCMS
A101: COMMPNSC2022O055 | B101: NSC--MCA 308515.C-CommPro | C101: 2180000 | D101: =VLOOKUP(C101,'[1]SAP Contract #s'!A:B,2,FALSE) -> 21557 | E101: CommPro Services, LLC - KY | F101: A | G101: CommPro Services, LLC | H101: 45565 | I101: 46052 | J101: TCMS
A102: COMMPNSC2022O055 | B102: NSC--MCA 308515.C-CommPro | C102: 2413000 | D102: =VLOOKUP(C102,'[1]SAP Contract #s'!A:B,2,FALSE) -> 21591 | E102: CommPro Services, LLC - SC | F102: A | G102: CommPro Services, LLC | H102: 44851 | I102: 46599 | J102: TCMS
A103: CONSONSC2022O066 | B103: NSC--CBS SFA Residential Install | C103: 2383011 | D103: =VLOOKUP(C103,'[1]SAP Contract #s'!A:B,2,FALSE) -> 21572 | E103: Consol Bus Svs-Canby dba Directlink Resi | F103: A | G103: Consolidated Business Services LLC | H103: 44865 | I103: 46174 | J103: TEOT
A104: CONSONSC2025O154 | B104: NSC--Consolidated CSA 04.18.25 | C104: 1056216 | D104: =VLOOKUP(C104,'[1]SAP Contract #s'!A:B,2,FALSE) -> 21262 | E104: Consolidated Communications - Natomas to | F104: A | G104: Fidium Enterprise Services LLC | H104: 45896 | I104: 46234 | J104: BIDC
... A108: CONSONSC2025O154 | B108: NSC--Consolidated CSA 04.18.25 | C108: 1056144 | D108: =VLOOKUP(C108,'[1]SAP Contract #s'!A:B,2,FALSE) -> 21569 | E108: Consolidated Communications MSA | F108: A | G108: Fidium Enterprise Services LLC | H108: 45789 | I108: 46022 | J108: TCMS
A109: CONSONSC2025O154 | B109: NSC--Consolidated CSA 04.18.25 | C109: 1056305 | D109: 21899 | E109: Consolidated Communications - Zinfandel | F109: A | G109: Fidium Enterprise Services LLC | H109: 46076 | I109: 46203 | J109: BIDC
A110: CPORTNSC2024O104 | B110: NSC--COP Maint. Cont. # 31002600 | C110: 1385127 | D110: =VLOOKUP(C110,'[1]SAP Contract #s'!A:B,2,FALSE) -> 21113 | E110: City of Portland-Splicing Maintenance 31 | F110: A | G110: City of Portland | H110: 45341 | I110: 47483 | J110: TCMS
A111: CROWNGSU2024O094 | B111: GSU--Crown Rapid Connect Maint. Appendix | C111: 2052147 | E111: Crown Castle-Rapid Connect GC Maintenanc | F111: A | G111: Crown Castle USA Inc | H111: 45586 | I111: 46387 | J111: TCMS
A112: CROWNNSC2016O013 | B112: CSMA (4.1.2016) | C112: 1056208 | D112: =VLOOKUP(C112,'[1]SAP Contract #s'!A:B,2,FALSE) -> 21201 | E112: Crown Castle - Network West Area Pricing | F112: A | G112: Crown Castle USA Inc | H112: 45885 | I112: 46752 | J112: TCMS
A113: CROWNNSC2024O131 | B113: NSC--Crown Rapid Connect Maint. Appendix | C113: 2136014 | D113: =VLOOKUP(C113,'[1]SAP Contract #s'!A:B,2,FALSE) -> 21191 | E113: Crown Castle - ID | F113: A | G113: Crown Castle USA Inc | H113: 45901 | I113: 45925 | J113: WIMS
A114: CSHWDNSC2025O160 | B114: NSC--BPD Broadband Expansion | C114: 1386152 | D114: =VLOOKUP(C114,'[1]SAP Contract #s'!A:B,2,FALSE) -> 21067 | E114: City of Sherwood - Broadband Expansion | F114: A | G114: City of Sherwood | H114: 45809 | I114: 46234 | J114: BIDC
A115: DECLANSC2025O175 | B115: NSC--Declaration Networks MCSA | C115: 1486221 | D115: =VLOOKUP(C115,'[1]SAP Contract #s'!A:B,2,FALSE) -> 21687 | E115: Declaration - Deep Lake, Seg 6 and 7 | F115: A | G115: Declaration Networks Group, Inc. | H115: 45915 | I115: 45961 | J115: BIDC
A116: EZEEFNSC2024O116 | B116: NSC--Ezee Fiber Proposal Work | C116: 2445009 | D116: =VLOOKUP(C116,'[1]SAP Contract #s'!A:B,2,FALSE) -> 21059 | E116: Ezee Fiber Texas-Venetian Apts | F116: A | G116: Ezee Fiber Texas, LLC | H116: 45838 | I116: 46203 | J116: BIDC
A117: EZEEFNSC2024O116 | B117: NSC--Ezee Fiber Proposal Work | C117: 2445021 | D117: =VLOOKUP(C117,'[1]SAP Contract #s'!A:B,2,FALSE) -> 21072 | E117: Ezee Fiber-Franklin Apts | F117: A | G117: Ezee Fiber Texas, LLC | H117: 45827 | I117: 46203 | J117: BIDC
A118: EZEEFNSC2024O116 | B118: NSC--Ezee Fiber Proposal Work | C118: 2445022 | D118: =VLOOKUP(C118,'[1]SAP Contract #s'!A:B,2,FALSE) -> 21078 | E118: Ezee Fiber-717 Lehman | F118: A | G118: Ezee Fiber Texas, LLC | H118: 45933 | I118: 46203 | J118: BIDC
A119: EZEEFNSC2024O116 | B119: NSC--Ezee Fiber Proposal Work | C119: 2445023 | D119: =VLOOKUP(C119,'[1]SAP Contract #s'!A:B,2,FALSE) -> 21089 | E119: Ezee Fiber - Azulejo Apartments | F119: A | G119: Ezee Fiber Texas, LLC | H119: 45945 | I119: 46203 | J119: BIDC
A120: EZEEFNSC2024O116 | B120: NSC--Ezee Fiber Proposal Work | C120: 2445024 | D120: =VLOOKUP(C120,'[1]SAP Contract #s'!A:B,2,FALSE) -> 21099 | E120: Ezee Fiber - Janicsh Apartments | F120: A | G120: Ezee Fiber Texas, LLC | H120: 45987 | I120: 46203 | J120: BIDC
A121: EZEEFNSC2024O116 | B121: NSC--Ezee Fiber Proposal Work | C121: 2445007 | D121: =VLOOKUP(C121,'[1]SAP Contract #s'!A:B,2,FALSE) -> 21381 | E121: Ezee Fiber Texas - Mallard Creek Apts | F121: A | G121: Ezee Fiber Texas, LLC | H121: 45748 | I121: 46203 | J121: BIDC
A122: EZEEFNSC2024O116 | B122: NSC--Ezee Fiber Proposal Work | C122: 2445020 | D122: =VLOOKUP(C122,'[1]SAP Contract #s'!A:B,2,FALSE) -> 21443 | E122: Ezee Fiber Texas-Arbors on Westheimer | F122: A | G122: Ezee Fiber Texas, LLC | H122: 45827 | I122: 46203 | J122: BIDC
A123: EZEEFNSC2024O116 | B123: NSC--Ezee Fiber Proposal Work | C123: 2445025 | D123: 21906 | E123: Ezee - San Antigua | F123: A | G123: Ezee Fiber Texas, LLC | H123: 46076 | I123: 46441 | J123: BIDC
A124: FRONTNSC2015O172 | B124: NSC--Frontier CSA 12-30-15 | C124: 1056196 | D124: =VLOOKUP(C124,'[1]SAP Contract #s'!A:B,2,FALSE) -> 21075 | E124: Frontier - Middle Mile Segment (Fire) | F124: A | G124: Citizens Telecom Services Company LLC | H124: 45862 | I124: 46203 | J124: BIDC
A125: FRONTNSC2015O172 | B125: NSC--Frontier CSA 12-30-15 | C125: 1056197 | D125: =VLOOKUP(C125,'[1]SAP Contract #s'!A:B,2,FALSE) -> 21082 | E125: Frontier - Hwy 172 to Mill Crk Re (Fire) | F125: A | G125: Citizens Telecom Services Company LLC | H125: 45862 | I125: 46203 | J125: BIDC
A126: FRONTNSC2015O172 | B126: NSC--Frontier CSA 12-30-15 | C126: 1056195 | D126: =VLOOKUP(C126,'[1]SAP Contract #s'!A:B,2,FALSE) -> 21490 | E126: Frontier - End of MM at Hwy 36 (Fire) | F126: A | G126: Citizens Telecom Services Company LLC | H126: 45862 | I126: 46203 | J126: BIDC
A127: FTRCQGSU2015O010 | B127: Frontier CSA 12-31-15 | C127: 1056136 | D127: =VLOOKUP(C127,'[1]SAP Contract #s'!A:B,2,FALSE) -> 21172 | E127: Frontier - Maint SSP Valley (2025-27) | F127: A | G127: Citizens Telecom Services Company LLC | H127: 45809 | I127: 46538 | J127: TCMS
A128: FTRCQGSU2015O010 | B128: Frontier CSA 12-31-15 | C128: 2052069 | D128: =VLOOKUP(C128,'[1]SAP Contract #s'!A:B,2,FALSE) -> 21174 | E128: Frontier - Maint SSP Selma (2022-25) | F128: A | G128: Citizens Telecom Services Company LLC | H128: 44713 | I128: 45808 | J128: TCMS
A129: FTRCQGSU2015O010 | B129: Frontier CSA 12-31-15 | C129: 1252080 | D129: =VLOOKUP(C129,'[1]SAP Contract #s'!A:B,2,FALSE) -> 21178 | E129: Frontier - FTTH Northern CA Communities | F129: A | G129: Citizens Telecom Services Company LLC | H129: 45334 | I129: 46387 | J129: TCMS
A130: FTRCQGSU2015O010 | B130: Frontier CSA 12-31-15 | C130: 1056143 | D130: =VLOOKUP(C130,'[1]SAP Contract #s'!A:B,2,FALSE) -> 21541 | E130: Frontier - Maint SSP South Bay (2025-27) | F130: A | G130: Citizens Telecom Services Company LLC | H130: 45809 | I130: 46538 | J130: TCMS
A131: FTRCQGSU2015O010 | B131: Frontier CSA 12-31-15 | C131: 1252046 | D131: =VLOOKUP(C131,'[1]SAP Contract #s'!A:B,2,FALSE) -> 21583 | E131: Frontier - FTTH Elk Grove | F131: A | G131: Citizens Telecom Services Company LLC | H131: 44470 | I131: 46387 | J131: TCMS
A132: FTRCQGSU2015O010 | B132: Frontier CSA 12-31-15 | C132: 1252077 | D132: =VLOOKUP(C132,'[1]SAP Contract #s'!A:B,2,FALSE) -> 21596 | E132: Frontier - FTTH Morgan Hill | F132: A | G132: Citizens Telecom Services Company LLC | H132: 44774 | I132: 46387 | J132: TCMS
A133: FTRCQGSU2015O010 | B133: Frontier CSA 12-31-15 | C133: 1252078 | D133: =VLOOKUP(C133,'[1]SAP Contract #s'!A:B,2,FALSE) -> 21614 | E133: Frontier - FTTH Redding | F133: A | G133: Citizens Telecom Services Company LLC | H133: 45852 | I133: 46387 | J133: TCMS
A134: FTRCQGSU2015O010 | B134: Frontier CSA 12-31-15 | C134: 1252081 | D134: =VLOOKUP(C134,'[1]SAP Contract #s'!A:B,2,FALSE) -> 21620 | E134: Frontier - FTTH Susanville | F134: A | G134: Citizens Telecom Services Company LLC | H134: 45590 | I134: 46387 | J134: TCMS
A135: FTRCQGSU2015O010 | B135: Frontier CSA 12-31-15 | C135: 1252082 | D135: =VLOOKUP(C135,'[1]SAP Contract #s'!A:B,2,FALSE) -> 21622 | E135: Frontier - FTTH - Kenwood | F135: A | G135: Citizens Telecom Services Company LLC | H135: 45943 | I135: 46387 | J135: TCMS
... A137: FTRCQGSU2015O010 | B137: Frontier CSA 12-31-15 | C137: 2052070 | D137: =VLOOKUP(C137,'[1]SAP Contract #s'!A:B,2,FALSE) -> 21681 | E137: Frontier - Maint SSP South Bay (2022-25) | F137: A | G137: Citizens Telecom Services Company LLC | H137: 44713 | I137: 45808 | J137: TCMS
A138: FTRCQGSU2015O010 | B138: Frontier CSA 12-31-15 | C138: 1252079 | D138: 21895 | E138: Frontier - FTTH - Bishop, Mammoth, June | F138: A | G138: Citizens Telecom Services Company LLC | H138: 46069 | I138: 46752 | J138: TCMS
A139: GOOGLNSC2022O061 | B139: MDU Installation | C139: 2445099 | D139: =VLOOKUP(C139,'[1]SAP Contract #s'!A:B,2,FALSE) -> 21129 | E139: Google-Fiber Greenfield TX | F139: A | G139: Google Fiber Inc | H139: 45611 | I139: 45989 | J139: TCMS
A140: GOOGLNSC2022O061 | B140: MDU Installation | C140: 2065000 | D140: =VLOOKUP(C140,'[1]SAP Contract #s'!A:B,2,FALSE) -> 21247 | E140: Google-Fiber FTTH MDU CO | F140: A | G140: Google Fiber Inc | H140: 45630 | I140: 46341 | J140: TCMS
A141: GOOGLNSC2022O061 | B141: MDU Installation | C141: 2443000 | D141: =VLOOKUP(C141,'[1]SAP Contract #s'!A:B,2,FALSE) -> 21595 | E141: Google-Google Fiber MSA (TX) | F141: A | G141: Google Fiber Inc | H141: 44839 | I141: 46354 | J141: TCMS
A142: GOOGLNSC2022O061 | B142: MDU Installation | C142: 2065002 | D142: =VLOOKUP(C142,'[1]SAP Contract #s'!A:B,2,FALSE) -> 21628 | E142: Google-Fiber FTTH Greenfields CO | F142: A | G142: Google Fiber Inc | H142: 45689 | I142: 46341 | J142: TCMS
A143: GOOGLNSC2022O061 | B143: MDU Installation | C143: 2065003 | D143: =VLOOKUP(C143,'[1]SAP Contract #s'!A:B,2,FALSE) -> 21635 | E143: Google Fiber FTTH Installations | F143: A | G143: Google Fiber Inc | H143: 45940 | I143: 46341 | J143: TCMS
A144: GOOGLNSC2022O061 | B144: MDU Installation | C144: 2036000 | D144: =VLOOKUP(C144,'[1]SAP Contract #s'!A:B,2,FALSE) -> 21672 | E144: Google-Google Fiber MSA (AZ) | F144: A | G144: Google Fiber Inc | H144: 45996 | I144: 46691 | J144: TCMS
A145: HUNTENSC2025O178 | B145: NSC--Hunter Contract Agmt 09.23.25 | C145: 2386011 | D145: =VLOOKUP(C145,'[1]SAP Contract #s'!A:B,2,FALSE) -> 21406 | E145: Hunter Communications & Technologies, LL | F145: A | G145: Hunter Communications & Technologies | H145: 45925 | I145: 46290 | J145: TCMS
A146: IDAHONSC2025O179 | B146: NSC--Idaho County DIGB 2 Fiber | C146: 1136235 | D146: =VLOOKUP(C146,'[1]SAP Contract #s'!A:B,2,FALSE) -> 21558 | E146: Idaho County - DIGB2 Phase II - Np - Grv | F146: A | G146: Idaho County | H146: 45929 | I146: 46234 | J146: BIDC
A147: JEPUDNSC2024O109 | B147: NSC--Jefferson PUD Olympic Fiber Build | C147: 1485141 | D147: =VLOOKUP(C147,'[1]SAP Contract #s'!A:B,2,FALSE) -> 21143 | E147: Jefferson PUD-Olympic Fiber Build | F147: A | G147: Public Utility District No. 1 of Jefferson County | H147: 45362 | I147: 45961 | J147: BIDC
A148: LUMENGSU2022026 | B148: Lumen CENCAL Enterprise | C148: 1056168 | D148: =VLOOKUP(C148,'[1]SAP Contract #s'!A:B,2,FALSE) -> 21045 | E148: Lumen - Bakersfield to Delano II - Splic | F148: A | G148: Lumen Technologies Service Group, LLC | H148: 45852 | I148: 45869 | J148: BIDC
A149: LUMENGSU2022026 | B149: Lumen CENCAL Enterprise | C149: 1056219 | D149: =VLOOKUP(C149,'[1]SAP Contract #s'!A:B,2,FALSE) -> 21454 | E149: Lumen - Road 66 - Splicing | F149: A | G149: Lumen Technologies Service Group, LLC | H149: 45908 | I149: 46112 | J149: BIDC
A150: LUMENGSU2022026 | B150: Lumen CENCAL Enterprise | C150: 1056142 | D150: =VLOOKUP(C150,'[1]SAP Contract #s'!A:B,2,FALSE) -> 21497 | E150: Lumen - Hanford Walmart | F150: A | G150: Lumen Technologies Service Group, LLC | H150: 45789 | I150: 46387 | J150: BIDC
... A160: LUMENGSU2024O099 | B160: GSU--COCAL (2025-26) | C160: 1056241 | D160: =VLOOKUP(C160,'[1]SAP Contract #s'!A:B,2,FALSE) -> 21543 | E160: Lumen - Main & Harrison - San Francisco | F160: A | G160: Lumen Technologies Service Group, LLC | H160: 45943 | I160: 46112 | J160: BIDC
...

Sheet Sheet1
A1: Projects in Unbilled Aging | B1: Vlookup | F1: Projects in MR | G1: Status
A2: 1055210 | B2: =VLOOKUP($A2,$F$2:$G$216,2,FALSE) -> In MR | F2: 011101 | G2: In MR
A3: 1056117 | B3: =VLOOKUP($A3,$F$2:$G$216,2,FALSE) -> In MR | F3: 1055210 | G3: In MR
A4: 1056119 | B4: =VLOOKUP($A4,$F$2:$G$216,2,FALSE) -> In MR | F4: 1056117 | G4: In MR
A5: 1056129 | B5: =VLOOKUP($A5,$F$2:$G$216,2,FALSE) -> In MR | F5: 1056119 | G5: In MR
A6: 1056130 | B6: =VLOOKUP($A6,$F$2:$G$216,2,FALSE) -> In MR | F6: 1056129 | G6: In MR
A7: 1056131 | B7: =VLOOKUP($A7,$F$2:$G$216,2,FALSE) -> In MR | F7: 1056130 | G7: In MR
A8: 1056133 | B8: =VLOOKUP($A8,$F$2:$G$216,2,FALSE) -> In MR | F8: 1056131 | G8: In MR
A9: 1056134 | B9: =VLOOKUP($A9,$F$2:$G$216,2,FALSE) -> In MR | F9: 1056133 | G9: In MR
A10: 1056136 | B10: =VLOOKUP($A10,$F$2:$G$216,2,FALSE) -> In MR | F10: 1056134 | G10: In MR
A11: 1056140 | B11: =VLOOKUP($A11,$F$2:$G$216,2,FALSE) -> In MR | F11: 1056136 | G11: In MR
A12: 1056141 | B12: =VLOOKUP($A12,$F$2:$G$216,2,FALSE) -> In MR | F12: 1056140 | G12: In MR
A13: 1056143 | B13: =VLOOKUP($A13,$F$2:$G$216,2,FALSE) -> In MR | F13: 1056141 | G13: In MR
... A154: 148704401 | B154: =VLOOKUP($A154,$F$2:$G$216,2,FALSE) -> In MR | F154: 2136006 | G154: In MR
F155: 2136007 | G155: In MR
F156: 2136008 | G156: In MR
F157: 2136010 | G157: In MR
F158: 2136011 | G158: In MR
F159: 2156000 | G159: In MR
F160: 2180000 | G160: In MR
F161: 2344000 | G161: In MR
F162: 2383011 | G162: In MR
F163: 2384101 | G163: In MR
F164: 2384111 | G164: In MR
F165: 2385000 | G165: In MR
F166: 2385009 | G166: In MR
... F216: 148704401 | G216: In MR
